Workbook
Name skill_names: skill_list!$A$1:$A$166

Sheet README
A1: SEAGAS gold annotation - annotator B
A2: Read the JD, then go down to the table and add one row per skill (skill_name, importance, evidence_text). keep can stay empty; N removes a row.
A3: Follow data/jd_dataset/gold/ANNOTATION_GUIDE.md (what counts as a skill, importance cues).
A4: skill_name: pick a canonical name from the drop-down, or type NEW: <term> (click Yes on the warning).
A5: evidence_text: copy the shortest phrase from the JD text. End it with ? if unsure about importance.
A6: One row per skill per JD. Do not rename sheets or move the table header.
A7: Label on your own: do not look at the draft, annotator A's workbook or gold_labels.csv.
A9: jd_ref | B9: role | C9: title | D9: keep = Y | E9: rows
A10: JD-CE-0001 | B10: CLOUD_ENGINEER | C10: IT Infra & Cloud Intern | D10: =COUNTIF('JD-CE-0001'!$D$34:$D$63,"Y") | E10: =COUNTA('JD-CE-0001'!$A$34:$A$63)
A11: JD-CE-0002 | B11: CLOUD_ENGINEER | C11: Internship - Cloud Infrastructure End User Computing | D11: =COUNTIF('JD-CE-0002'!$D$26:$D$55,"Y") | E11: =COUNTA('JD-CE-0002'!$A$26:$A$55)
A12: JD-CY-0004 | B12: CYBER_ANALYST | C12: Junior Incident Responder, Malaysia | D12: =COUNTIF('JD-CY-0004'!$D$52:$D$81,"Y") | E12: =COUNTA('JD-CY-0004'!$A$52:$A$81)
A13: JD-CY-0005 | B13: CYBER_ANALYST | C13: L1 Security Analyst | D13: =COUNTIF('JD-CY-0005'!$D$32:$D$61,"Y") | E13: =COUNTA('JD-CY-0005'!$A$32:$A$61)
A14: JD-DA-0003 | B14: DATA_ANALYST | C14: Data Analyst (Fresh Graduate) | D14: =COUNTIF('JD-DA-0003'!$D$34:$D$63,"Y") | E14: =COUNTA('JD-DA-0003'!$A$34:$A$63)
A15: JD-DA-0004 | B15: DATA_ANALYST | C15: Data Analyst Intern | D15: =COUNTIF('JD-DA-0004'!$D$29:$D$58,"Y") | E15: =COUNTA('JD-DA-0004'!$A$29:$A$58)
A16: JD-DS-0002 | B16: DATA_SCIENTIST | C16: Data Science & AI Internship | D16: =COUNTIF('JD-DS-0002'!$D$33:$D$62,"Y") | E16: =COUNTA('JD-DS-0002'!$A$33:$A$62)
A17: JD-DS-0009 | B17: DATA_SCIENTIST | C17: Associate Engineer, Data Science | D17: =COUNTIF('JD-DS-0009'!$D$29:$D$58,"Y") | E17: =COUNTA('JD-DS-0009'!$A$29:$A$58)
A18: JD-SD-0003 | B18: SOFTWARE_DEV | C18: Software Engineer (Internship) | D18: =COUNTIF('JD-SD-0003'!$D$25:$D$54,"Y") | E18: =COUNTA('JD-SD-0003'!$A$25:$A$54)
A19: JD-SD-0009 | B19: SOFTWARE_DEV | C19: Java Developer Intern | D19: =COUNTIF('JD-SD-0009'!$D$37:$D$66,"Y") | E19: =COUNTA('JD-SD-0009'!$A$37:$A$66)
A20: JD-WD-0001 | B20: WEB_DEV | C20: Interns - Software Developer | D20: =COUNTIF('JD-WD-0001'!$D$28:$D$57,"Y") | E20: =COUNTA('JD-WD-0001'!$A$28:$A$57)
A21: JD-WD-0011 | B21: WEB_DEV | C21: Junior PHP Web Developer | D21: =COUNTIF('JD-WD-0011'!$D$26:$D$55,"Y") | E21: =COUNTA('JD-WD-0011'!$A$26:$A$55)

Sheet JD-CE-0001
A1: JD-CE-0001 | CLOUD_ENGINEER | IT Infra & Cloud Intern (entry)
A2: Read the JD, then go down to the table and add one row per skill (skill_name, importance, evidence_text). keep can stay empty; N removes a row.
A3: Go to the label table
A4: Job description
A5: About the role
A7: This is an infrastructure support role assisting the Infrastructure team with IT infrastructure setup, configuration, monitoring and troubleshooting. You will support Microsoft Azure infrastructure activities, including virtual machines, virtual networks, storage and resource monitoring, under the guidance of senior engineers.
A9: Key responsibilities
A11: * Assist the Infrastructure team with basic IT infrastructure setup, configuration, monitoring and troubleshooting
A12: * Support Microsoft Azure infrastructure activities, including virtual machines, virtual networks, storage and resource monitoring, under the guidance of senior engineers
A13: * Assist with network troubleshooting, including IP addressing, DNS, connectivity and basic routing concepts
A14: * Support Windows Server and/or Linux system administration tasks
A15: * Assist in monitoring infrastructure performance, reviewing alerts and documenting incidents
... A31: * Good communication skills and attention to detail
A33: skill_name | B33: importance | C33: evidence_text | D33: keep | E33: note
A34: Azure | B34: required | C34: Support Microsoft Azure infrastructure activities | D34: Y
A35: Cloud Computing | B35: bonus | C35: Basic knowledge of Microsoft Azure or other cloud platforms is an added advantage | D35: Y
A36: Networking | B36: required | C36: Assist with network troubleshooting, including IP addressing, DNS, connectivity and basic routing concepts | D36: Y
A37: Windows Server | B37: required | C37: Support Windows Server and/or Linux system administration tasks | D37: Y
A38: Linux | B38: required | C38: Windows Server and/or Linux system administration tasks | D38: Y
A39: Monitoring & Observability | B39: required | C39: Assist in monitoring infrastructure performance, reviewing alerts | D39: Y
A40: Documentation | B40: required | C40: Prepare and maintain technical documentation | D40: Y
A41: Identity & Access Management | B41: preferred | C41: Learn and follow IT security practices, access control procedures? | D41: Y
A42: PowerShell | B42: bonus | C42: Familiarity with PowerShell, Bash, scripting or infrastructure monitoring tools is a plus | D42: Y
A43: Bash | B43: bonus | C43: Familiarity with PowerShell, Bash, scripting or infrastructure monitoring tools is a plus | D43: Y
A44: Problem Solving | B44: required | C44: Good analytical and problem-solving skills | D44: Y
A45: Teamwork | B45: required | C45: work collaboratively with the technical team | D45: Y
... A47: Attention to Detail | B47: required | C47: attention to detail | D47: Y

Sheet JD-CE-0002
A1: JD-CE-0002 | CLOUD_ENGINEER | Internship - Cloud Infrastructure End User Computing (entry)
A2: Read the JD, then go down to the table and add one row per skill (skill_name, importance, evidence_text). keep can stay empty; N removes a row.
A3: Go to the label table
A4: Job description
A5: Responsibilities
A7: * Provide first-level technical support for hardware, software and network issues, ensuring prompt resolution and positive user experience.
A8: * Diagnosing and resolving IT incidents in line with organizational standards and best practices.
A9: * Support daily operations through IT asset management, inventory tracking and administration of hardware, software and infrastructure components.
A10: * Maintain accurate and up-to-date documentation of IT systems, configurations, processes and procedures to support transparency and knowledge sharing.
A11: * Assist in designing, developing and implementing new or improved systems and workflows to enhance operational efficiency.
A12: * Process and track IT-related invoices, telecommunications bills, software subscriptions, maintenance contracts and supporting records.
A13: * Support the testing and validation of new systems, applications and technologies to ensure quality and business alignment.
... A23: * Familiarity with public cloud platforms (AWS, Azure, GCP), UiPath (RPA) and programming or database technologies such as SQL is an advantage.
A25: skill_name | B25: importance | C25: evidence_text | D25: keep | E25: note
A26: NEW: Technical Support | B26: required | C26: Provide first-level technical support for hardware, software and network issues | D26: Y
A27: NEW: IT Asset Management | B27: required | C27: IT asset management, inventory tracking | D27: Y
A28: Documentation | B28: required | C28: Maintain accurate and up-to-date documentation of IT systems | D28: Y
A29: Generative AI | B29: required | C29: introduce emerging technologies and solutions, including Generative AI | D29: Y
A30: Communication | B30: required | C30: Strong communication and interpersonal abilities. | D30: Y
A31: Interpersonal Skills | B31: required | C31: Strong communication and interpersonal abilities. | D31: Y
A32: Time Management | B32: required | C32: Effective time management | D32: Y
A33: Problem Solving | B33: required | C33: problem-solving skills | D33: Y
A34: Teamwork | B34: required | C34: Enjoy collaborating with individuals from diverse backgrounds | D34: Y
A35: Self-Motivation | B35: required | C35: Self-motivated | D35: Y
A36: NEW: Microsoft 365 | B36: required | C36: Proficient in Microsoft technologies, including Microsoft 365 | D36: Y
A37: NEW: Microsoft Copilot | B37: required | C37: Microsoft Copilot | D37: Y
... A44: SQL | B44: bonus | C44: database technologies such as SQL is an advantage | D44: Y

Sheet JD-CY-0004
A1: JD-CY-0004 | CYBER_ANALYST | Junior Incident Responder, Malaysia (junior)
A2: Read the JD, then go down to the table and add one row per skill (skill_name, importance, evidence_text). keep can stay empty; N removes a row.
A3: Go to the label table
A4: Job description
A5: Your Mission: Junior Incident Responder
A7: As a Junior Incident Responder, you will work alongside senior responders on live engagements — helping clients contain, investigate, and recover from real cyber attacks. This is a delivery-focused role: your job is to do the work, learn the craft, and grow into a fully fledged responder under direct mentorship.
A8: We hire for attitude and aptitude. We don't expect you to have seen everything yet — we expect you to be curious, coachable, and serious about building a career in incident response. The right candidate can demonstrate a genuine interest in IR through their experience, side projects, study, or community involvement, and shows up ready to learn fast in a real-world environment.
A10: Core Responsibilities
A12: Delivery Alongside Senior Responders
A14: * Support senior consultants on active incidents — assisting with containment, evidence collection, forensic analysis, and reporting.
A15: * Acquire and triage forensic artifacts across Windows, Linux, macOS, and cloud environments under the guidance of more experienced team members.
A16: * Analyse logs, endpoint telemetry, network data, and malware artifacts, and contribute findings to investigation timelines.
... A49: Perks and benefits: Paired with senior responders from day one; Hands-on mentorship and structured instructor-led training program
A51: skill_name | B51: importance | C51: evidence_text | D51: keep | E51: note
A52: Incident Response | B52: required | C52: assisting with containment, evidence collection, forensic analysis, and reporting | D52: Y
A53: Digital Forensics | B53: required | C53: Acquire and triage forensic artifacts | D53: Y
A54: Linux | B54: required | C54: Acquire and triage forensic artifacts across Windows, Linux, macOS, and cloud environments | D54: Y
A55: NEW: Windows | B55: required | C55: Acquire and triage forensic artifacts across Windows, Linux, macOS, and cloud environments | D55: Y
A56: NEW: macOS | B56: required | C56: Acquire and triage forensic artifacts across Windows, Linux, macOS, and cloud environments | D56: Y
A57: Cloud Computing | B57: required | C57: Windows, Linux, macOS, and cloud environments | D57: Y
A58: Log Analysis | B58: required | C58: Analyse logs, endpoint telemetry, network data | D58: Y
A59: Malware Analysis | B59: required | C59: malware artifacts | D59: Y
A60: Python | B60: required | C60: Basic scripting ability in Python, Bash, or PowerShell | D60: Y
A61: Bash | B61: required | C61: Basic scripting ability in Python, Bash, or PowerShell | D61: Y
A62: PowerShell | B62: required | C62: Basic scripting ability in Python, Bash, or PowerShell | D62: Y
A63: Documentation | B63: required | C63: Document findings clearly and accurately | D63: Y
... A67: SIEM | B67: preferred | C67: Hands-on exposure to EDR, SIEM, or forensic tooling | D67: Y

Sheet JD-CY-0005
A1: JD-CY-0005 | CYBER_ANALYST | L1 Security Analyst (junior)
A2: Read the JD, then go down to the table and add one row per skill (skill_name, importance, evidence_text). keep can stay empty; N removes a row.
A3: Go to the label table
A4: Job description
A5: Key Responsibilities
A7: * Monitor security alerts and logs from various security tools such as SIEM (Security Information and Event Management) systems, firewalls, antivirus, and intrusion detection/prevention systems.
A8: * Investigate and analyze potential security incidents or breaches and escalate as necessary to senior analysts or incident response teams.
A9: * Perform routine security assessments and vulnerability scans to identify and report risks.
A10: * Assist in maintaining and updating security documentation, policies, and procedures.
A11: * Participate in security awareness training programs for employees.
A12: * Support compliance efforts with relevant regulations and standards (e.g., GDPR, HIPAA, PCI-DSS).
A13: * Collaborate with IT teams to implement security controls and mitigate identified risks.
... A29: Perks and benefits: Medical; Miscellaneous allowance; Dental; Sports (e.g. Gym); Parking
A31: skill_name | B31: importance | C31: evidence_text | D31: keep | E31: note
A32: SIEM | B32: required | C32: Monitor security alerts and logs from various security tools such as SIEM | D32: Y
A33: Log Analysis | B33: required | C33: Monitor security alerts and logs | D33: Y
A34: Firewall Management | B34: required | C34: firewalls | D34: Y
A35: NEW: Intrusion Detection/Prevention | B35: required | C35: intrusion detection/prevention systems | D35: Y
A36: NEW: Antivirus | B36: required | C36: antivirus | D36: Y
A37: Incident Response | B37: required | C37: Investigate and analyze potential security incidents | D37: Y
A38: Vulnerability Assessment | B38: required | C38: Perform routine security assessments and vulnerability scans | D38: Y
A39: Risk Analysis | B39: required | C39: identify and report risks | D39: Y
A40: Documentation | B40: required | C40: maintaining and updating security documentation, policies, and procedures | D40: Y
A41: Security Frameworks | B41: required | C41: Support compliance efforts with relevant regulations and standards (e.g., GDPR, HIPAA, PCI-DSS) | D41: Y
A42: Teamwork | B42: required | C42: Collaborate with IT teams | D42: Y
A43: Networking | B43: required | C43: Basic understanding of network protocols | D43: Y
... A47: Communication | B47: required | C47: Good communication skills | D47: Y

Sheet JD-DA-0003
A1: JD-DA-0003 | DATA_ANALYST | Data Analyst (Fresh Graduate) (junior)
A2: Read the JD, then go down to the table and add one row per skill (skill_name, importance, evidence_text). keep can stay empty; N removes a row.
A3: Go to the label table
A4: Job description
A5: Graduate With a Degree. Leave With Real Data Experience.
A6: Your first job can be more than an entry-level title.
A7: Start your career working with real data, real business problems, modern AI tools, and experienced mentors — while building the technical skills companies actually look for in data professionals.
A8: Fresh graduates are welcome. No years of experience required. If you know SQL, understand data, and have the curiosity to keep learning, we'll help you take the next step.
A10: Key responsibilities
A12: * Data Extraction & Wrangling — write efficient SQL queries across our cloud data warehouse (Google BigQuery) to extract, validate, and transform multi-source business data.
A13: * Exploratory & Diagnostic Analysis — investigate operational workflows, transaction lifecycles, and unit economics to diagnose root causes and identify optimization opportunities.
A14: * Reporting & Visualisation — build and maintain clean data reports, performance tracking scorecards, and interactive dashboards to monitor key operational and financial metrics.
... A31: Perks and benefits: Medical Coverage; Well-being Benefit; Group Insurance Coverage; Learning & Development
A33: skill_name | B33: importance | C33: evidence_text | D33: keep | E33: note
A34: SQL | B34: required | C34: Strong SQL fundamentals | D34: Y
A35: NEW: Google BigQuery | B35: required | C35: Google BigQuery | D35: Y
A36: Data Warehousing | B36: required | C36: cloud data warehouse | D36: Y
A37: ETL | B37: required | C37: extract, validate, and transform multi-source business data | D37: Y
A38: Data Cleaning | B38: required | C38: data hygiene checks | D38: Y
A39: Data Analysis | B39: required | C39: Basic understanding of data analysis | D39: Y
A40: Statistical Analysis | B40: required | C40: data analysis, statistics, and data visualisation | D40: Y
A41: Data Visualisation | B41: required | C41: interactive dashboards | D41: Y
A42: Stakeholder Communication | B42: required | C42: partner with cross-functional teams | D42: Y
A43: Python | B43: required | C43: Foundational Python knowledge | D43: Y
A44: Pandas | B44: preferred | C44: familiarity with Python for data manipulation using tools such as pandas and NumPy | D44: Y
A45: NumPy | B45: preferred | C45: familiarity with Python for data manipulation using tools such as pandas and NumPy | D45: Y
... A50: Communication | B50: required | C50: Good communication skills | D50: Y

Sheet JD-DA-0004
A1: JD-DA-0004 | DATA_ANALYST | Data Analyst Intern (entry)
A2: Read the JD, then go down to the table and add one row per skill (skill_name, importance, evidence_text). keep can stay empty; N removes a row.
A3: Go to the label table
A4: Job description
A5: What you'll do
A7: * Assist in collecting, cleaning, and organising data from various sources.
A8: * Conduct exploratory data analysis to identify trends, patterns, and insights.
A9: * Support the development and maintenance of dashboards and reports for internal stakeholders.
A10: * Collaborate with cross-functional teams to understand data needs and provide analytical solutions.
A11: * Perform data validation and quality checks to ensure accuracy and reliability of data.
A12: * Assist in developing and implementing data-driven strategies to improve business processes.
A13: * Participate in team meetings and contribute to discussions on data analysis and interpretation.
... A26: Perks and benefits: Young collaborative team; Well-stocked pantry
A28: skill_name | B28: importance | C28: evidence_text | D28: keep | E28: note
A29: Data Cleaning | B29: required | C29: collecting, cleaning, and organising data | D29: Y
A30: Data Analysis | B30: required | C30: Conduct exploratory data analysis | D30: Y
A31: Data Visualisation | B31: required | C31: Intermediate experience with SQL and data visualisation tools | D31: Y
A32: Looker | B32: required | C32: data visualisation tools (e.g. Looker Studio) | D32: Y
A33: SQL | B33: required | C33: Intermediate experience with SQL | D33: Y
A34: Excel | B34: required | C34: Proficiency in Microsoft Office suite (Word, Excel, PowerPoint) | D34: Y
A35: NEW: Microsoft Office | B35: required | C35: Proficiency in Microsoft Office suite | D35: Y
A36: Statistical Analysis | B36: bonus | C36: Experience with statistical analysis software (e.g., R, Python) is an advantage | D36: Y
A37: R | B37: bonus | C37: statistical analysis software (e.g., R, Python) is an advantage | D37: Y
A38: Python | B38: bonus | C38: statistical analysis software (e.g., R, Python) is an advantage | D38: Y
A39: Teamwork | B39: required | C39: Collaborate with cross-functional teams | D39: Y
A40: Problem Solving | B40: required | C40: Strong analytical and problem-solving skills | D40: Y
... A43: Interpersonal Skills | B43: required | C43: Excellent communication and interpersonal skills | D43: Y

Sheet JD-DS-0002
A1: JD-DS-0002 | DATA_SCIENTIST | Data Science & AI Internship (entry)
A2: Read the JD, then go down to the table and add one row per skill (skill_name, importance, evidence_text). keep can stay empty; N removes a row.
A3: Go to the label table
A4: Job description
A5: Job Scope
A7: * Assist the team to develop and deploy AI use cases from business users.
A8: * Support the team in research and development (R&D) of features that are part of a larger AI system.
A9: * Assist with data processing, chatbot evaluation, AI model evaluation, and building RPA pipelines.
A10: * Support multiple concurrent tasks and use cases as required by the team.
A12: Contribute to company transformation initiatives through projects such as:
A14: * Building RPA solutions for agency teams.
A15: * Building monitoring dashboards.
... A30: Perks and benefits: Miscellaneous allowance; Monthly Incentive, Free Oversea Convention
A32: skill_name | B32: importance | C32: evidence_text | D32: keep | E32: note
A33: NEW: RPA | B33: required | C33: building RPA pipelines | D33: Y
A34: Model Evaluation | B34: required | C34: AI model evaluation | D34: Y
A35: Data Visualisation | B35: required | C35: Building monitoring dashboards | D35: Y
A36: NEW: Data Labelling | B36: required | C36: Helping build labelled datasets for model evaluation | D36: Y
A37: Python | B37: preferred | C37: Python coding | D37: Y
A38: Cloud Computing | B38: preferred | C38: Cloud infrastructure | D38: Y
A39: SQL | B39: preferred | C39: SQL querying | D39: Y
A40: Data Cleaning | B40: preferred | C40: Data manipulation tasks? | D40: Y

Sheet JD-DS-0009
A1: JD-DS-0009 | DATA_SCIENTIST | Associate Engineer, Data Science (junior)
A2: Read the JD, then go down to the table and add one row per skill (skill_name, importance, evidence_text). keep can stay empty; N removes a row.
A3: Go to the label table
A4: Job description
A5: About the role
A7: This role builds strong technical foundations across data engineering, analytics, automation and digital transformation. You will work on real-world semiconductor manufacturing and supply-chain problems alongside experienced team members, developing data pipelines, analytical solutions and digital applications.
A9: Key responsibilities
A11: * Support the development and maintenance of data pipelines and data-processing workflows.
A12: * Write and maintain Python and SQL code for data extraction, transformation, validation and analysis.
A13: * Assist with integrating data from databases, APIs, files and enterprise systems.
A14: * Support the development of analytical datasets, dashboards and reports for supply-chain and manufacturing projects.
A15: * Perform data validation, reconciliation and troubleshooting.
... A26: * Academic or personal projects involving Python, SQL, data analytics, APIs or cloud technologies, or exposure to Power BI, Tableau or Git, are advantageous.
A28: skill_name | B28: importance | C28: evidence_text | D28: keep | E28: note
A29: ETL | B29: required | C29: Support the development and maintenance of data pipelines | D29: Y
A30: Python | B30: required | C30: Write and maintain Python and SQL code | D30: Y
A31: SQL | B31: required | C31: Write and maintain Python and SQL code | D31: Y
A32: NEW: Relational Databases | B32: required | C32: Fundamental knowledge of Python, SQL, relational databases | D32: Y
A33: REST API | B33: preferred | C33: integrating data from databases, APIs? | D33: Y
A34: Data Analysis | B34: required | C34: data extraction, transformation, validation and analysis | D34: Y
A35: Data Cleaning | B35: required | C35: Perform data validation, reconciliation and troubleshooting | D35: Y
A36: Data Visualisation | B36: required | C36: dashboards and reports | D36: Y
A37: Documentation | B37: required | C37: Prepare technical documentation | D37: Y
A38: Teamwork | B38: required | C38: collaborate with cross-functional teams | D38: Y
A39: Problem Solving | B39: required | C39: Strong analytical and problem-solving skills | D39: Y
A40: Communication | B40: required | C40: good communication | D40: Y
... A44: Git | B44: bonus | C44: exposure to Power BI, Tableau or Git, are advantageous | D44: Y

Sheet JD-SD-0003
A1: JD-SD-0003 | SOFTWARE_DEV | Software Engineer (Internship) (entry)
A2: Read the JD, then go down to the table and add one row per skill (skill_name, importance, evidence_text). keep can stay empty; N removes a row.
A3: Go to the label table
A4: Job description
A5: We are hiring for our Internship Program! We are looking for enthusiastic problem-solver with an interest in software development to join us to build our next generation system. We only accept candidates who knows how to code.
A7: Job Responsibilities
A9: * Assisting Software Engineers to develop in HTML, CSS, Javascript, ASP.net & C#
A10: * Involve in whole Software Development Life Cycle (SDLC)
A11: * Maintain good documentation and maintenance practice
A13: Who we need
A15: * Current or Graduating student taking Computer Science or Computer Engineering.
A16: * Passion in software development!
... A22: Perks and benefits: Highly competitive compensation; Skilled programmer as mentor; Opportunity to convert to full-time role; 5-day work week; Flexible work environment; Fully stocked refreshments
A24: skill_name | B24: importance | C24: evidence_text | D24: keep | E24: note
A25: HTML | B25: required | C25: develop in HTML, CSS, Javascript, ASP.net & C# | D25: Y
A26: CSS | B26: required | C26: develop in HTML, CSS, Javascript, ASP.net & C# | D26: Y
A27: JavaScript | B27: required | C27: develop in HTML, CSS, Javascript, ASP.net & C# | D27: Y
A28: NEW: ASP.NET | B28: required | C28: develop in HTML, CSS, Javascript, ASP.net & C# | D28: Y
A29: C# | B29: required | C29: develop in HTML, CSS, Javascript, ASP.net & C# | D29: Y
A30: NEW: SDLC | B30: required | C30: Involve in whole Software Development Life Cycle (SDLC) | D30: Y
A31: Documentation | B31: required | C31: Maintain good documentation | D31: Y
A32: Problem Solving | B32: required | C32: enthusiastic problem-solver | D32: Y
A33: Critical Thinking | B33: required | C33: Good logical thinking | D33: Y

Sheet JD-SD-0009
A1: JD-SD-0009 | SOFTWARE_DEV | Java Developer Intern (entry)
A2: Read the JD, then go down to the table and add one row per skill (skill_name, importance, evidence_text). keep can stay empty; N removes a row.
A3: Go to the label table
A4: Job description
A5: About the Role
A7: We are looking for a passionate and driven Java Developer Intern to join our growing engineering team. This is a hands-on internship where you'll work alongside experienced developers on real-world projects.
A8: Whether you're a final-year student or a fresh graduate eager to kickstart your tech career in Southeast Asia's thriving tech ecosystem, we'd love to hear from you!
A10: Duration & Start Date
A12: * Duration: 4–8 months
A13: * Start Date: 2026 July
A14: * Commitment: Full-time (Mon–Fri)
A16: What You'll Do
... A34: Perks and benefits: Mentorship from senior engineers; Real project ownership with code shipped to production; Certificate of completion and potential full-time conversion upon graduation
A36: skill_name | B36: importance | C36: evidence_text | D36: keep | E36: note
A37: Java | B37: required | C37: Solid foundational knowledge of Java | D37: Y
A38: NEW: Backend Development | B38: required | C38: Java-based backend services and APIs | D38: Y
A39: REST API | B39: preferred | C39: Java-based backend services and APIs? | D39: Y
A40: NEW: SDLC | B40: required | C40: Participate in the full software development lifecycle | D40: Y
A41: Documentation | B41: required | C41: well-documented code | D41: Y
A42: Agile / Scrum | B42: required | C42: in an Agile environment | D42: Y
A43: Teamwork | B43: required | C43: Collaborate with cross-functional teams (PM, QA, DevOps) | D43: Y
A44: NEW: Debugging | B44: required | C44: Debug and troubleshoot application issues | D44: Y
A45: CI/CD | B45: required | C45: CI/CD pipelines | D45: Y
A46: Spring Boot | B46: preferred | C46: Familiarity with Spring Boot | D46: Y
A47: SQL | B47: required | C47: Basic understanding of SQL / relational databases | D47: Y
A48: NEW: Relational Databases | B48: required | C48: Basic understanding of SQL / relational databases | D48: Y
A49: Problem Solving | B49: required | C49: Good problem-solving mindset | D49: Y

Sheet JD-WD-0001
A1: JD-WD-0001 | WEB_DEV | Interns - Software Developer (entry)
A2: Read the JD, then go down to the table and add one row per skill (skill_name, importance, evidence_text). keep can stay empty; N removes a row.
A3: Go to the label table
A4: Job description
A5: We welcome interns! Join [COMPANY] and gain practical skills and real-world experience in software development. We provide guidance and training to help you grow as a developer.
A7: What you'll learn
A9: You'll gain hands-on experience by working together with software development team to support ongoing projects:
A11: * Assist in the development and enhancement of software applications.
A12: * Assist in preparing software and product documentation.
A13: * Perform testing and debugging to identify and resolve software issues.
A14: * Assist in troubleshooting and modifying existing applications when required.
A16: What you'll need
... A25: Perks and benefits: Hands-on experience with real projects; Mentorship from experienced developers; Opportunity to grow into a full-time role (based on performance)
A27: skill_name | B27: importance | C27: evidence_text | D27: keep | E27: note
A28: Java | B28: required | C28: Basic knowledge in programming languages such as Java and JavaScript | D28: Y
A29: JavaScript | B29: required | C29: Basic knowledge in programming languages such as Java and JavaScript | D29: Y
A30: Vue.js | B30: required | C30: Vue.js ecosystem | D30: Y
A31: NEW: Tailwind CSS | B31: required | C31: UI styling with Tailwind CSS | D31: Y
A32: Documentation | B32: required | C32: preparing software and product documentation | D32: Y
A33: NEW: Software Testing | B33: required | C33: Perform testing and debugging | D33: Y
A34: NEW: Debugging | B34: required | C34: Perform testing and debugging | D34: Y
A35: Problem Solving | B35: required | C35: strong analytical and problem-solving skills | D35: Y
A36: Self-Motivation | B36: required | C36: Self-Driven | D36: Y

Sheet JD-WD-0011
A1: JD-WD-0011 | WEB_DEV | Junior PHP Web Developer (junior)
A2: Read the JD, then go down to the table and add one row per skill (skill_name, importance, evidence_text). keep can stay empty; N removes a row.
A3: Go to the label table
A4: Job description
A5: Are you a passionate developer ready to make an impact? Join our team and help us create innovative web solutions!
A7: Key Responsibilities
A9: * Build and maintain high-quality web applications using PHP, HTML, CSS, and JavaScript.
A10: * Expand and enhance existing backend services to meet application needs.
A11: * Ensure web components are consistent and of high quality across all projects.
A12: * Manage multiple projects simultaneously and deliver projects within deadlines.
A14: Requirements
A16: * Diploma/Advanced/Higher Diploma in Computer Science or a related field.
... A23: Perks and benefits: Exciting projects that enhance your skills; Supportive team where your ideas matter; Hands-on experience in a dynamic environment
A25: skill_name | B25: importance | C25: evidence_text | D25: keep | E25: note
A26: PHP | B26: required | C26: Must Have: PHP, HTML, CSS, JavaScript. | D26: Y
A27: HTML | B27: required | C27: Must Have: PHP, HTML, CSS, JavaScript. | D27: Y
A28: CSS | B28: required | C28: Must Have: PHP, HTML, CSS, JavaScript. | D28: Y
A29: JavaScript | B29: required | C29: Must Have: PHP, HTML, CSS, JavaScript. | D29: Y
A30: NEW: Backend Development | B30: required | C30: Expand and enhance existing backend services | D30: Y
A31: MySQL | B31: required | C31: Experience with MySQL | D31: Y
A32: NEW: Sourcetree | B32: preferred | C32: Familiarity with Sourcetree, Bootstrap, and CodeIgniter Framework | D32: Y
A33: NEW: Bootstrap | B33: preferred | C33: Familiarity with Sourcetree, Bootstrap, and CodeIgniter Framework | D33: Y
A34: NEW: CodeIgniter | B34: preferred | C34: Familiarity with Sourcetree, Bootstrap, and CodeIgniter Framework | D34: Y
A35: Time Management | B35: required | C35: deliver projects within deadlines | D35: Y

Sheet skill_list
A1: A/B Testing
A2: Accounting
A3: Accounting Software
A4: Adaptability
A5: Agile / Scrum
A6: AI Literacy
A7: Angular
A8: Ansible
A9: Apache Spark
A10: Attention to Detail
A11: Auditing
A12: AWS
... A166: Wireshark
