Workbook
Name skill_names: skill_list!$A$1:$A$166

Sheet README
A1: SEAGAS gold annotation - annotator A
A2: Read the JD, then go down to the table. Mark every pre-filled row keep = Y (correct, fix the cells if needed) or N (wrong). Add missing skills on the empty rows with keep = Y. Yellow rows still need a Y or N.
A3: Follow data/jd_dataset/gold/ANNOTATION_GUIDE.md (what counts as a skill, importance cues).
A4: skill_name: pick a canonical name from the drop-down, or type NEW: <term> (click Yes on the warning).
A5: evidence_text: copy the shortest phrase from the JD text. End it with ? if unsure about importance.
A6: One row per skill per JD. Do not rename sheets or move the table header.
A8: jd_ref | B8: role | C8: title | D8: keep = Y | E8: still to review
A9: JD-CE-0001 | B9: CLOUD_ENGINEER | C9: IT Infra & Cloud Intern | D9: =COUNTIF('JD-CE-0001'!$D$34:$D$77,"Y") | E9: =COUNTIFS('JD-CE-0001'!$A$34:$A$77,"<>",'JD-CE-0001'!$D$34:$D$77,"")
A10: JD-CE-0002 | B10: CLOUD_ENGINEER | C10: Internship - Cloud Infrastructure End User Computing | D10: =COUNTIF('JD-CE-0002'!$D$26:$D$65,"Y") | E10: =COUNTIFS('JD-CE-0002'!$A$26:$A$65,"<>",'JD-CE-0002'!$D$26:$D$65,"")
A11: JD-CE-0003 | B11: CLOUD_ENGINEER | C11: Junior Cloud Engineer | D11: =COUNTIF('JD-CE-0003'!$D$76:$D$129,"Y") | E11: =COUNTIFS('JD-CE-0003'!$A$76:$A$129,"<>",'JD-CE-0003'!$D$76:$D$129,"")
A12: JD-CE-0004 | B12: CLOUD_ENGINEER | C12: Junior System Administrator | D12: =COUNTIF('JD-CE-0004'!$D$17:$D$50,"Y") | E12: =COUNTIFS('JD-CE-0004'!$A$17:$A$50,"<>",'JD-CE-0004'!$D$17:$D$50,"")
A13: JD-CE-0005 | B13: CLOUD_ENGINEER | C13: Internship - IT (Cybersecurity & System Administration) | D13: =COUNTIF('JD-CE-0005'!$D$16:$D$46,"Y") | E13: =COUNTIFS('JD-CE-0005'!$A$16:$A$46,"<>",'JD-CE-0005'!$D$16:$D$46,"")
A14: JD-CE-0006 | B14: CLOUD_ENGINEER | C14: Cloud Delivery Support Engineer | D14: =COUNTIF('JD-CE-0006'!$D$37:$D$73,"Y") | E14: =COUNTIFS('JD-CE-0006'!$A$37:$A$73,"<>",'JD-CE-0006'!$D$37:$D$73,"")
A15: JD-CE-0007 | B15: CLOUD_ENGINEER | C15: Specialist - Junior DevOps Engineer | D15: =COUNTIF('JD-CE-0007'!$D$37:$D$71,"Y") | E15: =COUNTIFS('JD-CE-0007'!$A$37:$A$71,"<>",'JD-CE-0007'!$D$37:$D$71,"")
A16: JD-CE-0008 | B16: CLOUD_ENGINEER | C16: Cloud Systems Engineer | D16: =COUNTIF('JD-CE-0008'!$D$51:$D$92,"Y") | E16: =COUNTIFS('JD-CE-0008'!$A$51:$A$92,"<>",'JD-CE-0008'!$D$51:$D$92,"")
A17: JD-CE-0009 | B17: CLOUD_ENGINEER | C17: IT Intern | D17: =COUNTIF('JD-CE-0009'!$D$21:$D$57,"Y") | E17: =COUNTIFS('JD-CE-0009'!$A$21:$A$57,"<>",'JD-CE-0009'!$D$21:$D$57,"")
A18: JD-CE-0010 | B18: CLOUD_ENGINEER | C18: Cloud and IT Operation Intern (2026 Intake) | D18: =COUNTIF('JD-CE-0010'!$D$42:$D$85,"Y") | E18: =COUNTIFS('JD-CE-0010'!$A$42:$A$85,"<>",'JD-CE-0010'!$D$42:$D$85,"")
A19: JD-CY-0001 | B19: CYBER_ANALYST | C19: Internship - Technical Support Engineer | D19: =COUNTIF('JD-CY-0001'!$D$33:$D$66,"Y") | E19: =COUNTIFS('JD-CY-0001'!$A$33:$A$66,"<>",'JD-CY-0001'!$D$33:$D$66,"")
A20: JD-CY-0002 | B20: CYBER_ANALYST | C20: Security Operations Center (SOC) Analyst | D20: =COUNTIF('JD-CY-0002'!$D$49:$D$89,"Y") | E20: =COUNTIFS('JD-CY-0002'!$A$49:$A$89,"<>",'JD-CY-0002'!$D$49:$D$89,"")
A21: JD-CY-0003 | B21: CYBER_ANALYST | C21: PENETRATING TESTING INTERN | D21: =COUNTIF('JD-CY-0003'!$D$26:$D$63,"Y") | E21: =COUNTIFS('JD-CY-0003'!$A$26:$A$63,"<>",'JD-CY-0003'!$D$26:$D$63,"")
A22: JD-CY-0004 | B22: CYBER_ANALYST | C22: Junior Incident Responder, Malaysia | D22: =COUNTIF('JD-CY-0004'!$D$52:$D$88,"Y") | E22: =COUNTIFS('JD-CY-0004'!$A$52:$A$88,"<>",'JD-CY-0004'!$D$52:$D$88,"")
A23: JD-CY-0005 | B23: CYBER_ANALYST | C23: L1 Security Analyst | D23: =COUNTIF('JD-CY-0005'!$D$32:$D$66,"Y") | E23: =COUNTIFS('JD-CY-0005'!$A$32:$A$66,"<>",'JD-CY-0005'!$D$32:$D$66,"")
A24: JD-CY-0006 | B24: CYBER_ANALYST | C24: Junior Cyber Security Analyst | D24: =COUNTIF('JD-CY-0006'!$D$30:$D$64,"Y") | E24: =COUNTIFS('JD-CY-0006'!$A$30:$A$64,"<>",'JD-CY-0006'!$D$30:$D$64,"")
A25: JD-CY-0007 | B25: CYBER_ANALYST | C25: Security Analyst | D25: =COUNTIF('JD-CY-0007'!$D$31:$D$69,"Y") | E25: =COUNTIFS('JD-CY-0007'!$A$31:$A$69,"<>",'JD-CY-0007'!$D$31:$D$69,"")
A26: JD-CY-0008 | B26: CYBER_ANALYST | C26: Internship for Cyber Security Students - RM2,000 for Top Students | D26: =COUNTIF('JD-CY-0008'!$D$22:$D$53,"Y") | E26: =COUNTIFS('JD-CY-0008'!$A$22:$A$53,"<>",'JD-CY-0008'!$D$22:$D$53,"")
A27: JD-CY-0009 | B27: CYBER_ANALYST | C27: IT Intern | D27: =COUNTIF('JD-CY-0009'!$D$30:$D$64,"Y") | E27: =COUNTIFS('JD-CY-0009'!$A$30:$A$64,"<>",'JD-CY-0009'!$D$30:$D$64,"")
A28: JD-CY-0010 | B28: CYBER_ANALYST | C28: Cybersecurity Trainee | D28: =COUNTIF('JD-CY-0010'!$D$27:$D$67,"Y") | E28: =COUNTIFS('JD-CY-0010'!$A$27:$A$67,"<>",'JD-CY-0010'!$D$27:$D$67,"")
A29: JD-DA-0001 | B29: DATA_ANALYST | C29: Business Data Analyst – AI Tools & Growth | D29: =COUNTIF('JD-DA-0001'!$D$35:$D$71,"Y") | E29: =COUNTIFS('JD-DA-0001'!$A$35:$A$71,"<>",'JD-DA-0001'!$D$35:$D$71,"")
A30: JD-DA-0002 | B30: DATA_ANALYST | C30: Digital & Automation Intern | D30: =COUNTIF('JD-DA-0002'!$D$34:$D$70,"Y") | E30: =COUNTIFS('JD-DA-0002'!$A$34:$A$70,"<>",'JD-DA-0002'!$D$34:$D$70,"")
A31: JD-DA-0003 | B31: DATA_ANALYST | C31: Data Analyst (Fresh Graduate) | D31: =COUNTIF('JD-DA-0003'!$D$34:$D$77,"Y") | E31: =COUNTIFS('JD-DA-0003'!$A$34:$A$77,"<>",'JD-DA-0003'!$D$34:$D$77,"")
A32: JD-DA-0004 | B32: DATA_ANALYST | C32: Data Analyst Intern | D32: =COUNTIF('JD-DA-0004'!$D$29:$D$67,"Y") | E32: =COUNTIFS('JD-DA-0004'!$A$29:$A$67,"<>",'JD-DA-0004'!$D$29:$D$67,"")
A33: JD-DA-0005 | B33: DATA_ANALYST | C33: Data Analyst | D33: =COUNTIF('JD-DA-0005'!$D$29:$D$63,"Y") | E33: =COUNTIFS('JD-DA-0005'!$A$29:$A$63,"<>",'JD-DA-0005'!$D$29:$D$63,"")
A34: JD-DA-0006 | B34: DATA_ANALYST | C34: Data Management Assistant | D34: =COUNTIF('JD-DA-0006'!$D$69:$D$109,"Y") | E34: =COUNTIFS('JD-DA-0006'!$A$69:$A$109,"<>",'JD-DA-0006'!$D$69:$D$109,"")
A35: JD-DA-0007 | B35: DATA_ANALYST | C35: DATA ANALYST (INTERNSHIP) | D35: =COUNTIF('JD-DA-0007'!$D$28:$D$60,"Y") | E35: =COUNTIFS('JD-DA-0007'!$A$28:$A$60,"<>",'JD-DA-0007'!$D$28:$D$60,"")
A36: JD-DA-0008 | B36: DATA_ANALYST | C36: Data Analyst (Fresh Graduate Opportunity) | D36: =COUNTIF('JD-DA-0008'!$D$26:$D$65,"Y") | E36: =COUNTIFS('JD-DA-0008'!$A$26:$A$65,"<>",'JD-DA-0008'!$D$26:$D$65,"")
A37: JD-DA-0010 | B37: DATA_ANALYST | C37: Business Intelligence (BI) Intern | D37: =COUNTIF('JD-DA-0010'!$D$32:$D$70,"Y") | E37: =COUNTIFS('JD-DA-0010'!$A$32:$A$70,"<>",'JD-DA-0010'!$D$32:$D$70,"")
A38: JD-DA-0011 | B38: DATA_ANALYST | C38: JUNIOR DATA ANALYST – MANUFACTURING SYSTEMS & PLANNING | D38: =COUNTIF('JD-DA-0011'!$D$61:$D$97,"Y") | E38: =COUNTIFS('JD-DA-0011'!$A$61:$A$97,"<>",'JD-DA-0011'!$D$61:$D$97,"")
A39: JD-DS-0001 | B39: DATA_SCIENTIST | C39: Data Science Intern | D39: =COUNTIF('JD-DS-0001'!$D$34:$D$73,"Y") | E39: =COUNTIFS('JD-DS-0001'!$A$34:$A$73,"<>",'JD-DS-0001'!$D$34:$D$73,"")
A40: JD-DS-0002 | B40: DATA_SCIENTIST | C40: Data Science & AI Internship | D40: =COUNTIF('JD-DS-0002'!$D$33:$D$67,"Y") | E40: =COUNTIFS('JD-DS-0002'!$A$33:$A$67,"<>",'JD-DS-0002'!$D$33:$D$67,"")
A41: JD-DS-0003 | B41: DATA_SCIENTIST | C41: AI Intern – Computer Vision & Multimodal RAG | D41: =COUNTIF('JD-DS-0003'!$D$79:$D$128,"Y") | E41: =COUNTIFS('JD-DS-0003'!$A$79:$A$128,"<>",'JD-DS-0003'!$D$79:$D$128,"")
A42: JD-DS-0004 | B42: DATA_SCIENTIST | C42: Data Scientist Executive (Decision Intelligence) | D42: =COUNTIF('JD-DS-0004'!$D$35:$D$72,"Y") | E42: =COUNTIFS('JD-DS-0004'!$A$35:$A$72,"<>",'JD-DS-0004'!$D$35:$D$72,"")
A43: JD-DS-0005 | B43: DATA_SCIENTIST | C43: Data Scientist, Intern - [COMPANY] | D43: =COUNTIF('JD-DS-0005'!$D$34:$D$69,"Y") | E43: =COUNTIFS('JD-DS-0005'!$A$34:$A$69,"<>",'JD-DS-0005'!$D$34:$D$69,"")
A44: JD-DS-0006 | B44: DATA_SCIENTIST | C44: Internship for Computer/IT/Software/Data Science | D44: =COUNTIF('JD-DS-0006'!$D$22:$D$60,"Y") | E44: =COUNTIFS('JD-DS-0006'!$A$22:$A$60,"<>",'JD-DS-0006'!$D$22:$D$60,"")
A45: JD-DS-0007 | B45: DATA_SCIENTIST | C45: Technology Associate - Data Science | D45: =COUNTIF('JD-DS-0007'!$D$47:$D$91,"Y") | E45: =COUNTIFS('JD-DS-0007'!$A$47:$A$91,"<>",'JD-DS-0007'!$D$47:$D$91,"")
A46: JD-DS-0008 | B46: DATA_SCIENTIST | C46: Intern - Data Science | D46: =COUNTIF('JD-DS-0008'!$D$46:$D$85,"Y") | E46: =COUNTIFS('JD-DS-0008'!$A$46:$A$85,"<>",'JD-DS-0008'!$D$46:$D$85,"")
A47: JD-DS-0009 | B47: DATA_SCIENTIST | C47: Associate Engineer, Data Science | D47: =COUNTIF('JD-DS-0009'!$D$29:$D$71,"Y") | E47: =COUNTIFS('JD-DS-0009'!$A$29:$A$71,"<>",'JD-DS-0009'!$D$29:$D$71,"")
A48: JD-DS-0010 | B48: DATA_SCIENTIST | C48: Degree Internship (Data Science/ IT) | D48: =COUNTIF('JD-DS-0010'!$D$25:$D$58,"Y") | E48: =COUNTIFS('JD-DS-0010'!$A$25:$A$58,"<>",'JD-DS-0010'!$D$25:$D$58,"")
A49: JD-SD-0002 | B49: SOFTWARE_DEV | C49: Software Developer / Junior Software Developer | D49: =COUNTIF('JD-SD-0002'!$D$35:$D$71,"Y") | E49: =COUNTIFS('JD-SD-0002'!$A$35:$A$71,"<>",'JD-SD-0002'!$D$35:$D$71,"")
A50: JD-SD-0003 | B50: SOFTWARE_DEV | C50: Software Engineer (Internship) | D50: =COUNTIF('JD-SD-0003'!$D$25:$D$59,"Y") | E50: =COUNTIFS('JD-SD-0003'!$A$25:$A$59,"<>",'JD-SD-0003'!$D$25:$D$59,"")
A51: JD-SD-0005 | B51: SOFTWARE_DEV | C51: Software Developer (Internship) | D51: =COUNTIF('JD-SD-0005'!$D$18:$D$51,"Y") | E51: =COUNTIFS('JD-SD-0005'!$A$18:$A$51,"<>",'JD-SD-0005'!$D$18:$D$51,"")
A52: JD-SD-0006 | B52: SOFTWARE_DEV | C52: Junior Software Engineer | D52: =COUNTIF('JD-SD-0006'!$D$25:$D$61,"Y") | E52: =COUNTIFS('JD-SD-0006'!$A$25:$A$61,"<>",'JD-SD-0006'!$D$25:$D$61,"")
A53: JD-SD-0007 | B53: SOFTWARE_DEV | C53: Software Engineer (Full-Stack, AI-Assisted Development) | D53: =COUNTIF('JD-SD-0007'!$D$38:$D$70,"Y") | E53: =COUNTIFS('JD-SD-0007'!$A$38:$A$70,"<>",'JD-SD-0007'!$D$38:$D$70,"")
A54: JD-SD-0008 | B54: SOFTWARE_DEV | C54: Junior Software Developer/Engineer | D54: =COUNTIF('JD-SD-0008'!$D$26:$D$62,"Y") | E54: =COUNTIFS('JD-SD-0008'!$A$26:$A$62,"<>",'JD-SD-0008'!$D$26:$D$62,"")
A55: JD-SD-0009 | B55: SOFTWARE_DEV | C55: Java Developer Intern | D55: =COUNTIF('JD-SD-0009'!$D$37:$D$71,"Y") | E55: =COUNTIFS('JD-SD-0009'!$A$37:$A$71,"<>",'JD-SD-0009'!$D$37:$D$71,"")
A56: JD-SD-0010 | B56: SOFTWARE_DEV | C56: Intern, Software Developer (JAVA) | D56: =COUNTIF('JD-SD-0010'!$D$33:$D$70,"Y") | E56: =COUNTIFS('JD-SD-0010'!$A$33:$A$70,"<>",'JD-SD-0010'!$D$33:$D$70,"")
A57: JD-SD-0011 | B57: SOFTWARE_DEV | C57: Junior Tester | D57: =COUNTIF('JD-SD-0011'!$D$20:$D$50,"Y") | E57: =COUNTIFS('JD-SD-0011'!$A$20:$A$50,"<>",'JD-SD-0011'!$D$20:$D$50,"")
A58: JD-SD-0012 | B58: SOFTWARE_DEV | C58: Junior Software Engineer (Fresh graduates are welcome to apply) | D58: =COUNTIF('JD-SD-0012'!$D$62:$D$106,"Y") | E58: =COUNTIFS('JD-SD-0012'!$A$62:$A$106,"<>",'JD-SD-0012'!$D$62:$D$106,"")
A59: JD-WD-0001 | B59: WEB_DEV | C59: Interns - Software Developer | D59: =COUNTIF('JD-WD-0001'!$D$28:$D$64,"Y") | E59: =COUNTIFS('JD-WD-0001'!$A$28:$A$64,"<>",'JD-WD-0001'!$D$28:$D$64,"")
A60: JD-WD-0002 | B60: WEB_DEV | C60: Junior IT Programmer / Interns | D60: =COUNTIF('JD-WD-0002'!$D$33:$D$71,"Y") | E60: =COUNTIFS('JD-WD-0002'!$A$33:$A$71,"<>",'JD-WD-0002'!$D$33:$D$71,"")
A61: JD-WD-0003 | B61: WEB_DEV | C61: Full Stack Developer - (Junior to Mid Level) (MY Based) | D61: =COUNTIF('JD-WD-0003'!$D$39:$D$84,"Y") | E61: =COUNTIFS('JD-WD-0003'!$A$39:$A$84,"<>",'JD-WD-0003'!$D$39:$D$84,"")
A62: JD-WD-0004 | B62: WEB_DEV | C62: Software & Tech Internship | D62: =COUNTIF('JD-WD-0004'!$D$58:$D$96,"Y") | E62: =COUNTIFS('JD-WD-0004'!$A$58:$A$96,"<>",'JD-WD-0004'!$D$58:$D$96,"")
A63: JD-WD-0005 | B63: WEB_DEV | C63: Frontend Developer | D63: =COUNTIF('JD-WD-0005'!$D$38:$D$73,"Y") | E63: =COUNTIFS('JD-WD-0005'!$A$38:$A$73,"<>",'JD-WD-0005'!$D$38:$D$73,"")
A64: JD-WD-0006 | B64: WEB_DEV | C64: Junior Front End Developer | D64: =COUNTIF('JD-WD-0006'!$D$47:$D$85,"Y") | E64: =COUNTIFS('JD-WD-0006'!$A$47:$A$85,"<>",'JD-WD-0006'!$D$47:$D$85,"")
A65: JD-WD-0008 | B65: WEB_DEV | C65: Junior Full Stack Developer | D65: =COUNTIF('JD-WD-0008'!$D$34:$D$82,"Y") | E65: =COUNTIFS('JD-WD-0008'!$A$34:$A$82,"<>",'JD-WD-0008'!$D$34:$D$82,"")
A66: JD-WD-0009 | B66: WEB_DEV | C66: Junior Web Developer | D66: =COUNTIF('JD-WD-0009'!$D$27:$D$61,"Y") | E66: =COUNTIFS('JD-WD-0009'!$A$27:$A$61,"<>",'JD-WD-0009'!$D$27:$D$61,"")
A67: JD-WD-0010 | B67: WEB_DEV | C67: Intern, Fresh, Programmer, Personal Assistant (IT, Computer Sc) | D67: =COUNTIF('JD-WD-0010'!$D$31:$D$65,"Y") | E67: =COUNTIFS('JD-WD-0010'!$A$31:$A$65,"<>",'JD-WD-0010'!$D$31:$D$65,"")
A68: JD-WD-0011 | B68: WEB_DEV | C68: Junior PHP Web Developer | D68: =COUNTIF('JD-WD-0011'!$D$26:$D$61,"Y") | E68: =COUNTIFS('JD-WD-0011'!$A$26:$A$61,"<>",'JD-WD-0011'!$D$26:$D$61,"")

Sheet JD-CE-0001
A1: JD-CE-0001 | CLOUD_ENGINEER | IT Infra & Cloud Intern (entry)
A2: Read the JD, then go down to the table. Mark every pre-filled row keep = Y (correct, fix the cells if needed) or N (wrong). Add missing skills on the empty rows with keep = Y. Yellow rows still need a Y or N.
A3: Go to the label table
A4: Job description
A5: About the role
A7: This is an infrastructure support role assisting the Infrastructure team with IT infrastructure setup, configuration, monitoring and troubleshooting. You will support Microsoft Azure infrastructure activities, including virtual machines, virtual networks, storage and resource monitoring, under the guidance of senior engineers.
A9: Key responsibilities
A11: * Assist the Infrastructure team with basic IT infrastructure setup, configuration, monitoring and troubleshooting
A12: * Support Microsoft Azure infrastructure activities, including virtual machines, virtual networks, storage and resource monitoring, under the guidance of senior engineers
A13: * Assist with network troubleshooting, including IP addressing, DNS, connectivity and basic routing concepts
A14: * Support Windows Server and/or Linux system administration tasks
A15: * Assist in monitoring infrastructure performance, reviewing alerts and documenting incidents
... A31: * Good communication skills and attention to detail
A33: skill_name | B33: importance | C33: evidence_text | D33: keep | E33: note
A34: Monitoring & Observability | B34: required | C34: This is an infrastructure support role assisting the Infrastructure team with IT infrastructure setup, configuration, monitoring and troubleshooting | D34: Y
A35: Problem Solving | B35: required | C35: Good analytical and problem-solving skills | D35: Y
A36: Azure | B36: required | C36: You will support Microsoft Azure infrastructure activities, including virtual machines, virtual networks, storage and resource monitoring, under the guidance of senior engineers | D36: Y
A37: Networking | B37: required | C37: * Assist with network troubleshooting, including IP addressing, DNS, connectivity and basic routing concepts | D37: Y
A38: Windows Server | B38: required | C38: * Support Windows Server and/or Linux system administration tasks | D38: Y
A39: Linux | B39: required | C39: * Support Windows Server and/or Linux system administration tasks | D39: Y
A40: Documentation | B40: required | C40: * Prepare and maintain technical documentation, configuration records and troubleshooting guides | D40: Y
A41: Identity & Access Management | B41: required | C41: * Learn and follow IT security practices, access control procedures and infrastructure management standards | D41: N
A42: Cloud Computing | B42: required | C42: Support Microsoft Azure infrastructure activities | D42: Y
A43: PowerShell | B43: bonus | C43: * Familiarity with PowerShell, Bash, scripting or infrastructure monitoring tools is a plus | D43: Y
A44: Bash | B44: bonus | C44: * Familiarity with PowerShell, Bash, scripting or infrastructure monitoring tools is a plus | D44: Y
A45: Self-Motivation | B45: required | C45: * Willingness to learn, take initiative and work collaboratively with the technical team | D45: Y
... A48: Teamwork | B48: required | C48: work collaboratively with the technical team | D48: Y
A49: Cybersecurity | B49: preferred | C49: Learn and follow IT security practices | D49: Y | E49: '?' resolved, preferred; A/B resolution, AI-assisted adjudication 2026-10-29, see resolution.xlsx
A50: NEW: Virtualisation | B50: bonus | C50: virtual machines or networking technologies is an advantage | D50: Y
A51: Identity & Access Management | B51: preferred | C51: Learn and follow IT security practices, access control procedures | D51: Y | E51: added from B; A/B resolution, AI-assisted adjudication 2026-10-29, see resolution.xlsx

Sheet JD-CE-0002
A1: JD-CE-0002 | CLOUD_ENGINEER | Internship - Cloud Infrastructure End User Computing (entry)
A2: Read the JD, then go down to the table. Mark every pre-filled row keep = Y (correct, fix the cells if needed) or N (wrong). Add missing skills on the empty rows with keep = Y. Yellow rows still need a Y or N.
A3: Go to the label table
A4: Job description
A5: Responsibilities
A7: * Provide first-level technical support for hardware, software and network issues, ensuring prompt resolution and positive user experience.
A8: * Diagnosing and resolving IT incidents in line with organizational standards and best practices.
A9: * Support daily operations through IT asset management, inventory tracking and administration of hardware, software and infrastructure components.
A10: * Maintain accurate and up-to-date documentation of IT systems, configurations, processes and procedures to support transparency and knowledge sharing.
A11: * Assist in designing, developing and implementing new or improved systems and workflows to enhance operational efficiency.
A12: * Process and track IT-related invoices, telecommunications bills, software subscriptions, maintenance contracts and supporting records.
A13: * Support the testing and validation of new systems, applications and technologies to ensure quality and business alignment.
... A23: * Familiarity with public cloud platforms (AWS, Azure, GCP), UiPath (RPA) and programming or database technologies such as SQL is an advantage.
A25: skill_name | B25: importance | C25: evidence_text | D25: keep | E25: note
A26: UI/UX Design | B26: required | C26: * Provide first-level technical support for hardware, software and network issues, ensuring prompt resolution and positive user experience | D26: N
A27: Documentation | B27: required | C27: * Maintain accurate and up-to-date documentation of IT systems, configurations, processes and procedures to support transparency and knowledge sharing | D27: Y
A28: Generative AI | B28: required | C28: * Research, evaluate and introduce emerging technologies and solutions, including Generative AI, automation and robotics to drive organizational improvement | D28: Y
A29: Communication | B29: required | C29: * Strong communication and interpersonal abilities | D29: Y
A30: Time Management | B30: required | C30: * Effective time management and problem-solving skills | D30: Y
A31: Cloud Computing | B31: bonus | C31: * Familiarity with public cloud platforms (AWS, Azure, GCP), UiPath (RPA) and programming or database technologies such as SQL is an advantage | D31: Y
A32: AWS | B32: bonus | C32: * Familiarity with public cloud platforms (AWS, Azure, GCP), UiPath (RPA) and programming or database technologies such as SQL is an advantage | D32: Y
A33: Azure | B33: bonus | C33: * Familiarity with public cloud platforms (AWS, Azure, GCP), UiPath (RPA) and programming or database technologies such as SQL is an advantage | D33: Y
A34: GCP | B34: bonus | C34: * Familiarity with public cloud platforms (AWS, Azure, GCP), UiPath (RPA) and programming or database technologies such as SQL is an advantage | D34: Y
A35: SQL | B35: bonus | C35: * Familiarity with public cloud platforms (AWS, Azure, GCP), UiPath (RPA) and programming or database technologies such as SQL is an advantage | D35: Y
A36: Interpersonal Skills | B36: required | C36: Strong communication and interpersonal abilities. | D36: Y
A37: Problem Solving | B37: required | C37: Effective time management and problem-solving skills. | D37: Y
... A45: NEW: IT Support | B45: required | C45: Provide first-level technical support for hardware, software and network issues | D45: Y
A46: NEW: UiPath | B46: bonus | C46: UiPath (RPA) | D46: Y | E46: added from B; A/B resolution, AI-assisted adjudication 2026-10-29, see resolution.xlsx
A47: NEW: IT Asset Management | B47: required | C47: IT asset management, inventory tracking | D47: Y | E47: added from B; A/B resolution, AI-assisted adjudication 2026-10-29, see resolution.xlsx

Sheet JD-CE-0003
A1: JD-CE-0003 | CLOUD_ENGINEER | Junior Cloud Engineer (junior)
A2: Read the JD, then go down to the table. Mark every pre-filled row keep = Y (correct, fix the cells if needed) or N (wrong). Add missing skills on the empty rows with keep = Y. Yellow rows still need a Y or N.
A3: Go to the label table
A4: Job description
A5: Key Responsibilities
A7: * Build, deploy and maintain the cloud infrastructure that runs our own platforms and our clients’ hosted environments, working to designs set by senior engineers and architects.
A8: * Run day-to-day operations across cloud and on-premises environments — provisioning, patching, monitoring, backup and incident response.
A9: * Take part in migration and deployment projects, from environment build through UAT to go-live support.
A10: * Document what you build: configurations, runbooks, network diagrams and as-built records.
A11: * Learn the platform and the business behind it and grow into owning environments of your own.
A13: Cloud Infrastructure
A15: * Provision and configure compute, storage, networking and identity services on at least one major cloud platform (AWS, Azure or Google Cloud).
... A73: * Occasional onsite work at data centres and client premises, including out-of-hours cutovers and DR drills.
A75: skill_name | B75: importance | C75: evidence_text | D75: keep | E75: note
A76: Cloud Computing | B76: required | C76: * Build, deploy and maintain the cloud infrastructure that runs our own platforms and our clients’ hosted environments, working to designs set by senior engineers and architects | D76: Y
A77: Monitoring & Observability | B77: required | C77: * Run day-to-day operations across cloud and on-premises environments — provisioning, patching, monitoring, backup and incident response | D77: Y
A78: Incident Response | B78: required | C78: * Run day-to-day operations across cloud and on-premises environments — provisioning, patching, monitoring, backup and incident response | D78: Y
A79: Networking | B79: required | C79: * Provision and configure compute, storage, networking and identity services on at least one major cloud platform (AWS, Azure or Google Cloud) | D79: Y
A80: AWS | B80: required | C80: * Provision and configure compute, storage, networking and identity services on at least one major cloud platform (AWS, Azure or Google Cloud) | D80: Y
A81: Azure | B81: required | C81: * Provision and configure compute, storage, networking and identity services on at least one major cloud platform (AWS, Azure or Google Cloud) | D81: Y
A82: GCP | B82: required | C82: * Provision and configure compute, storage, networking and identity services on at least one major cloud platform (AWS, Azure or Google Cloud) | D82: Y
A83: VPN | B83: required | C83: * Support hybrid setups that link cloud environments to on-premises data centres over VPN or dedicated circuits | D83: Y
A84: Docker | B84: required | C84: * Build and maintain container images and run workloads under Docker or a comparable runtime | D84: Y
A85: Kubernetes | B85: required | C85: * Deploy and support applications on Kubernetes or a managed equivalent (EKS, AKS, GKE) — deployments, services, ingress, config maps, secrets and persistent volumes | D85: Y
A86: CI/CD | B86: required | C86: * Work with CI/CD pipelines to move builds through development, staging and production | D86: Y
A87: Linux | B87: required | C87: * Administer Linux servers (RHEL, Rocky, Ubuntu or equivalent) — users and permissions, packages, services, storage, OS and kernel patching, and shell scripting | D87: Y
... A107: NEW: Infrastructure as Code | B107: bonus | C107: Infrastructure as code | D107: Y

Sheet JD-CE-0004
A1: JD-CE-0004 | CLOUD_ENGINEER | Junior System Administrator (junior)
A2: Read the JD, then go down to the table. Mark every pre-filled row keep = Y (correct, fix the cells if needed) or N (wrong). Add missing skills on the empty rows with keep = Y. Yellow rows still need a Y or N.
A3: Go to the label table
A4: Job description
A5: Are you passionate about high-performance computing, digging deep into Linux systems, and working with cutting-edge infrastructure? Looking for a fast-paced environment where your skills directly support groundbreaking work across the globe?
A6: [COMPANY] is looking for a Junior System Administrator to join our global IT operations team. You'll be hands-on with our high-performance computing (HPC) infrastructure, working on everything from compute clusters to high-speed networks and large-scale storage systems. If you enjoy diving into Linux internals, writing and running bash scripts, and supporting users who rely on you to keep things running smoothly, we want to hear from you.
A8: Requirements
A10: * A Diploma/ Bachelor's in Computer Science, Computer Engineering, or equivalent.
A11: * Experience with Linux (any flavour!)
A12: * Hands-on homelab experience would be highly desirable
A13: * Excellent communication skills; fluent in written and spoken English.
A14: * The ability to multitask and be agile
A16: skill_name | B16: importance | C16: evidence_text | D16: keep | E16: note
A17: Linux | B17: required | C17: Are you passionate about high-performance computing, digging deep into Linux systems, and working with cutting-edge infrastructure? Looking for a fast-paced environment where your skills directly support groundbreaking work across the globe? | D17: Y
A18: Bash | B18: required | C18: If you enjoy diving into Linux internals, writing and running bash scripts, and supporting users who rely on you to keep things running smoothly, we want to hear from you | D18: Y
A19: Communication | B19: required | C19: * Excellent communication skills | D19: Y
A20: Agile / Scrum | B20: required | C20: * The ability to multitask and be agile | D20: N
A21: NEW: High-Performance Computing | B21: required | C21: high-performance computing (HPC) infrastructure | D21: Y
A22: Networking | B22: required | C22: high-speed networks | D22: Y
A23: Time Management | B23: required | C23: The ability to multitask? | D23: Y

Sheet JD-CE-0005
A1: JD-CE-0005 | CLOUD_ENGINEER | Internship - IT (Cybersecurity & System Administration) (entry)
A2: Read the JD, then go down to the table. Mark every pre-filled row keep = Y (correct, fix the cells if needed) or N (wrong). Add missing skills on the empty rows with keep = Y. Yellow rows still need a Y or N.
A3: Go to the label table
A4: Job description
A5: Requirements
A7: * Open to degree students pursuing studies in Computer Science, Information Technology, or any other relevant discipline
A8: * Interested to pursue internship opportunity in Cybersecurity or System Administraion field
A9: * For local students only
A10: * A minimum of 6 months placement is required
A11: * A good command of English
A13: Perks and benefits: Medical; Miscellaneous allowance; Loans; Dental; Vision; Employer EPF Contribution of 16%
A15: skill_name | B15: importance | C15: evidence_text | D15: keep | E15: note
A16: Cybersecurity | B16: required | C16: * Interested to pursue internship opportunity in Cybersecurity or System Administraion field | D16: N

Sheet JD-CE-0006
A1: JD-CE-0006 | CLOUD_ENGINEER | Cloud Delivery Support Engineer (entry)
A2: Read the JD, then go down to the table. Mark every pre-filled row keep = Y (correct, fix the cells if needed) or N (wrong). Add missing skills on the empty rows with keep = Y. Yellow rows still need a Y or N.
A3: Go to the label table
A4: Job description
A5: Cloud Delivery Support Engineer (Fresh graduate)
A7: Employment: 1-Year Contract, renewable annually; conversion to Permanent in the third year
A8: Work Mode: Hybrid, Shift-based
A9: Shift: 9:00 AM–6:00 PM / 5:00 PM–12:00 AM
A10: Rest Days: 2 rest days per week, scheduled based on roster and not fixed on Saturday or Sunday
A12: Responsibilities
A14: * Support cloud service delivery, including account provisioning, service activation, configuration and deployment.
A15: * Provide L1 technical support and basic troubleshooting for cloud-related issues.
... A34: * AWS, Azure, Alibaba Cloud or Tencent Cloud knowledge or certification is an advantage.
A36: skill_name | B36: importance | C36: evidence_text | D36: keep | E36: note
A37: Problem Solving | B37: required | C37: * Provide L1 technical support and basic troubleshooting for cloud-related issues | D37: Y
A38: Customer Focus | B38: required | C38: * Handle customer service requests, incidents and technical enquiries, with proper escalation when required | D38: Y
A39: Cloud Computing | B39: required | C39: * Support multiple cloud platforms, including AWS, Azure, Alibaba Cloud and Tencent Cloud | D39: Y
A40: AWS | B40: required | C40: * Support multiple cloud platforms, including AWS, Azure, Alibaba Cloud and Tencent Cloud | D40: Y
A41: Azure | B41: required | C41: * Support multiple cloud platforms, including AWS, Azure, Alibaba Cloud and Tencent Cloud | D41: Y
A42: Networking | B42: required | C42: * Basic understanding of cloud infrastructure, networking, virtual machines and cloud services | D42: Y
A43: Communication | B43: required | C43: * Proficiency in Mandarin is mandatory, as the role requires direct communication with Mandarin-speaking clients | D43: Y
A44: Excel | B44: required | C44: Proficient in Excel and Google Sheets. | D44: Y
A45: NEW: Google Sheets | B45: required | C45: Proficient in Excel and Google Sheets. | D45: Y
A46: Time Management | B46: required | C46: Able to manage multiple tasks in a fast-paced environment. | D46: Y
A47: Stakeholder Communication | B47: required | C47: Coordinate with Technical, Sales and Procurement teams | D47: Y
A48: NEW: Alibaba Cloud | B48: required | C48: Alibaba Cloud | D48: Y
... A50: NEW: IT Support | B50: required | C50: Provide L1 technical support and basic troubleshooting | D50: Y

Sheet JD-CE-0007
A1: JD-CE-0007 | CLOUD_ENGINEER | Specialist - Junior DevOps Engineer (junior)
A2: Read the JD, then go down to the table. Mark every pre-filled row keep = Y (correct, fix the cells if needed) or N (wrong). Add missing skills on the empty rows with keep = Y. Yellow rows still need a Y or N.
A3: Go to the label table
A4: Job description
A5: Responsibilities of the Role
A7: We are looking for an enthusiastic DevOps Engineer who has the following qualities and responsibilities:
A9: Application support
A11: * Resolve issues
A12: * Perform site performance monitoring to determine system performance bottlenecks.
A13: * Manage operation day-to-day technical issues.
A15: DevOps tasks
A17: * Support the application CI/CD pipeline for promoting software into higher environments.
... A34: Perks and benefits: Performance related bonus for confirmed staff; Annual Leave 15 days; Medical Leave 14 days; Medical and hospitalization coverage
A36: skill_name | B36: importance | C36: evidence_text | D36: keep | E36: note
A37: Monitoring & Observability | B37: required | C37: * Perform site performance monitoring to determine system performance bottlenecks | D37: Y
A38: CI/CD | B38: required | C38: * Support the application CI/CD pipeline for promoting software into higher environments | D38: Y
A39: Self-Motivation | B39: required | C39: Proactive learner | D39: Y
A40: Teamwork | B40: required | C40: * Good teamwork | D40: Y
A41: Communication | B41: required | C41: * Good interpersonal and communication skills | D41: Y
A42: Critical Thinking | B42: required | C42: Critical thinker | D42: Y
A43: Problem Solving | B43: required | C43: Critical thinker and problem-solving skills. | D43: Y
A44: Time Management | B44: required | C44: Good time-management skills. | D44: Y
A45: Interpersonal Skills | B45: required | C45: Good interpersonal and communication skills. | D45: Y
A46: Research Skills | B46: required | C46: ability to research and quickly utilize new technologies | D46: Y
A47: NEW: DevOps | B47: required | C47: DevOps tools support | D47: Y

Sheet JD-CE-0008
A1: JD-CE-0008 | CLOUD_ENGINEER | Cloud Systems Engineer (mid)
A2: Read the JD, then go down to the table. Mark every pre-filled row keep = Y (correct, fix the cells if needed) or N (wrong). Add missing skills on the empty rows with keep = Y. Yellow rows still need a Y or N.
A3: Go to the label table
A4: Job description
A5: We are looking for a Cloud System Engineer who is well-versed in private and public cloud infrastructure, Linux server management, along with experience in on-premise to cloud migration.
A6: Responsibilities include implementation, configuration and support of our cloud server infrastructure across South East Asia, as well as planning and execution of migration of on-premise servers and applications to the cloud.
A7: Most tasks will be carried out remotely.
A9: What you will be doing
A11: * Operating and maintaining large scale cloud infrastructure and servers in global data centres
A12: * Working on various Linux server projects alongside multiple departments
A13: * Migrating clients on-premise servers to the cloud via replication or data backups
A14: * Assessing and resolving server and network-related issues escalated by internal and external users
... A48: * Willing to travel (e.g. to server locations for cloud migration)
A50: skill_name | B50: importance | C50: evidence_text | D50: keep | E50: note
A51: Cloud Computing | B51: required | C51: We are looking for a Cloud System Engineer who is well-versed in private and public cloud infrastructure, Linux server management, along with experience in on-premise to cloud migration | D51: Y
A52: Linux | B52: required | C52: We are looking for a Cloud System Engineer who is well-versed in private and public cloud infrastructure, Linux server management, along with experience in on-premise to cloud migration | D52: Y
A53: Self-Motivation | B53: required | C53: Able to work autonomously | D53: Y
A54: Monitoring & Observability | B54: required | C54: * Proactive monitoring of supported cloud instances | D54: Y
A55: Problem Solving | B55: required | C55: Assessing and resolving server and network-related issues | D55: Y
A56: Azure | B56: bonus | C56: Both AWS/Azure/GCP and non-AWS/Azure/GCP cloud experience | D56: Y
A57: Ansible | B57: required | C57: * Automation - Salt, Ansible, Puppet, Chef | D57: Y
A58: AWS | B58: bonus | C58: Both AWS/Azure/GCP and non-AWS/Azure/GCP cloud experience | D58: Y
A59: GCP | B59: bonus | C59: Both AWS/Azure/GCP and non-AWS/Azure/GCP cloud experience | D59: Y
A60: Windows Server | B60: bonus | C60: Experience with Windows Server 2012, 2016, 2019, and Microsoft SQL | D60: Y
A61: NEW: Microsoft SQL Server | B61: bonus | C61: Microsoft SQL | D61: Y
A62: Communication | B62: required | C62: * Excellent written and verbal communication skills (English) | D62: Y
... A69: NEW: OpenStack | B69: bonus | C69: Cloudstack, Openstack, Proxmox VE | D69: Y

Sheet JD-CE-0009
A1: JD-CE-0009 | CLOUD_ENGINEER | IT Intern (entry)
A2: Read the JD, then go down to the table. Mark every pre-filled row keep = Y (correct, fix the cells if needed) or N (wrong). Add missing skills on the empty rows with keep = Y. Yellow rows still need a Y or N.
A3: Go to the label table
A4: Job description
A5: Job Responsibilities
A7: * System Administration: Provide support in managing and overseeing the company’s ticketing platform in coordination with the Operations department
A8: * Technical Support: Assist with troubleshooting procedures and deliver technical guidance whenever necessary
A9: * Resource Management: Systematize, track, and maintain the organization’s IT assets and technical resources
A10: * Directives: Execute specific tasks and projects as designated by the Chief Technology Officer (CTO) or the Head of Department
A12: Job Requirements
A14: * Academic Credentials: Minimum of a Diploma, Advanced/Higher/Graduate Diploma, or a Bachelor’s Degree in Computer Science, Software Engineering, Information Technology, or a similar technical field
A15: * Technical Proficiency: Familiarity with a diverse range of programming languages and frameworks is an added advantage (PHP Laravel, Node.js, React.ks, JavaScript, HTML, CSS, Flutter)
... A18: Perks and benefits: 5 working days a week (9:00 AM – 6:00 PM); 7-minute walk from Taman Perindustrian Puchong LRT station; Basement parking
A20: skill_name | B20: importance | C20: evidence_text | D20: keep | E20: note
A21: Problem Solving | B21: required | C21: * Technical Support: Assist with troubleshooting procedures and deliver technical guidance whenever necessary | D21: Y
A22: PHP | B22: bonus | C22: * Technical Proficiency: Familiarity with a diverse range of programming languages and frameworks is an added advantage (PHP Laravel, Node | D22: Y
A23: Node.js | B23: bonus | C23: * Technical Proficiency: Familiarity with a diverse range of programming languages and frameworks is an added advantage (PHP Laravel, Node.js, React | D23: Y
A24: React | B24: bonus | C24: Familiarity with a diverse range of programming languages and frameworks is an added advantage | D24: Y
A25: JavaScript | B25: bonus | C25: ks, JavaScript, HTML, CSS, Flutter) | D25: Y
A26: HTML | B26: bonus | C26: ks, JavaScript, HTML, CSS, Flutter) | D26: Y
A27: CSS | B27: bonus | C27: ks, JavaScript, HTML, CSS, Flutter) | D27: Y
A28: NEW: Laravel | B28: bonus | C28: PHP Laravel | D28: Y
A29: NEW: Flutter | B29: bonus | C29: Flutter | D29: Y
A30: NEW: IT Support | B30: required | C30: Assist with troubleshooting procedures and deliver technical guidance | D30: Y
A31: NEW: IT Asset Management | B31: required | C31: IT assets and technical resources | D31: Y

Sheet JD-CE-0010
A1: JD-CE-0010 | CLOUD_ENGINEER | Cloud and IT Operation Intern (2026 Intake) (entry)
A2: Read the JD, then go down to the table. Mark every pre-filled row keep = Y (correct, fix the cells if needed) or N (wrong). Add missing skills on the empty rows with keep = Y. Yellow rows still need a Y or N.
A3: Go to the label table
A4: Job description
A5: About the Role
A7: We are looking for passionate Interns to assist our Delivery team in resolving common day-to-day challenges in Enterprise Cloud and ITO Infrastructure (Active Directory, Servers, Storage, Backup, Database, Middleware, Networks etc) services. The Intern would need to be eager to explore new things including elements of AI in helping us improve our services delivery.
A9: Key Responsibilities
A11: * Assist in research and documentation related to AI technologies and their applications in enterprise environments.
A12: * Support infrastructure-related tasks such as monitoring systems, basic troubleshooting, and configuration under supervision.
A13: * Help with endpoint device management (Windows, macOS, mobile devices), including inventory checks and basic setup.
A14: * Participate in testing and validation of AI-driven tools and automation workflows.
A15: * Prepare reports and presentations on findings and progress.
... A39: * Malaysian citizens only
A41: skill_name | B41: importance | C41: evidence_text | D41: keep | E41: note
A42: Identity & Access Management | B42: required | C42: We are looking for passionate Interns to assist our Delivery team in resolving common day-to-day challenges in Enterprise Cloud and ITO Infrastructure (Active Directory, Servers, Storage, Backup, Database, Middleware, Networks etc) services | D42: Y
A43: Documentation | B43: required | C43: * Assist in research and documentation related to AI technologies and their applications in enterprise environments | D43: Y
A44: Monitoring & Observability | B44: required | C44: * Support infrastructure-related tasks such as monitoring systems, basic troubleshooting, and configuration under supervision | D44: Y
A45: Problem Solving | B45: required | C45: * Support infrastructure-related tasks such as monitoring systems, basic troubleshooting, and configuration under supervision | D45: Y
A46: AI Literacy | B46: required | C46: * Basic understanding of AI concepts (e | D46: Y
A47: Machine Learning | B47: required | C47: , machine learning, chatbots, automation) | D47: Y
A48: Linux | B48: preferred | C48: * Familiarity with multiple OS platform (Windows, Unix, Linux, macOS, mobile platforms) | D48: Y
A49: Python | B49: preferred | C49: * Exposure to scripting languages (Python, PowerShell) or interest in learning | D49: Y
A50: PowerShell | B50: preferred | C50: * Exposure to scripting languages (Python, PowerShell) or interest in learning | D50: Y
A51: Cloud Computing | B51: required | C51: * Awareness of cloud platforms (Azure, AWS, or GCP) | D51: Y
A52: Azure | B52: preferred | C52: Awareness of cloud platforms (Azure, AWS, or GCP). | D52: Y
A53: AWS | B53: preferred | C53: Awareness of cloud platforms (Azure, AWS, or GCP). | D53: Y
... A63: NEW: Endpoint Device Management | B63: required | C63: endpoint device management | D63: Y

Sheet JD-CY-0001
A1: JD-CY-0001 | CYBER_ANALYST | Internship - Technical Support Engineer (entry)
A2: Read the JD, then go down to the table. Mark every pre-filled row keep = Y (correct, fix the cells if needed) or N (wrong). Add missing skills on the empty rows with keep = Y. Yellow rows still need a Y or N.
A3: Go to the label table
A4: Job description
A5: Job Description
A7: * The candidate will be assigned to the technical support department and will be trained on providing technical support for the assigned cybersecurity products.
A8: * Work closely with technical support team to learn the technical support operations and assist the team on case management.
A9: * Learn and use the case management tool and phone system to perform support operations.
A10: * Perform any other duties deemed relevant as assigned.
A12: Highlights
A14: * Exposure in cybersecurity products and technologies.
A15: * Learning on how to investigate and troubleshoot cybersecurity products issues.
... A30: * Internship duration is 6 months.
A32: skill_name | B32: importance | C32: evidence_text | D32: keep | E32: note
A33: Cybersecurity | B33: required | C33: Attended courses related to networking and security. | D33: Y
A34: Communication | B34: required | C34: * Improving communication and customer engagement skills through working with customers and users from different Asia Pacific countries and from different levels within a company | D34: Y
A35: Networking | B35: required | C35: Attended courses related to networking and security. | D35: Y
A36: Time Management | B36: required | C36: * Strong organizational and time management skills | D36: Y
A37: Self-Motivation | B37: required | C37: Quick learner and always look for ways to improve own self. | D37: Y
A38: Teamwork | B38: required | C38: Work closely with technical support team | D38: Y
A39: NEW: Organisational Skills | B39: required | C39: Strong organizational and time management skills. | D39: Y
A40: NEW: IT Support | B40: required | C40: providing technical support for the assigned cybersecurity products | D40: Y | E40: renamed; guide rule R1 applied after the A/B resolution (AI-assisted, 2026-10-29)

Sheet JD-CY-0002
A1: JD-CY-0002 | CYBER_ANALYST | Security Operations Center (SOC) Analyst (mid)
A2: Read the JD, then go down to the table. Mark every pre-filled row keep = Y (correct, fix the cells if needed) or N (wrong). Add missing skills on the empty rows with keep = Y. Yellow rows still need a Y or N.
A3: Go to the label table
A4: Job description
A5: Job Responsibility
A7: A passion for research, and uncovering the unknown about internet threats and threat actors.
A9: i) Communication
A11: * The first point of contact for security incident notifications from customers, service desks, IT engineers and administrator during emergencies
A12: * Develop a professional working relationship with fellow analysts.
A14: ii) Monitoring
A16: * General SIEM monitoring, analysis, content development, and maintenance.
A18: iii) Identifying
... A46: * Excellent communication (written and oral) and interpersonal skills
A48: skill_name | B48: importance | C48: evidence_text | D48: keep | E48: note
A49: Communication | B49: required | C49: i) Communication | D49: Y
A50: Monitoring & Observability | B50: required | C50: ii) Monitoring | D50: N
A51: SIEM | B51: required | C51: * General SIEM monitoring, analysis, content development, and maintenance | D51: Y
A52: React | B52: required | C52: * React to security alerts and security events of interest from defense systems like IDS, endpoint protection and other security-related systems | D52: N
A53: Documentation | B53: required | C53: including log retrieval and documentation | D53: Y
A54: Incident Response | B54: required | C54: * Assist in incident response activities such as host triage and retrieval, malware analysis, remote system analysis and remediation efforts | D54: Y
A55: Malware Analysis | B55: required | C55: * Assist in incident response activities such as host triage and retrieval, malware analysis, remote system analysis and remediation efforts | D55: Y
A56: Cybersecurity | B56: required | C56: * Analyze cybersecurity alerts and data for false positive/true positive outcomes while modifying, alerts as needed | D56: Y
A57: Security Operations (SOC) | B57: required | C57: * Ensure the SOC analyst team is providing excellent customer service and support | D57: Y
A58: Customer Focus | B58: required | C58: * Ensure the SOC analyst team is providing excellent customer service and support | D58: Y
A59: Interpersonal Skills | B59: required | C59: * Excellent communication (written and oral) and interpersonal skills | D59: Y
A60: Threat Intelligence | B60: required | C60: uncovering the unknown about internet threats and threat actors | D60: Y
... A65: NEW: Root Cause Analysis | B65: required | C65: Perform Root Cause Analysis of security incidents | D65: Y

Sheet JD-CY-0003
A1: JD-CY-0003 | CYBER_ANALYST | PENETRATING TESTING INTERN (entry)
A2: Read the JD, then go down to the table. Mark every pre-filled row keep = Y (correct, fix the cells if needed) or N (wrong). Add missing skills on the empty rows with keep = Y. Yellow rows still need a Y or N.
A3: Go to the label table
A4: Job description
A5: Key responsibilities
A7: * Assist the Security Assessment team in conducting penetration testing and vulnerability assessments
A8: * Assist with documenting security findings and preparing penetration testing reports
A9: * Support basic security testing of web applications, networks and systems
A10: * Assist in identifying, validating and documenting security vulnerabilities
A11: * Help prepare technical reports and documentation
A12: * Conduct research on vulnerabilities, exploits and cybersecurity tools
A13: * Support other technical tasks assigned by the team
... A23: Perks and benefits: Medical; Miscellaneous allowance; Education support; Dental; Parking; Vision
A25: skill_name | B25: importance | C25: evidence_text | D25: keep | E25: note
A26: Ethical Hacking | B26: required | C26: * Assist the Security Assessment team in conducting penetration testing and vulnerability assessments | D26: Y
A27: Documentation | B27: required | C27: * Help prepare technical reports and documentation | D27: Y
A28: Cybersecurity | B28: required | C28: * Conduct research on vulnerabilities, exploits and cybersecurity tools | D28: Y
A29: Networking | B29: required | C29: * Basic knowledge of networking, operating systems and cybersecurity concepts | D29: Y
A30: Vulnerability Assessment | B30: required | C30: * Interest in penetration testing, ethical hacking and vulnerability assessment | D30: Y
A31: Kali Linux | B31: bonus | C31: * Familiarity with tools such as Kali Linux, Burp Suite or Nmap is an advantage | D31: Y
A32: Burp Suite | B32: bonus | C32: * Familiarity with tools such as Kali Linux, Burp Suite or Nmap is an advantage | D32: Y
A33: Nmap | B33: bonus | C33: * Familiarity with tools such as Kali Linux, Burp Suite or Nmap is an advantage | D33: Y
A34: Problem Solving | B34: required | C34: Good analytical and problem-solving skills | D34: Y
A35: Research Skills | B35: required | C35: Conduct research on vulnerabilities, exploits and cybersecurity tools | D35: Y
A36: Self-Motivation | B36: required | C36: with a willingness to learn | D36: Y
A37: NEW: Web Application Security | B37: required | C37: Support basic security testing of web applications | D37: Y

Sheet JD-CY-0004
A1: JD-CY-0004 | CYBER_ANALYST | Junior Incident Responder, Malaysia (junior)
A2: Read the JD, then go down to the table. Mark every pre-filled row keep = Y (correct, fix the cells if needed) or N (wrong). Add missing skills on the empty rows with keep = Y. Yellow rows still need a Y or N.
A3: Go to the label table
A4: Job description
A5: Your Mission: Junior Incident Responder
A7: As a Junior Incident Responder, you will work alongside senior responders on live engagements — helping clients contain, investigate, and recover from real cyber attacks. This is a delivery-focused role: your job is to do the work, learn the craft, and grow into a fully fledged responder under direct mentorship.
A8: We hire for attitude and aptitude. We don't expect you to have seen everything yet — we expect you to be curious, coachable, and serious about building a career in incident response. The right candidate can demonstrate a genuine interest in IR through their experience, side projects, study, or community involvement, and shows up ready to learn fast in a real-world environment.
A10: Core Responsibilities
A12: Delivery Alongside Senior Responders
A14: * Support senior consultants on active incidents — assisting with containment, evidence collection, forensic analysis, and reporting.
A15: * Acquire and triage forensic artifacts across Windows, Linux, macOS, and cloud environments under the guidance of more experienced team members.
A16: * Analyse logs, endpoint telemetry, network data, and malware artifacts, and contribute findings to investigation timelines.
... A49: Perks and benefits: Paired with senior responders from day one; Hands-on mentorship and structured instructor-led training program
A51: skill_name | B51: importance | C51: evidence_text | D51: keep | E51: note
A52: Incident Response | B52: required | C52: We don't expect you to have seen everything yet — we expect you to be curious, coachable, and serious about building a career in incident response | D52: Y
A53: Linux | B53: required | C53: * Acquire and triage forensic artifacts across Windows, Linux, macOS, and cloud environments under the guidance of more experienced team members | D53: Y
A54: Python | B54: required | C54: * Use scripting (Python, Bash, or PowerShell) to assist with collection, parsing, and automation tasks where useful | D54: Y
A55: Bash | B55: required | C55: * Use scripting (Python, Bash, or PowerShell) to assist with collection, parsing, and automation tasks where useful | D55: Y
A56: PowerShell | B56: required | C56: * Use scripting (Python, Bash, or PowerShell) to assist with collection, parsing, and automation tasks where useful | D56: Y
A57: Cybersecurity | B57: required | C57: * 1+ year of experience in cybersecurity, IT, or an adjacent technical field (e | D57: Y
A58: SIEM | B58: preferred | C58: * Hands-on exposure to EDR, SIEM, or forensic tooling, even in a learning context | D58: Y
A59: Digital Forensics | B59: required | C59: forensic analysis | D59: Y
A60: Log Analysis | B60: required | C60: Analyse logs, endpoint telemetry, network data | D60: Y
A61: Malware Analysis | B61: required | C61: malware artifacts | D61: Y
A62: Documentation | B62: required | C62: Document findings clearly and accurately | D62: Y
A63: Communication | B63: required | C63: communicate professionally with teammates and clients | D63: Y
... A69: NEW: EDR | B69: preferred | C69: Hands-on exposure to EDR, SIEM, or forensic tooling | D69: Y
A70: Cloud Computing | B70: required | C70: Windows, Linux, macOS, and cloud environments | D70: Y | E70: added from B; A/B resolution, AI-assisted adjudication 2026-10-29, see resolution.xlsx
A71: NEW: Chain of Custody | B71: required | C71: chain-of-custody requirements | D71: Y | E71: added from B; A/B resolution, AI-assisted adjudication 2026-10-29, see resolution.xlsx

Sheet JD-CY-0005
A1: JD-CY-0005 | CYBER_ANALYST | L1 Security Analyst (junior)
A2: Read the JD, then go down to the table. Mark every pre-filled row keep = Y (correct, fix the cells if needed) or N (wrong). Add missing skills on the empty rows with keep = Y. Yellow rows still need a Y or N.
A3: Go to the label table
A4: Job description
A5: Key Responsibilities
A7: * Monitor security alerts and logs from various security tools such as SIEM (Security Information and Event Management) systems, firewalls, antivirus, and intrusion detection/prevention systems.
A8: * Investigate and analyze potential security incidents or breaches and escalate as necessary to senior analysts or incident response teams.
A9: * Perform routine security assessments and vulnerability scans to identify and report risks.
A10: * Assist in maintaining and updating security documentation, policies, and procedures.
A11: * Participate in security awareness training programs for employees.
A12: * Support compliance efforts with relevant regulations and standards (e.g., GDPR, HIPAA, PCI-DSS).
A13: * Collaborate with IT teams to implement security controls and mitigate identified risks.
... A29: Perks and benefits: Medical; Miscellaneous allowance; Dental; Sports (e.g. Gym); Parking
A31: skill_name | B31: importance | C31: evidence_text | D31: keep | E31: note
A32: SIEM | B32: required | C32: * Monitor security alerts and logs from various security tools such as SIEM (Security Information and Event Management) systems, firewalls, antivirus, and intrusion detection/prevention systems | D32: Y
A33: Incident Response | B33: required | C33: * Investigate and analyze potential security incidents or breaches and escalate as necessary to senior analysts or incident response teams | D33: Y
A34: Documentation | B34: required | C34: * Assist in maintaining and updating security documentation, policies, and procedures | D34: Y
A35: Cybersecurity | B35: required | C35: * Stay updated with the latest cybersecurity trends, threats, and technologies | D35: Y
A36: Communication | B36: required | C36: * Good communication skills for documenting incidents and collaborating with teams | D36: Y
A37: Vulnerability Assessment | B37: required | C37: Perform routine security assessments and vulnerability scans | D37: Y
A38: Security Frameworks | B38: required | C38: relevant regulations and standards (e.g., GDPR, HIPAA, PCI-DSS) | D38: Y
A39: Networking | B39: required | C39: Basic understanding of network protocols | D39: Y
A40: Problem Solving | B40: required | C40: Strong analytical and problem-solving skills. | D40: Y
A41: Teamwork | B41: required | C41: Collaborate with IT teams to implement security controls | D41: Y
A42: Risk Analysis | B42: required | C42: mitigate identified risks | D42: Y
A43: Log Analysis | B43: required | C43: Monitor security alerts and logs | D43: Y
A44: Security Operations (SOC) | B44: required | C44: Monitor security alerts and logs from various security tools | D44: Y
A45: Firewall Management | B45: required | C45: Monitor security alerts and logs from various security tools such as SIEM (Security Information and Event Management) systems, firewalls | D45: Y | E45: importance preferred -> required (duty); A/B resolution, AI-assisted adjudication 2026-10-29, see resolution.xlsx
A46: NEW: Intrusion Detection/Prevention | B46: required | C46: intrusion detection/prevention systems | D46: Y | E46: renamed (R1); A/B resolution, AI-assisted adjudication 2026-10-29, see resolution.xlsx
A47: NEW: Antivirus | B47: required | C47: antivirus | D47: Y | E47: added from B; A/B resolution, AI-assisted adjudication 2026-10-29, see resolution.xlsx
A48: NEW: Operating Systems | B48: required | C48: Basic understanding of network protocols, operating systems | D48: Y | E48: added from B; A/B resolution, AI-assisted adjudication 2026-10-29, see resolution.xlsx

Sheet JD-CY-0006
A1: JD-CY-0006 | CYBER_ANALYST | Junior Cyber Security Analyst (junior)
A2: Read the JD, then go down to the table. Mark every pre-filled row keep = Y (correct, fix the cells if needed) or N (wrong). Add missing skills on the empty rows with keep = Y. Yellow rows still need a Y or N.
A3: Go to the label table
A4: Job description
A5: Continuous Security Monitoring Execute 24/7
A7: * Continuous monitoring of security events across enterprise infrastructure using SIEM platforms.
A8: * Analyze correlated security alerts to identify active threats, suspicious behaviors, and false positives.
A9: * Maintain baseline awareness of system traffic patterns and flag anomalous volume or connection spikes.
A11: Incident Triage & Tier-2 Escalation Perform
A13: * Initial investigation and scope analysis for confirmed security events and policy violations.
A14: * Document comprehensive triage findings, context, and impact assessments within incident tracking tickets.
A15: * Escalate complex or high-severity threats to L2 SOC Analysts, Incident Response, or Engineering units.
... A27: Perks and benefits: Flexible schedule; Maternity leave
A29: skill_name | B29: importance | C29: evidence_text | D29: keep | E29: note
A30: Security Operations (SOC) | B30: required | C30: Continuous Security Monitoring Execute 24/7 | D30: Y
A31: Monitoring & Observability | B31: required | C31: * Continuous monitoring of security events across enterprise infrastructure using SIEM platforms | D31: N
A32: SIEM | B32: required | C32: * Continuous monitoring of security events across enterprise infrastructure using SIEM platforms | D32: Y
A33: Incident Response | B33: required | C33: * Escalate complex or high-severity threats to L2 SOC Analysts, Incident Response, or Engineering units | D33: Y
A34: Threat Intelligence | B34: required | C34: * Utilize threat intelligence feeds and known Indicators of Compromise (IOCs) for targeted environment queries | D34: Y
A35: Log Analysis | B35: required | C35: Collect, parse, and validate ingestion from multi-vendor sources | D35: Y
A36: Documentation | B36: required | C36: Document comprehensive triage findings | D36: Y
A37: Network Security | B37: required | C37: enterprise network traffic | D37: Y

Sheet JD-CY-0007
A1: JD-CY-0007 | CYBER_ANALYST | Security Analyst (junior)
A2: Read the JD, then go down to the table. Mark every pre-filled row keep = Y (correct, fix the cells if needed) or N (wrong). Add missing skills on the empty rows with keep = Y. Yellow rows still need a Y or N.
A3: Go to the label table
A4: Job description
A5: Key Responsibilities
A7: * Monitor security events and alerts from SIEM tools and other security platforms.
A8: * Perform initial analysis and triage of security incidents based on standard operating procedures (SOPs).
A9: * Escalate verified incidents to L2/L3 analysts or Incident Response team when necessary.
A10: * Document alerts, investigations, and incident handling actions accurately in ticketing systems.
A11: * Perform basic threat intelligence lookups and log analysis to support investigations.
A12: * Follow defined playbooks and assist in fine-tuning alert rules and use cases.
A13: * Support daily health checks on security monitoring tools and systems.
... A28: * Understanding of cybersecurity fundamentals and common attack techniq
A30: skill_name | B30: importance | C30: evidence_text | D30: keep | E30: note
A31: SIEM | B31: required | C31: * Monitor security events and alerts from SIEM tools and other security platforms | D31: Y
A32: Incident Response | B32: required | C32: * Escalate verified incidents to L2/L3 analysts or Incident Response team when necessary | D32: Y
A33: Threat Intelligence | B33: required | C33: * Perform basic threat intelligence lookups and log analysis to support investigations | D33: Y
A34: Log Analysis | B34: required | C34: * Perform basic threat intelligence lookups and log analysis to support investigations | D34: Y
A35: Security Operations (SOC) | B35: required | C35: * Support daily health checks on security monitoring tools and systems | D35: Y
A36: Cybersecurity | B36: required | C36: * Maintain awareness of current cybersecurity threats and trends | D36: Y
A37: Networking | B37: required | C37: * Basic understanding of networking concepts (TCP/IP, DNS, firewalls, etc | D37: Y
A38: Splunk | B38: preferred | C38: Familiarity with SIEM tools (e.g., Splunk, QRadar, LogRhythm). | D38: Y
A39: Linux | B39: required | C39: * Basic knowledge of Windows and Linux operating systems | D39: Y
A40: Documentation | B40: required | C40: Document alerts, investigations, and incident handling actions | D40: Y
A41: NEW: Windows | B41: required | C41: Basic knowledge of Windows and Linux operating systems. | D41: Y
A42: NEW: QRadar | B42: preferred | C42: QRadar | D42: Y
A43: NEW: LogRhythm | B43: preferred | C43: LogRhythm | D43: Y

Sheet JD-CY-0008
A1: JD-CY-0008 | CYBER_ANALYST | Internship for Cyber Security Students - RM2,000 for Top Students (entry)
A2: Read the JD, then go down to the table. Mark every pre-filled row keep = Y (correct, fix the cells if needed) or N (wrong). Add missing skills on the empty rows with keep = Y. Yellow rows still need a Y or N.
A3: Go to the label table
A4: Job description
A5: You will join our [COMPANY] Security team in charge of the overall security posture of the company. As part of SecOps, we overlook the security and threat aspects of [COMPANY] and work hand in hand together with other departments. If you will like to experience how the security team work and consistently update your knowledge on all those new emerging threats, join us on our journey!
A7: Responsibilities
A9: * Testing and implementation of new security-related project. (SIEM / endpoint related)
A10: * Help out with daily monitoring of security solutions in the environment.
A11: * Enhance email phishing exercise for internal staffs.
A12: * Ad hoc assignment.
A14: Requirements
A16: * Candidate must possess or currently pursuing in Degree in computer Science/ IT security or equivalent.
... A19: * Available for duration of 3-6 months.
A21: skill_name | B21: importance | C21: evidence_text | D21: keep | E21: note
A22: SIEM | B22: required | C22: (SIEM / endpoint related) | D22: Y
A23: Monitoring & Observability | B23: required | C23: * Help out with daily monitoring of security solutions in the environment | D23: N
A24: Security Operations (SOC) | B24: required | C24: Help out with daily monitoring of security solutions in the environment. | D24: Y
A25: Cybersecurity | B25: preferred | C25: good understanding in Security and Network related concept | D25: Y
A26: Networking | B26: preferred | C26: good understanding in Security and Network related concept | D26: Y
A27: Self-Motivation | B27: required | C27: Able to work independently and fast learner. | D27: Y
A28: NEW: Security Awareness Training | B28: required | C28: Enhance email phishing exercise for internal staffs. | D28: Y

Sheet JD-CY-0009
A1: JD-CY-0009 | CYBER_ANALYST | IT Intern (entry)
A2: Read the JD, then go down to the table. Mark every pre-filled row keep = Y (correct, fix the cells if needed) or N (wrong). Add missing skills on the empty rows with keep = Y. Yellow rows still need a Y or N.
A3: Go to the label table
A4: Job description
A5: About the role
A7: This is a full-time hybrid role for an IT Intern with a six-month duration, based in Setia Alam. The role offers a combination of on-site and remote work flexibility. The IT Intern will assist in software development, software testing, network administration, perform troubleshooting, and ensure systems' reliability and security. Additionally, the intern will support network security initiatives and provide customer service by addressing IT-related inquiries and concerns.
A9: Key responsibilities
A11: * Assist in software development
A12: * Perform software testing
A13: * Support network administration
A14: * Perform troubleshooting to resolve technical issues
A15: * Ensure systems' reliability and security
... A27: * Hands-on experience with IT systems and networks is a plus
A29: skill_name | B29: importance | C29: evidence_text | D29: keep | E29: note
A30: Problem Solving | B30: required | C30: The IT Intern will assist in software development, software testing, network administration, perform troubleshooting, and ensure systems' reliability and security | D30: Y
A31: Network Security | B31: required | C31: Support network security initiatives | D31: Y
A32: Customer Focus | B32: required | C32: Additionally, the intern will support network security initiatives and provide customer service by addressing IT-related inquiries and concerns | D32: Y
A33: PHP | B33: preferred | C33: * Familiarity with PHP, Java, and Network Security practices to support secure system operations | D33: Y
A34: Java | B34: preferred | C34: * Familiarity with PHP, Java, and Network Security practices to support secure system operations | D34: Y
A35: NEW: Software Development | B35: required | C35: Proficiency in Software Development | D35: Y
A36: NEW: Software Testing | B36: required | C36: Perform software testing | D36: Y
A37: Networking | B37: required | C37: Support network administration | D37: Y
A38: Communication | B38: required | C38: communicate effectively | D38: Y
A39: Teamwork | B39: required | C39: Ability to work both independently and collaboratively | D39: Y
A40: Self-Motivation | B40: required | C40: Ability to work both independently | D40: Y

Sheet JD-CY-0010
A1: JD-CY-0010 | CYBER_ANALYST | Cybersecurity Trainee (entry)
A2: Read the JD, then go down to the table. Mark every pre-filled row keep = Y (correct, fix the cells if needed) or N (wrong). Add missing skills on the empty rows with keep = Y. Yellow rows still need a Y or N.
A3: Go to the label table
A4: Job description
A5: Passionate about cybersecurity and eager to learn? Here’s your chance to gain real-world experience and kickstart your career in tech with [COMPANY]!
A6: We're looking for a highly motivated Cybersecurity Intern to join our Security Operations Center (SOC). This is your chance to work alongside industry experts, develop essential cybersecurity skills, and lay the foundation for a successful career in cybersecurity.
A8: What You’ll Do
A10: * Assist in Security Event Monitoring – Work alongside SOC Analysts to track alerts, logs, and security incidents.
A11: * Support Incident Investigations – Learn to analyze security threats, document findings, and escalate potential risks.
A12: * Conduct Basic Security Assessments – Assist in vulnerability scanning, penetration testing, and compliance checks.
A13: * Participate in Cybersecurity Research & Training – Stay updated on emerging threats, attack vectors, and security frameworks.
A14: * Contribute to SOC Operations & Security Awareness – Help develop security policies, training materials, and best practices.
... A24: Perks and benefits: Work with real cybersecurity threats in a dynamic SOC environment; Potential career progression into a permanent SOC role; Hands-on experience with industry professionals and security tools
A26: skill_name | B26: importance | C26: evidence_text | D26: keep | E26: note
A27: Cybersecurity | B27: required | C27: Passionate about cybersecurity and eager to learn? Here’s your chance to gain real-world experience and kickstart your career in tech with [COMPANY]! | D27: Y
A28: Security Operations (SOC) | B28: required | C28: We're looking for a highly motivated Cybersecurity Intern to join our Security Operations Center (SOC) | D28: Y
A29: Monitoring & Observability | B29: required | C29: * Assist in Security Event Monitoring – Work alongside SOC Analysts to track alerts, logs, and security incidents | D29: N
A30: Vulnerability Assessment | B30: required | C30: * Conduct Basic Security Assessments – Assist in vulnerability scanning, penetration testing, and compliance checks | D30: Y
A31: Ethical Hacking | B31: required | C31: * Conduct Basic Security Assessments – Assist in vulnerability scanning, penetration testing, and compliance checks | D31: Y
A32: Security Frameworks | B32: required | C32: * Participate in Cybersecurity Research & Training – Stay updated on emerging threats, attack vectors, and security frameworks | D32: Y
A33: Threat Intelligence | B33: required | C33: * Passionate about cybersecurity – Interested in SOC operations, ethical hacking, or cyber threat intelligence | D33: Y
A34: Networking | B34: required | C34: * Basic understanding of networking & security concepts – Familiar with firewalls, malware analysis, TCP/IP, and operating systems | D34: Y
A35: Malware Analysis | B35: preferred | C35: Familiar with firewalls, malware analysis, TCP/IP | D35: Y
A36: Communication | B36: required | C36: * Strong communication & teamwork skills – Work effectively with SOC professionals and security engineers | D36: Y
A37: Teamwork | B37: required | C37: * Strong communication & teamwork skills – Work effectively with SOC professionals and security engineers | D37: Y
A38: Firewall Management | B38: preferred | C38: Familiar with firewalls, malware analysis, TCP/IP | D38: Y
... A42: Research Skills | B42: required | C42: Participate in Cybersecurity Research & Training | D42: Y

Sheet JD-DA-0001
A1: JD-DA-0001 | DATA_ANALYST | Business Data Analyst – AI Tools & Growth (junior)
A2: Read the JD, then go down to the table. Mark every pre-filled row keep = Y (correct, fix the cells if needed) or N (wrong). Add missing skills on the empty rows with keep = Y. Yellow rows still need a Y or N.
A3: Go to the label table
A4: Job description
A5: Most data analyst jobs mean making the same report every Monday. This one doesn't.
A6: We are a Malaysian healthcare products company. We supply medical, rehab and pet products to clinics and pharmacies across the country, and sell our own brands on Shopee, Lazada and TikTok Shop. Every order, invoice and delivery is already in our own systems, and we already build our own dashboards and tools with AI.
A7: We need a statistician who wants to use that data to decide where the company grows next, and then build the tools that make it happen.
A9: What you will do
A11: 1. Find growth: which customers, products, areas and sales channels we should push next, proven with numbers before we spend money.
A12: 2. Build monitoring tools: dashboards and alerts that catch problems early, such as a clinic that stopped reordering, a product about to run out, or a sales territory falling behind target.
A13: 3. Track what works: measure every promotion, campaign and product launch, and tell us honestly whether it made money.
A14: 4. Use artificial intelligence (AI) to build: write SQL and Python with AI tools such as Claude, ChatGPT or Copilot, and turn an idea into a working tool in days, not months.
... A32: Perks and benefits: Direct access to management; Room to grow into data science, machine learning and business strategy; EPF, SOCSO, EIS
A34: skill_name | B34: importance | C34: evidence_text | D34: keep | E34: note
A35: Monitoring & Observability | B35: required | C35: Build monitoring tools: dashboards and alerts that catch problems early, such as a clinic that stopped reordering, a product about to run out, or a sales territory falling behind target | D35: N
A36: AI Literacy | B36: required | C36: Use artificial intelligence (AI) to build: write SQL and Python with AI tools such as Claude, ChatGPT or Copilot, and turn an idea into a working tool in days, not months | D36: N | E36: dropped: same sentence is Generative AI; guide rule R4 applied after the A/B resolution (AI-assisted, 2026-10-29)
A37: SQL | B37: required | C37: Use artificial intelligence (AI) to build: write SQL and Python with AI tools such as Claude, ChatGPT or Copilot, and turn an idea into a working tool in days, not months | D37: Y
A38: Python | B38: required | C38: Use artificial intelligence (AI) to build: write SQL and Python with AI tools such as Claude, ChatGPT or Copilot, and turn an idea into a working tool in days, not months | D38: Y
A39: Statistical Analysis | B39: required | C39: We need a statistician who wants to use that data to decide where the company grows next | D39: Y | E39: evidence was the degree line; replaced with a skill sentence (assisted review, 2026-10-29)
A40: Power BI | B40: bonus | C40: Power BI is a plus | D40: Y
A41: Machine Learning | B41: required | C41: Room to grow into data science, machine learning and business strategy | D41: N
A42: Data Visualisation | B42: required | C42: dashboards and alerts that catch problems early | D42: Y
A43: Data Analysis | B43: required | C43: use that data to decide where the company grows next | D43: Y
A44: Excel | B44: required | C44: Good with Excel | D44: Y
A45: R | B45: required | C45: comfortable with at least one of SQL, Python or R | D45: Y
A46: Generative AI | B46: required | C46: write SQL and Python with AI tools such as Claude, ChatGPT or Copilot | D46: Y
A47: Communication | B47: required | C47: explain your findings in plain language that leads to a decision | D47: Y
A48: Stakeholder Communication | B48: required | C48: sit with the sales team and management | D48: Y
A49: Critical Thinking | B49: required | C49: Curious about how a business makes money | D49: Y
A50: NEW: Forecasting | B50: required | C50: A forecast of which products will run short next month | D50: Y

Sheet JD-DA-0002
A1: JD-DA-0002 | DATA_ANALYST | Digital & Automation Intern (entry)
A2: Read the JD, then go down to the table. Mark every pre-filled row keep = Y (correct, fix the cells if needed) or N (wrong). Add missing skills on the empty rows with keep = Y. Yellow rows still need a Y or N.
A3: Go to the label table
A4: Job description
A5: Department: Customer Service & Logistics (CS&L) – Customer Engagement
A6: Duration: 4 to 6 Months
A8: About the Role
A10: Are you passionate about using technology to solve real-world operational challenges? At [COMPANY], our Customer Service & Logistics (CS&L) department manages a massive, complex supply chain network.
A11: As a Digital & Automation Intern, you will be placed directly within the Customer Engagement function under the CS&L team. Your core mission will be helping the team digitalize and automate their daily tasks, manual workflows, and reporting processes. You won't just be maintaining systems; you will act as an internal "Citizen Developer," identifying manual bottlenecks and building automated solutions that directly improve how efficiently we engage with our B2B customers and deliver our products globally.
A13: Key Responsibilities
A15: * Process Automation: Identify highly manual, repetitive tasks within the Customer Engagement workflow and develop automated solutions (using tools like Power Automate, VBA, or basic scripting) to increase efficiency and reduce manual data entry.
A16: * Digitalizing Workflows: Transform traditional paper-based or manual tracker processes into streamlined, digital workflows that the Customer Engagement team can easily adopt.
... A31: Perks and benefits: Build and deploy digital solutions used by a global FMCG company; Mentorship from experienced professionals; Dynamic, inclusive environment
A33: skill_name | B33: importance | C33: evidence_text | D33: keep | E33: note
A34: Customer Focus | B34: required | C34: Department: Customer Service & Logistics (CS&L) – Customer Engagement | D34: N
A35: Power BI | B35: required | C35: , using DOMO, PowerBI, or Tableau) to track customer service KPIs, order fulfillment rates, and logistics data | D35: Y
A36: Tableau | B36: required | C36: , using DOMO, PowerBI, or Tableau) to track customer service KPIs, order fulfillment rates, and logistics data | D36: Y
A37: AI Literacy | B37: required | C37: * Currently pursuing a Bachelor’s Degree in Computer Science, Information Technology, Artificial Intelligence, Software Engineering, Data Science, or a related technical field | D37: N
A38: Python | B38: required | C38: , Python, SQL, VBA) and automation platforms (e | D38: Y
A39: SQL | B39: required | C39: , Python, SQL, VBA) and automation platforms (e | D39: Y
A40: Communication | B40: required | C40: * Excellent communication skills—specifically the ability to explain technical concepts to non-technical business stakeholders | D40: Y
A41: Data Visualisation | B41: required | C41: Design, build, and maintain dynamic BI dashboards | D41: Y
A42: Process Mapping | B42: required | C42: process mapping | D42: Y
A43: User Acceptance Testing | B43: required | C43: user acceptance testing (UAT) | D43: Y
A44: Problem Solving | B44: required | C44: A strong problem-solving mindset | D44: Y
A45: Stakeholder Communication | B45: required | C45: explain technical concepts to non-technical business stakeholders | D45: Y
... A51: NEW: User Training | B51: required | C51: training non-technical customer service and logistics coordinators | D51: Y

Sheet JD-DA-0003
A1: JD-DA-0003 | DATA_ANALYST | Data Analyst (Fresh Graduate) (junior)
A2: Read the JD, then go down to the table. Mark every pre-filled row keep = Y (correct, fix the cells if needed) or N (wrong). Add missing skills on the empty rows with keep = Y. Yellow rows still need a Y or N.
A3: Go to the label table
A4: Job description
A5: Graduate With a Degree. Leave With Real Data Experience.
A6: Your first job can be more than an entry-level title.
A7: Start your career working with real data, real business problems, modern AI tools, and experienced mentors — while building the technical skills companies actually look for in data professionals.
A8: Fresh graduates are welcome. No years of experience required. If you know SQL, understand data, and have the curiosity to keep learning, we'll help you take the next step.
A10: Key responsibilities
A12: * Data Extraction & Wrangling — write efficient SQL queries across our cloud data warehouse (Google BigQuery) to extract, validate, and transform multi-source business data.
A13: * Exploratory & Diagnostic Analysis — investigate operational workflows, transaction lifecycles, and unit economics to diagnose root causes and identify optimization opportunities.
A14: * Reporting & Visualisation — build and maintain clean data reports, performance tracking scorecards, and interactive dashboards to monitor key operational and financial metrics.
... A31: Perks and benefits: Medical Coverage; Well-being Benefit; Group Insurance Coverage; Learning & Development
A33: skill_name | B33: importance | C33: evidence_text | D33: keep | E33: note
A34: SQL | B34: required | C34: If you know SQL, understand data, and have the curiosity to keep learning, we'll help you take the next step | D34: Y
A35: Data Warehousing | B35: required | C35: * Data Extraction & Wrangling — write efficient SQL queries across our cloud data warehouse (Google BigQuery) to extract, validate, and transform multi-source business data | D35: Y
A36: GCP | B36: required | C36: * Data Extraction & Wrangling — write efficient SQL queries across our cloud data warehouse (Google BigQuery) to extract, validate, and transform multi-source business data | D36: Y
A37: Stakeholder Communication | B37: required | C37: * Stakeholder Collaboration — partner with cross-functional teams (Operations, Product & Tech, Finance) to establish clear metric definitions and maintain data integrity | D37: Y
A38: Python | B38: required | C38: * Workflow Automation & Tooling — leverage Python and modern developer tools to automate recurring analytical pipelines and data hygiene checks | D38: Y
A39: Statistical Analysis | B39: required | C39: Basic understanding of data analysis, statistics, and data visualisation. | D39: Y | E39: evidence was the degree line; replaced with a skill sentence (assisted review, 2026-10-29)
A40: Pandas | B40: preferred | C40: * Foundational Python knowledge — familiarity with Python for data manipulation using tools such as pandas and NumPy | D40: Y
A41: NumPy | B41: preferred | C41: * Foundational Python knowledge — familiarity with Python for data manipulation using tools such as pandas and NumPy | D41: Y
A42: Data Analysis | B42: required | C42: * Basic understanding of data analysis, statistics, and data visualisation | D42: Y
A43: Data Visualisation | B43: required | C43: * Basic understanding of data analysis, statistics, and data visualisation | D43: Y
A44: Generative AI | B44: preferred | C44: * Familiarity with AI tools and LLM-based assistants for coding, analysis, prototyping, or productivity | D44: Y
A45: Critical Thinking | B45: required | C45: * Strong problem-solving and analytical thinking | D45: Y
A46: Attention to Detail | B46: required | C46: * High attention to detail and commitment to data accuracy | D46: Y
A47: Communication | B47: required | C47: * Good communication skills and the ability to explain technical findings in clear, simple language | D47: Y
A48: Problem Solving | B48: required | C48: Strong problem-solving and analytical thinking. | D48: Y
A49: ETL | B49: required | C49: extract, validate, and transform multi-source business data | D49: Y
A50: Data Cleaning | B50: required | C50: data hygiene checks | D50: Y
A51: NEW: BigQuery | B51: required | C51: Google BigQuery | D51: Y
A52: NEW: Root Cause Analysis | B52: required | C52: diagnose root causes | D52: Y

Sheet JD-DA-0004
A1: JD-DA-0004 | DATA_ANALYST | Data Analyst Intern (entry)
A2: Read the JD, then go down to the table. Mark every pre-filled row keep = Y (correct, fix the cells if needed) or N (wrong). Add missing skills on the empty rows with keep = Y. Yellow rows still need a Y or N.
A3: Go to the label table
A4: Job description
A5: What you'll do
A7: * Assist in collecting, cleaning, and organising data from various sources.
A8: * Conduct exploratory data analysis to identify trends, patterns, and insights.
A9: * Support the development and maintenance of dashboards and reports for internal stakeholders.
A10: * Collaborate with cross-functional teams to understand data needs and provide analytical solutions.
A11: * Perform data validation and quality checks to ensure accuracy and reliability of data.
A12: * Assist in developing and implementing data-driven strategies to improve business processes.
A13: * Participate in team meetings and contribute to discussions on data analysis and interpretation.
... A26: Perks and benefits: Young collaborative team; Well-stocked pantry
A28: skill_name | B28: importance | C28: evidence_text | D28: keep | E28: note
A29: Data Analysis | B29: required | C29: * Conduct exploratory data analysis to identify trends, patterns, and insights | D29: Y
A30: Statistical Analysis | B30: bonus | C30: Experience with statistical analysis software (e.g., R, Python) is an advantage. | D30: Y
A31: Attention to Detail | B31: required | C31: * Strong analytical and problem-solving skills with a keen attention to detail | D31: Y
A32: Communication | B32: required | C32: * Excellent communication and interpersonal skills | D32: Y
A33: Interpersonal Skills | B33: required | C33: * Excellent communication and interpersonal skills | D33: Y
A34: SQL | B34: required | C34: * Intermediate experience with SQL and data visualisation tools (e | D34: Y
A35: Data Visualisation | B35: required | C35: * Intermediate experience with SQL and data visualisation tools (e | D35: Y
A36: Looker | B36: required | C36: Looker Studio) | D36: Y
A37: Python | B37: bonus | C37: , R, Python) is an advantage | D37: Y
A38: Data Cleaning | B38: required | C38: collecting, cleaning, and organising data | D38: Y
A39: Problem Solving | B39: required | C39: Strong analytical and problem-solving skills | D39: Y
A40: Excel | B40: required | C40: Proficiency in Microsoft Office suite (Word, Excel, PowerPoint). | D40: Y
... A44: NEW: Microsoft Office | B44: required | C44: Proficiency in Microsoft Office suite (Word, Excel, PowerPoint). | D44: Y

Sheet JD-DA-0005
A1: JD-DA-0005 | DATA_ANALYST | Data Analyst (mid)
A2: Read the JD, then go down to the table. Mark every pre-filled row keep = Y (correct, fix the cells if needed) or N (wrong). Add missing skills on the empty rows with keep = Y. Yellow rows still need a Y or N.
A3: Go to the label table
A4: Job description
A5: About [COMPANY]
A7: [COMPANY], an innovative solution designed to simplify and enhance your personal and business financial managements. Our platform curates a diverse range of offerings from approved fintech providers including cross-border transfer, supply chain financing, lending, insurance, and more – all in one place. With robust security and easy accessibility, we empower our users to take control of their financial future with ease.
A9: Key Duties & Responsibilities
A11: * Communicate with stakeholders and understand the entire data extraction requirement.
A12: * Clean input data, then perform bulk data extraction, and check the data integrity, and conduct analysis of the output data in a timely manner.
A13: * Conduct ad hoc analysis to support other departments i.e. sales, marketing, operations, and request from management.
A14: * Identify and rectify data integrity issues and liaise with members and respective data sources/owners.
A15: * Verify and investigate credit rating and score enquiry against the credit information, and provide useful advice to the enquirer for external and internal stakeholders.
... A26: * Good communication and interpersonal skills with attention to details and strong work ethic.
A28: skill_name | B28: importance | C28: evidence_text | D28: keep | E28: note
A29: Statistical Analysis | B29: bonus | C29: Knowledge and experience in SQL and/or Statistic will be an added advantage. | D29: Y
A30: Python | B30: required | C30: * Proficient in Excel and programming languages like Python and SQL | D30: Y
A31: SQL | B31: required | C31: * Proficient in Excel and programming languages like Python and SQL | D31: Y
A32: Communication | B32: required | C32: * Good communication and interpersonal skills with attention to details and strong work ethic | D32: Y
A33: Interpersonal Skills | B33: required | C33: * Good communication and interpersonal skills with attention to details and strong work ethic | D33: Y
A34: Excel | B34: required | C34: Proficient in Excel and programming languages like Python and SQL. | D34: Y
A35: Data Cleaning | B35: required | C35: Clean input data | D35: Y
A36: Data Analysis | B36: required | C36: conduct analysis of the output data | D36: Y
A37: Stakeholder Communication | B37: required | C37: Communicate with stakeholders | D37: Y
A38: Requirements Analysis | B38: required | C38: understand the entire data extraction requirement | D38: Y
A39: Attention to Detail | B39: required | C39: attention to details | D39: Y
A40: Self-Motivation | B40: required | C40: ability to work independently | D40: Y
... A43: NEW: Organisational Skills | B43: required | C43: Strong organizational skills | D43: Y
A44: Documentation | B44: required | C44: Capability to produce detailed and factually accurate and easily comprehensible reports. | D44: Y | E44: was NEW: Report Writing; changed to library skill Documentation (assisted review, 2026-10-29)

Sheet JD-DA-0006
A1: JD-DA-0006 | DATA_ANALYST | Data Management Assistant (junior)
A2: Read the JD, then go down to the table. Mark every pre-filled row keep = Y (correct, fix the cells if needed) or N (wrong). Add missing skills on the empty rows with keep = Y. Yellow rows still need a Y or N.
A3: Go to the label table
A4: Job description
A5: Job Summary
A7: The Data Administrator is responsible for maintaining the accuracy, integrity, and confidentiality of operational data across company systems. This role supports business operations through data entry, record maintenance, process coordination, reporting, and operational research activities. The position plays an important role in ensuring efficient workflows, supporting decision-making, and identifying opportunities for continuous operational improvement.
A9: Key Responsibilities
A11: Data Management & Maintenance
A13: * Enter, update, and maintain data in company systems and databases.
A14: * Ensure data accuracy, completeness, and consistency across multiple platforms.
A15: * Perform regular data audits, validation checks, and cleansing activities.
A16: * Identify and resolve data discrepancies, duplicates, and errors.
... A66: * Good communication and documentation skills.
A68: skill_name | B68: importance | C68: evidence_text | D68: keep | E68: note
A69: Decision Making | B69: required | C69: The position plays an important role in ensuring efficient workflows, supporting decision-making, and identifying opportunities for continuous operational improvement | D69: N
A70: Data Structures & Algorithms | B70: required | C70: * Assist in maintaining data structures and documentation | D70: N
A71: Documentation | B71: required | C71: Good communication and documentation skills. | D71: Y
A72: Data Analysis | B72: required | C72: Assist with basic trend analysis | D72: Y
A73: Excel | B73: required | C73: Advanced Microsoft Excel skills | D73: Y
A74: SQL | B74: bonus | C74: * Basic SQL knowledge is an advantage | D74: Y
A75: Power BI | B75: bonus | C75: * Familiarity with Power BI, Tableau, or reporting tools is a plus | D75: Y
A76: Tableau | B76: bonus | C76: * Familiarity with Power BI, Tableau, or reporting tools is a plus | D76: Y
A77: Attention to Detail | B77: required | C77: * Strong attention to detail and accuracy | D77: Y
A78: Time Management | B78: required | C78: * Excellent organizational and time management skills | D78: Y
A79: Communication | B79: required | C79: * Good communication and documentation skills | D79: Y
A80: Data Cleaning | B80: required | C80: cleansing activities | D80: Y
... A91: NEW: Organisational Skills | B91: required | C91: Excellent organizational and time management skills. | D91: Y

Sheet JD-DA-0007
A1: JD-DA-0007 | DATA_ANALYST | DATA ANALYST (INTERNSHIP) (entry)
A2: Read the JD, then go down to the table. Mark every pre-filled row keep = Y (correct, fix the cells if needed) or N (wrong). Add missing skills on the empty rows with keep = Y. Yellow rows still need a Y or N.
A3: Go to the label table
A4: Job description
A5: About the role
A7: As a growing SME, we're looking to strengthen our operations and decision making with the power of data. We are hiring both Data Analyst (Internship) to support business optimization and strategy development.
A8: Whether you're just stepping into the field or bringing hands-on experience, we want your insights to help shape smarter operations.
A10: What you'll do
A12: * Assist in collecting and cleaning data across departments
A13: * Learn to use Excel, Power BI, and other tools to build basic dashboard
A14: * Support market research and performance tracking
A15: * Gain real-world experience working alongside business teams
... A25: Work location: In person
A27: skill_name | B27: importance | C27: evidence_text | D27: keep | E27: note
A28: Decision Making | B28: required | C28: As a growing SME, we're looking to strengthen our operations and decision making with the power of data | D28: N
A29: Power BI | B29: required | C29: * Learn to use Excel, Power BI, and other tools to build basic dashboard | D29: Y
A30: Statistical Analysis | B30: required | C30: * Pursuing a degree in Business Analytics, Information Technology (IT), or a related field, with coursework in Data Science, Statistics, and Decision Science | D30: N
A31: Data Cleaning | B31: required | C31: Assist in collecting and cleaning data | D31: Y
A32: Excel | B32: required | C32: Learn to use Excel, Power BI | D32: Y
A33: Data Visualisation | B33: required | C33: build basic dashboard | D33: Y
A34: Market Research | B34: required | C34: Support market research | D34: Y
A35: Self-Motivation | B35: required | C35: ready to learn | D35: Y
A36: NEW: Microsoft Office | B36: required | C36: Proficient in Microsoft office | D36: Y

Sheet JD-DA-0008
A1: JD-DA-0008 | DATA_ANALYST | Data Analyst (Fresh Graduate Opportunity) (junior)
A2: Read the JD, then go down to the table. Mark every pre-filled row keep = Y (correct, fix the cells if needed) or N (wrong). Add missing skills on the empty rows with keep = Y. Yellow rows still need a Y or N.
A3: Go to the label table
A4: Job description
A5: Job Descriptions
A7: 1. Data Analysis: Review and analyze telecommunication data from various markets to identify trends, anomalies, and opportunities for improvement.
A8: 2. Data Mining: Extract and analyze large volumes of data to discover patterns and insights.
A9: 3. Data Modelling: Develop statistical models to understand and predict customer behavior or market trends.
A10: 4. Data Profiling: Assess the quality, structure, and integrity of data to ensure it is suitable for analysis or use in business decisions.
A11: 5. Reporting: Create comprehensive reports and visualizations to communicate data-driven insights to internal stakeholders across different regions.
A12: 6. Data Management: Collect, analyze, and store data in an organized manner for efficient retrieval and compliance with international data regulations.
A14: Requirements
... A23: Perks and benefits: Medical; Miscellaneous allowance; Insurance
A25: skill_name | B25: importance | C25: evidence_text | D25: keep | E25: note
A26: Data Analysis | B26: required | C26: Data Analysis: Review and analyze telecommunication data from various markets to identify trends, anomalies, and opportunities for improvement | D26: Y
A27: Data Mining | B27: required | C27: Data Mining: Extract and analyze large volumes of data to discover patterns and insights | D27: Y
A28: Data Modelling | B28: required | C28: Data Modelling: Develop statistical models to understand and predict customer behavior or market trends | D28: Y
A29: Statistical Analysis | B29: required | C29: Statistical Knowledge: Understanding of basic statistics and mathematical concepts. | D29: Y | E29: evidence was the degree line; replaced with a skill sentence (assisted review, 2026-10-29)
A30: Python | B30: required | C30: Technical Skills: Proficiency in data analysis and visualization software (Python, SQL, Excel, Tableau) and basic knowledge of coding languages, machine learning, and software development | D30: Y
A31: SQL | B31: required | C31: Technical Skills: Proficiency in data analysis and visualization software (Python, SQL, Excel, Tableau) and basic knowledge of coding languages, machine learning, and software development | D31: Y
A32: Tableau | B32: required | C32: Technical Skills: Proficiency in data analysis and visualization software (Python, SQL, Excel, Tableau) and basic knowledge of coding languages, machine learning, and software development | D32: Y
A33: Machine Learning | B33: required | C33: Technical Skills: Proficiency in data analysis and visualization software (Python, SQL, Excel, Tableau) and basic knowledge of coding languages, machine learning, and software development | D33: Y
A34: Communication | B34: required | C34: Communication Skills: Excellent written and verbal communication skills | D34: Y
A35: Adaptability | B35: required | C35: Adaptability: Able to adapt to challenges and pressure in a fast-paced environment | D35: Y
A36: Excel | B36: required | C36: (Python, SQL, Excel, Tableau) | D36: Y
A37: Data Visualisation | B37: required | C37: Create comprehensive reports and visualizations | D37: Y
A38: Problem Solving | B38: required | C38: Strong analytical and problem-solving skills | D38: Y
A39: NEW: Data Profiling | B39: required | C39: Assess the quality, structure, and integrity of data | D39: Y
A40: NEW: Software Development | B40: required | C40: basic knowledge of coding languages, machine learning, and software development | D40: Y

Sheet JD-DA-0010
A1: JD-DA-0010 | DATA_ANALYST | Business Intelligence (BI) Intern (entry)
A2: Read the JD, then go down to the table. Mark every pre-filled row keep = Y (correct, fix the cells if needed) or N (wrong). Add missing skills on the empty rows with keep = Y. Yellow rows still need a Y or N.
A3: Go to the label table
A4: Job description
A5: Key Responsibilities
A7: * Power BI Development - Assist in building and maintaining Power BI dashboards and reports. Support basic data modelling, DAX calculations, and data visualisation.
A8: * Data Preparation & Analysis - Help with data extraction, cleansing, and transformation using Excel (e.g. Power Query, Pivot Tables). Ensure data is accurate and ready for reporting.
A9: * Automation Support - Support simple automation tasks using PowerShell or scripts to improve reporting and data processes.
A10: * Programming & Integration - Use Python or other programming languages (where applicable) to support data analysis, basic automation, and API integrations.
A12: Requirements
A14: * Basic understanding of Power BI (Desktop preferred)
A15: * Familiar with Microsoft Excel (Pivot Tables, formulas; Power Query is a plus)
... A29: * Work location: Petaling Jaya, Selangor
A31: skill_name | B31: importance | C31: evidence_text | D31: keep | E31: note
A32: Power BI | B32: required | C32: * Power BI Development - Assist in building and maintaining Power BI dashboards and reports | D32: Y
A33: Data Modelling | B33: required | C33: Support basic data modelling, DAX calculations, and data visualisation | D33: Y
A34: Data Visualisation | B34: required | C34: Support basic data modelling, DAX calculations, and data visualisation | D34: Y
A35: Data Cleaning | B35: required | C35: * Data Preparation & Analysis - Help with data extraction, cleansing, and transformation using Excel (e | D35: Y
A36: PowerShell | B36: required | C36: * Automation Support - Support simple automation tasks using PowerShell or scripts to improve reporting and data processes | D36: Y
A37: Python | B37: required | C37: * Programming & Integration - Use Python or other programming languages (where applicable) to support data analysis, basic automation, and API integrations | D37: Y
A38: Data Analysis | B38: required | C38: * Programming & Integration - Use Python or other programming languages (where applicable) to support data analysis, basic automation, and API integrations | D38: Y
A39: Excel | B39: required | C39: * Familiar with Microsoft Excel (Pivot Tables, formulas | D39: Y
A40: Attention to Detail | B40: required | C40: * Willing to learn, detail-oriented, and able to work in a team | D40: Y
A41: ETL | B41: required | C41: data extraction, cleansing, and transformation | D41: Y
A42: REST API | B42: required | C42: API integrations | D42: Y
A43: Teamwork | B43: required | C43: able to work in a team | D43: Y
... A46: NEW: Power Query | B46: bonus | C46: Power Query is a plus | D46: Y

Sheet JD-DA-0011
A1: JD-DA-0011 | DATA_ANALYST | JUNIOR DATA ANALYST – MANUFACTURING SYSTEMS & PLANNING (junior)
A2: Read the JD, then go down to the table. Mark every pre-filled row keep = Y (correct, fix the cells if needed) or N (wrong). Add missing skills on the empty rows with keep = Y. Yellow rows still need a Y or N.
A3: Go to the label table
A4: Job description
A5: Key Responsibilities
A7: Manufacturing Data Analytics
A9: * Extract, consolidate, validate and analyze data from ERP and other manufacturing systems.
A10: * Develop and maintain operational dashboards, reports and analytical tools using Excel, SQL, Power BI or similar technologies.
A11: * Analyze key manufacturing indicators including production output, WIP, machine utilization, capacity, lead time, order status, schedule adherence and delivery performance.
A12: * Identify trends, abnormalities, bottlenecks and potential risks through data analysis.
A13: * Improve the accuracy, consistency and reliability of operational and management reporting.
A15: ERP & Manufacturing Systems
... A58: * Experience in a manufacturing environment.
A60: skill_name | B60: importance | C60: evidence_text | D60: keep | E60: note
A61: Data Analysis | B61: required | C61: Manufacturing Data Analytics | D61: Y
A62: SQL | B62: required | C62: * Develop and maintain operational dashboards, reports and analytical tools using Excel, SQL, Power BI or similar technologies | D62: Y
A63: Power BI | B63: required | C63: * Develop and maintain operational dashboards, reports and analytical tools using Excel, SQL, Power BI or similar technologies | D63: Y
A64: Data Structures & Algorithms | B64: required | C64: * Develop a strong understanding of ERP manufacturing processes, data structures and business logic | D64: N
A65: Decision Making | B65: required | C65: * Work with users to identify system or data issues affecting production visibility and operational decision-making | D65: N
A66: Statistical Analysis | B66: required | C66: * Statistics / Mathematics | D66: N
A67: Python | B67: bonus | C67: * Knowledge of Python or other analytical/programming tools | D67: Y
A68: Excel | B68: required | C68: using Excel, SQL, Power BI | D68: Y
A69: Data Visualisation | B69: required | C69: Develop and maintain operational dashboards | D69: Y
A70: Business Process Improvement | B70: required | C70: Recommend process, system and data improvements | D70: Y
A71: Requirements Analysis | B71: required | C71: Support user requirement analysis | D71: Y
A72: Teamwork | B72: required | C72: Work closely with Production, PPC, Warehouse, Quality, Sales, Supply Chain | D72: Y
... A76: NEW: Production Planning | B76: bonus | C76: Knowledge of production planning, scheduling, inventory, WIP or capacity planning. | D76: Y

Sheet JD-DS-0001
A1: JD-DS-0001 | DATA_SCIENTIST | Data Science Intern (entry)
A2: Read the JD, then go down to the table. Mark every pre-filled row keep = Y (correct, fix the cells if needed) or N (wrong). Add missing skills on the empty rows with keep = Y. Yellow rows still need a Y or N.
A3: Go to the label table
A4: Job description
A5: About the Role
A7: [COMPANY] AI delivers end-to-end AI solutions, from strategy and model development to deployment, integration, and long-term optimisation. Our engineers build the systems that make AI actually work at scale: pipelines, APIs, integrations, and the infrastructure that keeps everything running. We work across a diverse range of clients and enterprises, in environments where reliability and performance are not optional.
A8: We are looking for a Data Science Intern who can support our engineering and delivery teams in preparing, exploring, and modelling the data that feeds our internal systems and tooling. During this internship, you'll be working with real datasets, real constraints, and real deliverables, alongside consultants and engineers who expect you to bring rigour, not just curiosity.
A10: Who You Are
A12: * Currently pursuing or recently completed a degree in Data Science, Computer Science, Statistics, Engineering, or a related quantitative field
A13: * Comfortable with ambiguity as client data can be messy, priorities shift, and you won't always get a clean brief
A14: * Genuinely interested in how AI systems behave in production
A15: * Able to explain your reasoning and your results to people who are not technical
... A31: * You flag data quality or scope issues proactively, before they become someone else's problem
A33: skill_name | B33: importance | C33: evidence_text | D33: keep | E33: note
A34: Statistical Analysis | B34: required | C34: * Currently pursuing or recently completed a degree in Data Science, Computer Science, Statistics, Engineering, or a related quantitative field | D34: N
A35: Python | B35: required | C35: * Proficiency in Python for data work (pandas, numpy, and at least one ML library such as scikit-learn) | D35: Y
A36: Pandas | B36: required | C36: * Proficiency in Python for data work (pandas, numpy, and at least one ML library such as scikit-learn) | D36: Y
A37: NumPy | B37: required | C37: * Proficiency in Python for data work (pandas, numpy, and at least one ML library such as scikit-learn) | D37: Y
A38: Machine Learning | B38: required | C38: * Proficiency in Python for data work (pandas, numpy, and at least one ML library such as scikit-learn) | D38: Y
A39: Scikit-learn | B39: required | C39: * Proficiency in Python for data work (pandas, numpy, and at least one ML library such as scikit-learn) | D39: Y
A40: SQL | B40: required | C40: * Working knowledge of SQL | D40: Y
A41: Data Cleaning | B41: required | C41: * Experience with data cleaning, exploratory data analysis, and visualisation | D41: Y
A42: Data Analysis | B42: required | C42: * Experience with data cleaning, exploratory data analysis, and visualisation | D42: Y
A43: Leadership | B43: required | C43: * Strong written English, since findings get communicated to the team and leadership, not just left in a notebook | D43: N
A44: Model Evaluation | B44: required | C44: how to evaluate a model honestly | D44: Y
A45: Data Visualisation | B45: required | C45: exploratory data analysis, and visualisation | D45: Y
... A48: Adaptability | B48: required | C48: Comfortable with ambiguity | D48: Y

Sheet JD-DS-0002
A1: JD-DS-0002 | DATA_SCIENTIST | Data Science & AI Internship (entry)
A2: Read the JD, then go down to the table. Mark every pre-filled row keep = Y (correct, fix the cells if needed) or N (wrong). Add missing skills on the empty rows with keep = Y. Yellow rows still need a Y or N.
A3: Go to the label table
A4: Job description
A5: Job Scope
A7: * Assist the team to develop and deploy AI use cases from business users.
A8: * Support the team in research and development (R&D) of features that are part of a larger AI system.
A9: * Assist with data processing, chatbot evaluation, AI model evaluation, and building RPA pipelines.
A10: * Support multiple concurrent tasks and use cases as required by the team.
A12: Contribute to company transformation initiatives through projects such as:
A14: * Building RPA solutions for agency teams.
A15: * Building monitoring dashboards.
... A30: Perks and benefits: Miscellaneous allowance; Monthly Incentive, Free Oversea Convention
A32: skill_name | B32: importance | C32: evidence_text | D32: keep | E32: note
A33: Model Evaluation | B33: required | C33: * Assist with data processing, chatbot evaluation, AI model evaluation, and building RPA pipelines | D33: Y
A34: Monitoring & Observability | B34: required | C34: * Building monitoring dashboards | D34: N
A35: Python | B35: preferred | C35: Learn and gain exposure to: | D35: Y
A36: Cloud Computing | B36: preferred | C36: Learn and gain exposure to: | D36: Y
A37: SQL | B37: preferred | C37: Learn and gain exposure to: | D37: Y
A38: Data Visualisation | B38: required | C38: Building monitoring dashboards. | D38: Y
A39: Research Skills | B39: required | C39: research and development (R&D) | D39: N | E39: dropped: R&D names an activity; A/B resolution, AI-assisted adjudication 2026-10-29, see resolution.xlsx
A40: AI Literacy | B40: required | C40: Assist the team to develop and deploy AI use cases | D40: Y
A41: NEW: Robotic Process Automation | B41: required | C41: building RPA pipelines | D41: Y
A42: NEW: Data Labelling | B42: required | C42: Helping build labelled datasets for model evaluation. | D42: Y

Sheet JD-DS-0003
A1: JD-DS-0003 | DATA_SCIENTIST | AI Intern – Computer Vision & Multimodal RAG (entry)
A2: Read the JD, then go down to the table. Mark every pre-filled row keep = Y (correct, fix the cells if needed) or N (wrong). Add missing skills on the empty rows with keep = Y. Yellow rows still need a Y or N.
A3: Go to the label table
A4: Job description
A5: About the Team
A7: The [COMPANY] IT AI Solutions & Innovation Team is responsible for delivering cutting-edge AI solutions to global customers and strategic partners. Our team works closely with world-class organizations and events such as FIFA, Formula 1 (F1), and other enterprise customers to design, develop, and deploy AI-powered applications that create real business value and enhance user experiences.
A8: We are looking for passionate AI Interns who are eager to learn, explore emerging technologies, and contribute to real-world AI projects involving Computer Vision, Multimodal AI, and Retrieval-Augmented Generation (RAG).
A10: Responsibilities
A12: As an AI Intern, you will work alongside experienced AI engineers and solution architects to support the development and delivery of customer-facing AI solutions. Key responsibilities include:
A14: * Participate in AI projects serving external customers, including sports and entertainment organizations such as FIFA, F1, and other global enterprises.
A15: * Collaborate with customers and internal stakeholders to understand business requirements and translate them into AI solutions.
A16: * Develop and test AI applications based on Computer Vision and Multimodal RAG technologies.
... A76: Perks and benefits: Hands-on experience building enterprise-grade AI solutions; Exposure to global customer projects and large-scale events; Mentorship from experienced AI architects and engineers; Work with LLMs, Computer Vision, Multimodal AI and AI Agents
A78: skill_name | B78: importance | C78: evidence_text | D78: keep | E78: note
A79: Computer Vision | B79: required | C79: We are looking for passionate AI Interns who are eager to learn, explore emerging technologies, and contribute to real-world AI projects involving Computer Vision, Multimodal AI, and Retrieval-Augmented Generation (RAG) | D79: Y
A80: Requirements Analysis | B80: required | C80: * Collaborate with customers and internal stakeholders to understand business requirements and translate them into AI solutions | D80: Y
A81: ETL | B81: required | C81: * Build data pipelines, model evaluation workflows, and proof-of-concept demonstrations | D81: Y
A82: Model Evaluation | B82: required | C82: * Build data pipelines, model evaluation workflows, and proof-of-concept demonstrations | D82: Y
A83: UI/UX Design | B83: required | C83: * Fine-tune and optimize AI models to improve performance, accuracy, and user experience | D83: N
A84: AI Literacy | B84: required | C84: Participate in AI projects serving external customers | D84: Y | E84: evidence was a degree subject; replaced with a duty; guide rule R4 applied after the A/B resolution (AI-assisted, 2026-10-29)
A85: Generative AI | B85: required | C85: * Strong interest in Generative AI, Computer Vision, and Multimodal AI | D85: Y
A86: Python | B86: required | C86: * Solid programming skills in Python | D86: Y
A87: Machine Learning | B87: preferred | C87: * Familiarity with machine learning and deep learning fundamentals | D87: Y
A88: Deep Learning | B88: preferred | C88: * Familiarity with machine learning and deep learning fundamentals | D88: Y
A89: Prompt Engineering | B89: required | C89: * Basic understanding of LLMs, RAG, vector databases, and prompt engineering | D89: Y
A90: PyTorch | B90: preferred | C90: * PyTorch | D90: Y
A91: TensorFlow | B91: preferred | C91: * TensorFlow | D91: Y
A92: Hugging Face | B92: preferred | C92: * Hugging Face | D92: Y
A93: Self-Motivation | B93: required | C93: Self-motivated, proactive, and able to work effectively in a fast-paced environment. | D93: Y
A94: Communication | B94: required | C94: Good communication skills | D94: Y
A95: Cloud Computing | B95: bonus | C95: * Experience with cloud platforms such as AWS, Azure, Google Cloud, or [COMPANY] AI platforms | D95: Y
A96: AWS | B96: bonus | C96: * Experience with cloud platforms such as AWS, Azure, Google Cloud, or [COMPANY] AI platforms | D96: Y
... A113: NEW: Agentic AI | B113: bonus | C113: Agentic AI Workflows | D113: Y

Sheet JD-DS-0004
A1: JD-DS-0004 | DATA_SCIENTIST | Data Scientist Executive (Decision Intelligence) (junior)
A2: Read the JD, then go down to the table. Mark every pre-filled row keep = Y (correct, fix the cells if needed) or N (wrong). Add missing skills on the empty rows with keep = Y. Yellow rows still need a Y or N.
A3: Go to the label table
A4: Job description
A5: Key Responsibilities
A7: * What-if Simulation
A8: * Develop simulation models to evaluate business scenarios.
A9: * Assess impact of pricing, display, and stock changes.
A10: * Allocation Optimization
A11: * Design optimization models for inventory allocation across stores.
A12: * Balance constraints such as stock availability, demand, and capacity.
A13: * Dashboarding and Analytics
... A32: * Able to think from a business perspective and translate business problems into data-driven solutions.
A34: skill_name | B34: importance | C34: evidence_text | D34: keep | E34: note
A35: Model Evaluation | B35: bonus | C35: * Model Evaluation (Added Advantage) | D35: Y
A36: Data Analysis | B36: required | C36: * Data Analysis | D36: Y
A37: SQL | B37: required | C37: * Proficiency in Excel, SQL, BI tools, and Python (e | D37: Y
A38: Python | B38: required | C38: * Proficiency in Excel, SQL, BI tools, and Python (e | D38: Y
A39: Pandas | B39: required | C39: pandas, scikit-learn) | D39: Y
A40: Scikit-learn | B40: required | C40: pandas, scikit-learn) | D40: Y
A41: Communication | B41: required | C41: * Good communication skills with the ability to present data insights and recommendations to stakeholders | D41: Y
A42: Machine Learning | B42: bonus | C42: * Knowledge of forecasting, predictive modelling, or machine learning is an added advantage | D42: Y
A43: Excel | B43: required | C43: Proficiency in Excel, SQL, BI tools | D43: Y
A44: Problem Solving | B44: required | C44: Strong analytical, problem-solving, and structured-thinking skills. | D44: Y
A45: Critical Thinking | B45: required | C45: structured-thinking skills | D45: Y
A46: Data Visualisation | B46: required | C46: able to drive business on various platform eg. dashboard | D46: Y
... A52: NEW: Forecasting | B52: bonus | C52: Knowledge of forecasting, predictive modelling, or machine learning is an added advantage. | D52: Y

Sheet JD-DS-0005
A1: JD-DS-0005 | DATA_SCIENTIST | Data Scientist, Intern - [COMPANY] (entry)
A2: Read the JD, then go down to the table. Mark every pre-filled row keep = Y (correct, fix the cells if needed) or N (wrong). Add missing skills on the empty rows with keep = Y. Yellow rows still need a Y or N.
A3: Go to the label table
A4: Job description
A5: About the Role
A7: The Kuala Lumpur office is the technology powerhouse of [COMPANY]. We pride ourselves on innovative initiatives and thrive in a fast paced and challenging environment.
A8: We are looking for a data science intern to join our multicultural team of visionaries and industry rebels in disrupting the traditional finance industry! This internship will be 6 months long, starting June 2026 to December 2026. Kindly note that this internship is only open to Malaysians, with final year students preferred.
A10: Key Responsibilities
A12: * Perform analyses to understand how our users interact with our products and how to improve our products.
A13: * Discover new insights and understanding of business performance based on data
A14: * Develop dashboards to track relevant metrics.
A15: * Assist with regular maintenance/BAU operations within the data science team.
... A31: * Interview & Discussion of Take-Home Assessment - Hiring Manager (Virtual or face-to-face)
A33: skill_name | B33: importance | C33: evidence_text | D33: keep | E33: note
A34: Machine Learning | B34: required | C34: * Assist with prototyping and exploring new machine learning initiatives in [COMPANY] | D34: Y
A35: Python | B35: required | C35: * Proficient in either R, Python, Matlab or other analytics/data mining packages | D35: Y
A36: Data Mining | B36: required | C36: * Proficient in either R, Python, Matlab or other analytics/data mining packages | D36: Y
A37: Statistical Analysis | B37: required | C37: * Experience in machine learning, predictive analytics and statistical modelling, in academic and/or industry settings | D37: Y
A38: Communication | B38: required | C38: * Good written and verbal communication skills, with high attention to detail | D38: Y
A39: Attention to Detail | B39: required | C39: * Good written and verbal communication skills, with high attention to detail | D39: Y
A40: R | B40: required | C40: Proficient in either R, Python, Matlab | D40: Y
A41: Data Analysis | B41: required | C41: Perform analyses to understand how our users interact with our products | D41: Y
A42: Data Visualisation | B42: required | C42: Develop dashboards to track relevant metrics. | D42: Y
A43: Stakeholder Communication | B43: required | C43: Communicate findings to stakeholders | D43: Y
A44: Problem Solving | B44: required | C44: ability to problem-solve independently | D44: Y
A45: Self-Motivation | B45: required | C45: Fast learner | D45: Y
... A47: NEW: Predictive Analytics | B47: required | C47: predictive analytics | D47: Y

Sheet JD-DS-0006
A1: JD-DS-0006 | DATA_SCIENTIST | Internship for Computer/IT/Software/Data Science (entry)
A2: Read the JD, then go down to the table. Mark every pre-filled row keep = Y (correct, fix the cells if needed) or N (wrong). Add missing skills on the empty rows with keep = Y. Yellow rows still need a Y or N.
A3: Go to the label table
A4: Job description
A5: Job Description
A7: * Work closely with process team to understand their analytical needs for dashboard development (Tableau).
A8: * Develop the dashboard (Tableau) according to the extraction, formulation and manipulation of data to address business requirements.
A9: * Interpret analytical results and summarize key points.
A10: * Create user manual / dashboard application note upon dashboard completion.
A12: Qualifications
A14: * Degree in Computer Software/Science/Engineering/IT/Data Science, preferable 6 months and above availability for internship.
A15: * Strong knowledge - SQL, R, Python, Tableau, PowerBI, Hadoop, C++, C, C#, RStudio, Visual Studio, MS Office.
... A19: * Fluent English skills (written and spoken).
A21: skill_name | B21: importance | C21: evidence_text | D21: keep | E21: note
A22: Tableau | B22: required | C22: * Work closely with process team to understand their analytical needs for dashboard development (Tableau) | D22: Y
A23: Requirements Analysis | B23: required | C23: understand their analytical needs for dashboard development | D23: Y
A24: SQL | B24: required | C24: * Strong knowledge - SQL, R, Python, Tableau, PowerBI, Hadoop, C++, C, C#, RStudio, Visual Studio, MS Office | D24: Y
A25: Python | B25: required | C25: * Strong knowledge - SQL, R, Python, Tableau, PowerBI, Hadoop, C++, C, C#, RStudio, Visual Studio, MS Office | D25: Y
A26: Power BI | B26: required | C26: * Strong knowledge - SQL, R, Python, Tableau, PowerBI, Hadoop, C++, C, C#, RStudio, Visual Studio, MS Office | D26: Y
A27: Hadoop | B27: required | C27: * Strong knowledge - SQL, R, Python, Tableau, PowerBI, Hadoop, C++, C, C#, RStudio, Visual Studio, MS Office | D27: Y
A28: C++ | B28: required | C28: * Strong knowledge - SQL, R, Python, Tableau, PowerBI, Hadoop, C++, C, C#, RStudio, Visual Studio, MS Office | D28: Y
A29: C# | B29: required | C29: * Strong knowledge - SQL, R, Python, Tableau, PowerBI, Hadoop, C++, C, C#, RStudio, Visual Studio, MS Office | D29: Y
A30: Problem Solving | B30: required | C30: * Good hands-on skills, excellent analytical and problem solving capabilities | D30: Y
A31: R | B31: required | C31: SQL, R, Python | D31: Y
A32: Data Visualisation | B32: required | C32: Develop the dashboard (Tableau) | D32: Y
A33: Data Analysis | B33: required | C33: Interpret analytical results and summarize key points. | D33: Y
... A38: NEW: Microsoft Office | B38: required | C38: MS Office | D38: Y

Sheet JD-DS-0007
A1: JD-DS-0007 | DATA_SCIENTIST | Technology Associate - Data Science (junior)
A2: Read the JD, then go down to the table. Mark every pre-filled row keep = Y (correct, fix the cells if needed) or N (wrong). Add missing skills on the empty rows with keep = Y. Yellow rows still need a Y or N.
A3: Go to the label table
A4: Job description
A5: Job Overview
A7: We are looking for a passionate, ambitious, and highly educated Technology Associate to join our Digital team. This position is designed for recent graduates with a strong academic record who are eager to gain hands-on experience across various facets of digital technologies. As a Technology Associate, you will participate in a dynamic job rotation program, gaining exposure to cutting-edge digital solutions, emerging technologies, and innovation-driven projects. This role will provide a foundation for leadership opportunities in the rapidly evolving digital landscape.
A9: Key Responsibilities
A11: * Job Rotation: Participate in a structured rotation across key areas of Digital Technologies, including but not limited to Software Development, Data Science, Data Engineer, Cloud Technologies, and Digital Transformation initiatives.
A12: * Project Management: Support and manage digital technology projects from conception to execution, ensuring successful implementation within timelines and budgets.
A13: * Innovation & Strategy: Assist in the development and execution of digital transformation strategies, leveraging the latest technologies like AI, IoT, Blockchain, and Cloud Computing to drive business growth.
A14: * Data Analysis & Reporting: Analyze data and generate insights from digital platforms and systems to drive decisions and optimize digital performance.
A15: * Collaboration: Work with cross-functional teams, including IT, Business Units, and external partners, to deliver technology solutions that meet business objectives.
... A44: Perks and benefits: Comprehensive training in digital technologies with workshops, certifications and mentorship; Fast-track career growth into leadership positions
A46: skill_name | B46: importance | C46: evidence_text | D46: keep | E46: note
A47: Leadership | B47: required | C47: This role will provide a foundation for leadership opportunities in the rapidly evolving digital landscape | D47: Y
A48: Project Management | B48: required | C48: * Project Management: Support and manage digital technology projects from conception to execution, ensuring successful implementation within timelines and budgets | D48: Y
A49: Cloud Computing | B49: required | C49: * Innovation & Strategy: Assist in the development and execution of digital transformation strategies, leveraging the latest technologies like AI, IoT, Blockchain, and Cloud Computing to drive business growth | D49: Y
A50: Data Analysis | B50: required | C50: * Data Analysis & Reporting: Analyze data and generate insights from digital platforms and systems to drive decisions and optimize digital performance | D50: Y
A51: Teamwork | B51: required | C51: * Collaboration: Work with cross-functional teams, including IT, Business Units, and external partners, to deliver technology solutions that meet business objectives | D51: Y
A52: Problem Solving | B52: required | C52: * Problem-Solving: Contribute to identifying, troubleshooting, and solving digital and technical challenges faced by the organization | D52: Y
A53: Machine Learning | B53: required | C53: * Proficient in digital tools and platforms such as cloud computing, databases, AI/ML, DevOps, and business intelligence | D53: Y
A54: Python | B54: bonus | C54: , Python, Java, SQL), and/or data analytics tools (e | D54: Y
A55: Java | B55: bonus | C55: , Python, Java, SQL), and/or data analytics tools (e | D55: Y
A56: SQL | B56: bonus | C56: , Python, Java, SQL), and/or data analytics tools (e | D56: Y
A57: Tableau | B57: bonus | C57: , Tableau, Power BI) is a plus | D57: Y
A58: Power BI | B58: bonus | C58: , Tableau, Power BI) is a plus | D58: Y
... A67: NEW: Software Development | B67: bonus | C67: Familiarity with software development processes | D67: Y

Sheet JD-DS-0008
A1: JD-DS-0008 | DATA_SCIENTIST | Intern - Data Science (entry)
A2: Read the JD, then go down to the table. Mark every pre-filled row keep = Y (correct, fix the cells if needed) or N (wrong). Add missing skills on the empty rows with keep = Y. Yellow rows still need a Y or N.
A3: Go to the label table
A4: Job description
A5: Job Summary
A7: [COMPANY]'s Manufacturing Engineering team is looking for an enthusiastic intern to assist in developing an automated Off-hold Tracking solution. The intern will support efforts to reduce manual data compilation in the Factory Quality Assurance Process (FQAP). This is a learning-focused role ideal for students eager to apply their academic knowledge in a real-world manufacturing setting.
A9: Essential Duties and Responsibilities
A11: * Assist in building a simple automated system to track Off-hold status and reduce manual compilation
A12: * Learn and apply basic data extraction and cleaning techniques on FQAP-related data
A13: * Help create simple reports or dashboards to display Off-hold tracking results
A14: * Work with team members to understand existing manual workflows
A15: * Support data validation by comparing automated outputs with current manual records
... A43: * Eager to learn and take initiative
A45: skill_name | B45: importance | C45: evidence_text | D45: keep | E45: note
A46: Documentation | B46: required | C46: * Prepare basic documentation on the work completed | D46: Y
A47: Python | B47: required | C47: , Python or R) | D47: Y
A48: Data Analysis | B48: preferred | C48: * Exposure to data analysis concepts through coursework or personal projects | D48: Y
A49: SQL | B49: preferred | C49: Some awareness of databases or SQL (even from coursework) | D49: Y
A50: Excel | B50: required | C50: Microsoft Excel (intermediate level) | D50: Y
A51: Power BI | B51: required | C51: * Willingness to learn visualization tools (Power BI, Tableau, etc | D51: N
A52: Tableau | B52: required | C52: * Willingness to learn visualization tools (Power BI, Tableau, etc | D52: N
A53: Communication | B53: required | C53: * Good communication and teamwork | D53: Y
A54: Teamwork | B54: required | C54: * Good communication and teamwork | D54: Y
A55: Self-Motivation | B55: required | C55: * Eager to learn and take initiative | D55: Y
A56: Data Cleaning | B56: required | C56: basic data extraction and cleaning techniques | D56: Y
A57: Data Visualisation | B57: required | C57: Help create simple reports or dashboards | D57: Y
... A59: NEW: VBA | B59: required | C59: Basic programming (Python, R, or VBA) | D59: Y

Sheet JD-DS-0009
A1: JD-DS-0009 | DATA_SCIENTIST | Associate Engineer, Data Science (junior)
A2: Read the JD, then go down to the table. Mark every pre-filled row keep = Y (correct, fix the cells if needed) or N (wrong). Add missing skills on the empty rows with keep = Y. Yellow rows still need a Y or N.
A3: Go to the label table
A4: Job description
A5: About the role
A7: This role builds strong technical foundations across data engineering, analytics, automation and digital transformation. You will work on real-world semiconductor manufacturing and supply-chain problems alongside experienced team members, developing data pipelines, analytical solutions and digital applications.
A9: Key responsibilities
A11: * Support the development and maintenance of data pipelines and data-processing workflows.
A12: * Write and maintain Python and SQL code for data extraction, transformation, validation and analysis.
A13: * Assist with integrating data from databases, APIs, files and enterprise systems.
A14: * Support the development of analytical datasets, dashboards and reports for supply-chain and manufacturing projects.
A15: * Perform data validation, reconciliation and troubleshooting.
... A26: * Academic or personal projects involving Python, SQL, data analytics, APIs or cloud technologies, or exposure to Power BI, Tableau or Git, are advantageous.
A28: skill_name | B28: importance | C28: evidence_text | D28: keep | E28: note
A29: ETL | B29: required | C29: You will work on real-world semiconductor manufacturing and supply-chain problems alongside experienced team members, developing data pipelines, analytical solutions and digital applications | D29: Y
A30: Python | B30: required | C30: * Write and maintain Python and SQL code for data extraction, transformation, validation and analysis | D30: Y
A31: SQL | B31: required | C31: * Write and maintain Python and SQL code for data extraction, transformation, validation and analysis | D31: Y
A32: Problem Solving | B32: required | C32: * Perform data validation, reconciliation and troubleshooting | D32: Y
A33: Monitoring & Observability | B33: required | C33: * Participate in the development, testing, deployment and monitoring of digital applications and planning-system capabilities | D33: Y
A34: Documentation | B34: required | C34: * Prepare technical documentation, follow coding standards and collaborate with cross-functional teams across Penang and Singapore | D34: Y
A35: Communication | B35: required | C35: * Strong analytical and problem-solving skills, with good communication, teamwork and a proactive, ownership-oriented attitude | D35: Y
A36: Teamwork | B36: required | C36: * Strong analytical and problem-solving skills, with good communication, teamwork and a proactive, ownership-oriented attitude | D36: Y
A37: Self-Motivation | B37: required | C37: * Strong analytical and problem-solving skills, with good communication, teamwork and a proactive, ownership-oriented attitude | D37: Y
A38: Data Analysis | B38: required | C38: Write and maintain Python and SQL code for data extraction, transformation, validation and analysis. | D38: Y
A39: Power BI | B39: bonus | C39: * Academic or personal projects involving Python, SQL, data analytics, APIs or cloud technologies, or exposure to Power BI, Tableau or Git, are advantageous | D39: Y
A40: Tableau | B40: bonus | C40: * Academic or personal projects involving Python, SQL, data analytics, APIs or cloud technologies, or exposure to Power BI, Tableau or Git, are advantageous | D40: Y
... A46: NEW: Relational Databases | B46: required | C46: relational databases | D46: Y

Sheet JD-DS-0010
A1: JD-DS-0010 | DATA_SCIENTIST | Degree Internship (Data Science/ IT) (entry)
A2: Read the JD, then go down to the table. Mark every pre-filled row keep = Y (correct, fix the cells if needed) or N (wrong). Add missing skills on the empty rows with keep = Y. Yellow rows still need a Y or N.
A3: Go to the label table
A4: Job description
A5: Data Science / IT Internship
A7: * To undertake specific projects as assigned
A8: * To provide accurate, reliable test results or data analysis to strengthen the statistical back up in all relevant projects & department activities.
A9: * Responsible to carry out all development works assigned by the supervisor.
A10: * Execute assignments given and report on progress.
A11: * Any other tasks assigned by supervisor
A13: Minimum Qualification
A15: * Degree (Artificial Intelligence/ Computer Science/Data Science) disciplines are preferred
... A22: Perks and benefits: Medical; Miscellaneous allowance; Dental and optical; Hybrid Work; Annual bonuses; On-site gym; Meal subsidy; International exposure
A24: skill_name | B24: importance | C24: evidence_text | D24: keep | E24: note
A25: Data Analysis | B25: required | C25: * To provide accurate, reliable test results or data analysis to strengthen the statistical back up in all relevant projects & department activities | D25: Y
A26: AI Literacy | B26: preferred | C26: * Degree (Artificial Intelligence/ Computer Science/Data Science) disciplines are preferred | D26: N
A27: Power BI | B27: bonus | C27: Knowledge in Power BI is advantage | D27: Y
A28: Communication | B28: required | C28: * Ability to work in a team and good communication skills | D28: Y
A29: Teamwork | B29: required | C29: Ability to work in a team | D29: Y
A30: Statistical Analysis | B30: required | C30: strengthen the statistical back up | D30: Y

Sheet JD-SD-0002
A1: JD-SD-0002 | SOFTWARE_DEV | Software Developer / Junior Software Developer (junior)
A2: Read the JD, then go down to the table. Mark every pre-filled row keep = Y (correct, fix the cells if needed) or N (wrong). Add missing skills on the empty rows with keep = Y. Yellow rows still need a Y or N.
A3: Go to the label table
A4: Job description
A5: We’re looking for passionate and versatile Software Developers to join our growing tech team! Your main role is to work closely with the other members in the Accounting Team.
A7: Responsibilities
A9: * Develop and implement new software programmes.
A10: * Maintain and improve the performance of existing software.
A11: * Test and maintain software products to ensure strong functionality and optimization.
A12: * Design and update software database.
A13: * Analyze user needs and software requirement to determine feasibility of design within time and cost constraints.
A14: * Troubleshoot and resolve issues in existing software.
... A32: Perks and benefits: 5 working days; Parking subsidy; Fully-stocked fridge and pantry; Medical, dental and optical benefits, hospitalization & surgical insurance and group personal scheme; Training and guidance provided; Smart casual attire; Festive and birthday celebrations; Sports activities (badminton & pickleball)
A34: skill_name | B34: importance | C34: evidence_text | D34: keep | E34: note
A35: Documentation | B35: required | C35: * Prepare design documentation | D35: Y
A36: React | B36: required | C36: * Have at least 2 years of working experience with React Native or in related fields | D36: Y
A37: C# | B37: required | C37: NET Core MVC C#, HTML5, CSS, Razor/React | D37: Y
A38: HTML | B38: required | C38: NET Core MVC C#, HTML5, CSS, Razor/React | D38: Y
A39: CSS | B39: required | C39: NET Core MVC C#, HTML5, CSS, Razor/React | D39: Y
A40: JavaScript | B40: required | C40: js, Javascript and MSSQL | D40: Y
A41: Azure | B41: bonus | C41: * Experience in Azure will be an added advantage | D41: Y
A42: REST API | B42: required | C42: Experience with RESTful APIs | D42: Y
A43: UI/UX Design | B43: required | C43: Understanding of mobile UI/UX principles. | D43: Y
A44: Requirements Analysis | B44: required | C44: Analyze user needs and software requirement | D44: Y
A45: Problem Solving | B45: required | C45: Troubleshoot and resolve issues in existing software. | D45: Y
A46: Teamwork | B46: required | C46: Collaborate and communicate effectively with other team members | D46: Y
... A53: NEW: Database Design | B53: required | C53: Design and update software database. | D53: Y

Sheet JD-SD-0003
A1: JD-SD-0003 | SOFTWARE_DEV | Software Engineer (Internship) (entry)
A2: Read the JD, then go down to the table. Mark every pre-filled row keep = Y (correct, fix the cells if needed) or N (wrong). Add missing skills on the empty rows with keep = Y. Yellow rows still need a Y or N.
A3: Go to the label table
A4: Job description
A5: We are hiring for our Internship Program! We are looking for enthusiastic problem-solver with an interest in software development to join us to build our next generation system. We only accept candidates who knows how to code.
A7: Job Responsibilities
A9: * Assisting Software Engineers to develop in HTML, CSS, Javascript, ASP.net & C#
A10: * Involve in whole Software Development Life Cycle (SDLC)
A11: * Maintain good documentation and maintenance practice
A13: Who we need
A15: * Current or Graduating student taking Computer Science or Computer Engineering.
A16: * Passion in software development!
... A22: Perks and benefits: Highly competitive compensation; Skilled programmer as mentor; Opportunity to convert to full-time role; 5-day work week; Flexible work environment; Fully stocked refreshments
A24: skill_name | B24: importance | C24: evidence_text | D24: keep | E24: note
A25: HTML | B25: required | C25: * Assisting Software Engineers to develop in HTML, CSS, Javascript, ASP | D25: Y
A26: CSS | B26: required | C26: * Assisting Software Engineers to develop in HTML, CSS, Javascript, ASP | D26: Y
A27: JavaScript | B27: required | C27: * Assisting Software Engineers to develop in HTML, CSS, Javascript, ASP | D27: Y
A28: C# | B28: required | C28: net & C# | D28: Y
A29: Documentation | B29: required | C29: * Maintain good documentation and maintenance practice | D29: Y
A30: Problem Solving | B30: required | C30: enthusiastic problem-solver | D30: Y
A31: Critical Thinking | B31: required | C31: Good logical thinking | D31: Y
A32: NEW: ASP.NET | B32: required | C32: ASP.net & C# | D32: Y
A33: NEW: SDLC | B33: required | C33: Involve in whole Software Development Life Cycle (SDLC) | D33: Y

Sheet JD-SD-0005
A1: JD-SD-0005 | SOFTWARE_DEV | Software Developer (Internship) (entry)
A2: Read the JD, then go down to the table. Mark every pre-filled row keep = Y (correct, fix the cells if needed) or N (wrong). Add missing skills on the empty rows with keep = Y. Yellow rows still need a Y or N.
A3: Go to the label table
A4: Job description
A5: Responsibilities
A7: * Software Development Life Cycle (SDLC) including Design, Programming, QC, Documentation and etc.
A8: * To learn & involve in Enterprise Management Software (ERP), Industry 4.0 Development (Machine Automation, AGV, Mobility, Data Mining, Dashboard and etc).
A10: Requirements
A12: * Bachelor's Degree in Computer Science/ Information Technology, Science & Technology or equivalent.
A13: * Required skill(s): Communication, Adaptive, Teamwork.
A14: * Prefer Final Year Student and come with full 6 months internship period
A15: * 5 Internship position(s).
A17: skill_name | B17: importance | C17: evidence_text | D17: keep | E17: note
A18: Documentation | B18: required | C18: * Software Development Life Cycle (SDLC) including Design, Programming, QC, Documentation and etc | D18: Y
A19: Data Mining | B19: preferred | C19: To learn & involve in Enterprise Management Software (ERP), Industry 4.0 Development? | D19: Y
A20: Communication | B20: required | C20: * Required skill(s): Communication, Adaptive, Teamwork | D20: Y
A21: Teamwork | B21: required | C21: * Required skill(s): Communication, Adaptive, Teamwork | D21: Y
A22: Adaptability | B22: required | C22: Required skill(s): Communication, Adaptive, Teamwork. | D22: Y
A23: NEW: SDLC | B23: required | C23: Software Development Life Cycle (SDLC) | D23: Y
A24: NEW: ERP | B24: preferred | C24: To learn & involve in Enterprise Management Software (ERP) | D24: Y

Sheet JD-SD-0006
A1: JD-SD-0006 | SOFTWARE_DEV | Junior Software Engineer (junior)
A2: Read the JD, then go down to the table. Mark every pre-filled row keep = Y (correct, fix the cells if needed) or N (wrong). Add missing skills on the empty rows with keep = Y. Yellow rows still need a Y or N.
A3: Go to the label table
A4: Job description
A5: Responsibilities
A7: * Design, development, testing, and deployment of software & application to meet business objective under organization’s IT projects & initiatives.
A8: * Support & maintenance (2nd Level SLA) of software & application to ensure organization’s Business As Usual (BAU).
A9: * Upgrade of software & application to meet user’s & compliance requirements.
A10: * Research, design & planning for software & application to fulfil business requirement & organization objective.
A12: Requirements
A14: * Degree in Information Technology (IT)/ Computer Science/ Software Engineering or related field.
A15: * Minimum two (2) years’ working experience in Software Engineering or related field, with at least one (1) year of experience in IT-related projects.
... A22: * Fresh graduates are encouraged to apply.
A24: skill_name | B24: importance | C24: evidence_text | D24: keep | E24: note
A25: Communication | B25: required | C25: * Must have strong analytical, problem-solving, good communication and stakeholder management skills | D25: Y
A26: Stakeholder Communication | B26: required | C26: stakeholder management skills | D26: Y
A27: C# | B27: required | C27: (C#/ Java/ Javascript or equivalent) | D27: Y
A28: Java | B28: required | C28: (C#/ Java/ Javascript or equivalent) | D28: Y
A29: JavaScript | B29: required | C29: (C#/ Java/ Javascript or equivalent) | D29: Y
A30: SQL | B30: required | C30: * Must be proficient in SQL & Relational Database (MS SQL / MySQL or equivalent) | D30: Y
A31: MySQL | B31: required | C31: * Must be proficient in SQL & Relational Database (MS SQL / MySQL or equivalent) | D31: Y
A32: Problem Solving | B32: required | C32: Must have strong analytical, problem-solving | D32: Y
A33: Research Skills | B33: required | C33: Research, design & planning for software & application | D33: Y
A34: Requirements Analysis | B34: required | C34: to fulfil business requirement | D34: Y
A35: NEW: Microsoft SQL Server | B35: required | C35: MS SQL / MySQL or equivalent | D35: Y
A36: NEW: Relational Databases | B36: required | C36: Must be proficient in SQL & Relational Database | D36: Y
... A41: NEW: Data Engineering | B41: preferred | C41: Experience in fullstack development or data engineering is preferred. | D41: Y

Sheet JD-SD-0007
A1: JD-SD-0007 | SOFTWARE_DEV | Software Engineer (Full-Stack, AI-Assisted Development) (junior)
A2: Read the JD, then go down to the table. Mark every pre-filled row keep = Y (correct, fix the cells if needed) or N (wrong). Add missing skills on the empty rows with keep = Y. Yellow rows still need a Y or N.
A3: Go to the label table
A4: Job description
A5: The Role
A7: Join our KL engineering team to build and maintain web applications for real clients, covering frontend, backend, APIs, databases and integrations. You will work with tools like Claude, ChatGPT every day, and you must be able to spot when AI output is wrong, insecure or over-engineered, and fix it before release. We work spec-first: clear written requirements drive AI-assisted builds, and engineers own the quality of the result.
A9: What You'll Do
A11: * Turn business requirements and UI/UX flows into clean, secure, production-ready features
A12: * Write clear specs and give AI tools the right technical and business context, within our established project structure and conventions
A13: * Review AI-generated code for logic, security, performance and maintainability
A14: * Debug issues across frontend, backend, databases, servers and production
A15: * Own your features from development through deployment and support
... A35: Perks and benefits: Work for a US-headquartered company from Kuala Lumpur; Small team with visible impact; AI-first engineering workflow; Real ownership of features that go live
A37: skill_name | B37: importance | C37: evidence_text | D37: keep | E37: note
A38: Requirements Analysis | B38: required | C38: Turn business requirements and UI/UX flows into clean, secure, production-ready features | D38: Y
A39: Linux | B39: required | C39: * Linux, server, database and networking knowledge | D39: Y
A40: Networking | B40: required | C40: * Linux, server, database and networking knowledge | D40: Y
A41: Generative AI | B41: required | C41: Practical, hands-on experience using AI coding tools | D41: Y
A42: Prompt Engineering | B42: required | C42: give AI tools the right technical and business context | D42: Y
A43: REST API | B43: required | C43: Solid fundamentals in frontend, backend, APIs | D43: Y
A44: UI/UX Design | B44: required | C44: An eye for UI/UX detail | D44: Y
A45: Problem Solving | B45: required | C45: Strong debugging and logical problem-solving skills | D45: Y
A46: Self-Motivation | B46: required | C46: Able to work independently and take ownership | D46: Y
A47: Documentation | B47: required | C47: Write clear specs | D47: Y
A48: NEW: Code Review | B48: required | C48: Review AI-generated code for logic, security, performance and maintainability | D48: Y
A49: NEW: Full-Stack Development | B49: required | C49: Solid fundamentals in frontend, backend, APIs, databases and web architecture | D49: Y

Sheet JD-SD-0008
A1: JD-SD-0008 | SOFTWARE_DEV | Junior Software Developer/Engineer (junior)
A2: Read the JD, then go down to the table. Mark every pre-filled row keep = Y (correct, fix the cells if needed) or N (wrong). Add missing skills on the empty rows with keep = Y. Yellow rows still need a Y or N.
A3: Go to the label table
A4: Job description
A5: Ideal Candidate(s)
A7: * Technically competent, self-driven individual(s) with a proven track record in the software field.
A8: * Independent contributor who is also a good team player.
A9: * Possessing either strong design skills and/or good trouble-shooting acumen.
A11: Responsibilities
A13: * Define, develop, test, and support Industry 4.0 software applications for the semiconductor factories.
A14: * I4.0 applications usually involve systems to integrate with manufacturing equipment in semiconductor factories to collect data, provide analytics, and enable intelligent monitoring and control.
A15: * Occasional travel to local and overseas customer sites to provide product support and for project implementation.
... A23: * Able to work under min. supervision & independently. Good spoken and written English skills are necessary.
A25: skill_name | B25: importance | C25: evidence_text | D25: keep | E25: note
A26: Self-Motivation | B26: required | C26: * Technically competent, self-driven individual(s) with a proven track record in the software field | D26: Y
A27: Teamwork | B27: required | C27: * Independent contributor who is also a good team player | D27: Y
A28: Monitoring & Observability | B28: required | C28: 0 applications usually involve systems to integrate with manufacturing equipment in semiconductor factories to collect data, provide analytics, and enable intelligent monitoring and control | D28: N
A29: C# | B29: required | C29: * Proven track record with some of the following technologies/ programming languages: C#, | D29: Y
A30: NEW: Microsoft SQL Server | B30: required | C30: MS SQL Server | D30: Y
A31: Python | B31: required | C31: NET, Web Services, MS SQL Server, VB, Python, Web Programming, Dashboards, SECS/GEM, Machine Learning | D31: Y
A32: Machine Learning | B32: required | C32: NET, Web Services, MS SQL Server, VB, Python, Web Programming, Dashboards, SECS/GEM, Machine Learning | D32: Y
A33: Data Visualisation | B33: required | C33: Web Programming, Dashboards | D33: Y
A34: Generative AI | B34: preferred | C34: Familiar with the use of A.I. tools for software design, development, debugging | D34: Y
A35: Problem Solving | B35: required | C35: good trouble-shooting acumen | D35: Y
A36: NEW: .NET | B36: required | C36: C#, .NET | D36: Y
A37: NEW: VB | B37: required | C37: MS SQL Server, VB | D37: Y
... A40: NEW: SECS/GEM | B40: required | C40: SECS/GEM | D40: Y

Sheet JD-SD-0009
A1: JD-SD-0009 | SOFTWARE_DEV | Java Developer Intern (entry)
A2: Read the JD, then go down to the table. Mark every pre-filled row keep = Y (correct, fix the cells if needed) or N (wrong). Add missing skills on the empty rows with keep = Y. Yellow rows still need a Y or N.
A3: Go to the label table
A4: Job description
A5: About the Role
A7: We are looking for a passionate and driven Java Developer Intern to join our growing engineering team. This is a hands-on internship where you'll work alongside experienced developers on real-world projects.
A8: Whether you're a final-year student or a fresh graduate eager to kickstart your tech career in Southeast Asia's thriving tech ecosystem, we'd love to hear from you!
A10: Duration & Start Date
A12: * Duration: 4–8 months
A13: * Start Date: 2026 July
A14: * Commitment: Full-time (Mon–Fri)
A16: What You'll Do
... A34: Perks and benefits: Mentorship from senior engineers; Real project ownership with code shipped to production; Certificate of completion and potential full-time conversion upon graduation
A36: skill_name | B36: importance | C36: evidence_text | D36: keep | E36: note
A37: Java | B37: required | C37: We are looking for a passionate and driven Java Developer Intern to join our growing engineering team | D37: Y
A38: Agile / Scrum | B38: required | C38: * Collaborate with cross-functional teams (PM, QA, DevOps) in an Agile environment | D38: Y
A39: CI/CD | B39: required | C39: Learn and contribute to internal tooling and CI/CD pipelines | D39: Y | E39: importance preferred -> required (duty); A/B resolution, AI-assisted adjudication 2026-10-29, see resolution.xlsx
A40: Spring Boot | B40: preferred | C40: * Familiarity with Spring Boot or willingness to learn quickly | D40: Y
A41: SQL | B41: required | C41: * Basic understanding of SQL / relational databases | D41: Y
A42: REST API | B42: required | C42: Java-based backend services and APIs | D42: Y
A43: Problem Solving | B43: required | C43: Good problem-solving mindset | D43: Y
A44: Teamwork | B44: required | C44: Collaborate with cross-functional teams (PM, QA, DevOps) | D44: Y
A45: Self-Motivation | B45: required | C45: willingness to learn | D45: Y
A46: NEW: Relational Databases | B46: required | C46: Basic understanding of SQL / relational databases | D46: Y
A47: NEW: SDLC | B47: required | C47: Participate in the full software development lifecycle | D47: Y
A48: Documentation | B48: required | C48: well-documented code | D48: Y | E48: added from B; A/B resolution, AI-assisted adjudication 2026-10-29, see resolution.xlsx
A49: NEW: Backend Development | B49: required | C49: Java-based backend services and APIs | D49: Y | E49: added from B; A/B resolution, AI-assisted adjudication 2026-10-29, see resolution.xlsx
A50: NEW: Debugging | B50: required | C50: Debug and troubleshoot application issues | D50: Y | E50: added from B; A/B resolution, AI-assisted adjudication 2026-10-29, see resolution.xlsx

Sheet JD-SD-0010
A1: JD-SD-0010 | SOFTWARE_DEV | Intern, Software Developer (JAVA) (entry)
A2: Read the JD, then go down to the table. Mark every pre-filled row keep = Y (correct, fix the cells if needed) or N (wrong). Add missing skills on the empty rows with keep = Y. Yellow rows still need a Y or N.
A3: Go to the label table
A4: Job description
A5: Why This Role Matters
A7: The Software Developer Intern supports the development of enterprise financial applications, assisting in coding, testing, and troubleshooting. The role provides hands-on System Development Life Cycle (SDLC) experience, exposure to modern technologies, and opportunities to build technical and teamwork skills.
A9: How You'll Make a Difference
A11: * Undertake project assignments together with the project team to deliver enterprise digital financial solution/application.
A12: * Get real experience in project implementation-System Development Life Cycle by assisting project team in:
A14: 1. Delivery of accurate & efficient enterprise level application program according to specifications.
A15: 2. Software Development: Object-oriented design & development.
A16: 3. SIT and UAT Support. Troubleshooting issue and perform changes as needed to resolve issue.
... A30: Perks and benefits: Medical; Miscellaneous allowance; Dental; Parking
A32: skill_name | B32: importance | C32: evidence_text | D32: keep | E32: note
A33: Problem Solving | B33: required | C33: The Software Developer Intern supports the development of enterprise financial applications, assisting in coding, testing, and troubleshooting | D33: Y
A34: Teamwork | B34: required | C34: Collaborate with team and across teams. | D34: Y
A35: Spring Boot | B35: preferred | C35: Expose to different development framework and tools: Spring framework | D35: Y
A36: Angular | B36: preferred | C36: Expose to different development framework and tools: Spring framework, Angular, React, Kubernetes, Gradle, Docker, Bootstrap, Ionic, Microservices etc | D36: Y
A37: React | B37: preferred | C37: Expose to different development framework and tools: Spring framework, Angular, React, Kubernetes, Gradle, Docker, Bootstrap, Ionic, Microservices etc | D37: Y
A38: Kubernetes | B38: preferred | C38: Expose to different development framework and tools: Spring framework, Angular, React, Kubernetes, Gradle, Docker, Bootstrap, Ionic, Microservices etc | D38: Y
A39: Docker | B39: preferred | C39: Expose to different development framework and tools: Spring framework, Angular, React, Kubernetes, Gradle, Docker, Bootstrap, Ionic, Microservices etc | D39: Y
A40: Microservices | B40: preferred | C40: Expose to different development framework and tools: Spring framework, Angular, React, Kubernetes, Gradle, Docker, Bootstrap, Ionic, Microservices etc | D40: Y
A41: Object-Oriented Programming | B41: required | C41: Object-oriented design & development. | D41: Y
A42: User Acceptance Testing | B42: required | C42: SIT and UAT Support. | D42: Y
A43: Documentation | B43: required | C43: Assist Business team in preparing functional specification | D43: Y
A44: NEW: SDLC | B44: required | C44: System Development Life Cycle (SDLC) | D44: Y
... A47: NEW: Ionic | B47: preferred | C47: Ionic | D47: Y

Sheet JD-SD-0011
A1: JD-SD-0011 | SOFTWARE_DEV | Junior Tester (junior)
A2: Read the JD, then go down to the table. Mark every pre-filled row keep = Y (correct, fix the cells if needed) or N (wrong). Add missing skills on the empty rows with keep = Y. Yellow rows still need a Y or N.
A3: Go to the label table
A4: Job description
A5: Duration: 1 year extendable contract
A6: Experience: 1+ years
A8: We are looking for a Junior Tester with hands-on experience in manual testing and a good understanding of software testing practices.
A10: Requirements
A12: * 1+ years of experience in Manual Testing.
A13: * Good understanding of STLC, test case preparation, test execution, and defect reporting.
A14: * Knowledge or exposure to Automation Testing will be an advantage.
A15: * Banking/Financial Services domain experience is highly preferred.
... A17: * Ability to work effectively within a team and meet project timelines.
A19: skill_name | B19: importance | C19: evidence_text | D19: keep | E19: note
A20: Communication | B20: required | C20: * Good analytical, problem-solving, and communication skills | D20: Y
A21: Problem Solving | B21: required | C21: Good analytical, problem-solving, and communication skills. | D21: Y
A22: Teamwork | B22: required | C22: Ability to work effectively within a team | D22: Y
A23: Time Management | B23: required | C23: meet project timelines | D23: Y
A24: NEW: Manual Testing | B24: required | C24: 1+ years of experience in Manual Testing. | D24: Y
A25: NEW: Test Case Design | B25: required | C25: test case preparation, test execution, and defect reporting | D25: Y
A26: NEW: Test Automation | B26: bonus | C26: Knowledge or exposure to Automation Testing will be an advantage. | D26: Y

Sheet JD-SD-0012
A1: JD-SD-0012 | SOFTWARE_DEV | Junior Software Engineer (Fresh graduates are welcome to apply) (junior)
A2: Read the JD, then go down to the table. Mark every pre-filled row keep = Y (correct, fix the cells if needed) or N (wrong). Add missing skills on the empty rows with keep = Y. Yellow rows still need a Y or N.
A3: Go to the label table
A4: Job description
A5: Job Summary
A7: We are looking for a motivated and detail-oriented Junior Software Engineer to join our growing engineering team. Your primary responsibility will be to maintain, troubleshoot, and improve our existing mobile applications and web platforms. You will also have the opportunity to gradually expand your skills into AI development, data processing, and embedded firmware development for our exoskeleton products.
A8: Fresh graduates are welcome to apply. Prior experience in AI or firmware development is not required. You will work closely with experienced engineers who will provide hands-on guidance and technical training.
A10: Key Responsibilities
A12: App & Web Development
A14: * Maintain, troubleshoot, and improve existing mobile applications and web platforms.
A15: * Identify and resolve software bugs, performance issues, and compatibility problems.
A16: * Support the implementation of new features and improvements based on product and business requirements.
... A59: * Interest in robotics, wearable technology, IoT, embedded systems, or consumer electronics.
A61: skill_name | B61: importance | C61: evidence_text | D61: keep | E61: note
A62: Attention to Detail | B62: required | C62: We are looking for a motivated and detail-oriented Junior Software Engineer to join our growing engineering team | D62: Y
A63: Business Analysis | B63: required | C63: * Support the implementation of new features and improvements based on product and business requirements | D63: N
A64: Documentation | B64: required | C64: * Maintain clear and organized source code, technical documentation, and development records | D64: Y
A65: A/B Testing | B65: required | C65: * Assist the engineering team with AI-related product development and experimentation | D65: N
A66: UI/UX Design | B66: required | C66: * Explore and learn new AI technologies that may improve product performance and user experience | D66: N
A67: Problem Solving | B67: required | C67: * Assist in product testing, troubleshooting, and technical issue investigation | D67: Y
A68: Self-Motivation | B68: required | C68: * Self-motivated, proactive, and willing to take ownership of assigned tasks | D68: Y
A69: Communication | B69: required | C69: * Good communication skills and ability to work effectively within a multidisciplinary team | D69: Y
A70: Python | B70: preferred | C70: Knowledge of Python, JavaScript / TypeScript, C / C++, or similar programming languages. | D70: Y
A71: JavaScript | B71: preferred | C71: * Knowledge of Python, JavaScript / TypeScript, C / C++, or similar programming languages | D71: Y
A72: TypeScript | B72: preferred | C72: * Knowledge of Python, JavaScript / TypeScript, C / C++, or similar programming languages | D72: Y
A73: C++ | B73: preferred | C73: * Knowledge of Python, JavaScript / TypeScript, C / C++, or similar programming languages | D73: Y
... A88: NEW: C | B88: preferred | C88: C / C++ | D88: Y

Sheet JD-WD-0001
A1: JD-WD-0001 | WEB_DEV | Interns - Software Developer (entry)
A2: Read the JD, then go down to the table. Mark every pre-filled row keep = Y (correct, fix the cells if needed) or N (wrong). Add missing skills on the empty rows with keep = Y. Yellow rows still need a Y or N.
A3: Go to the label table
A4: Job description
A5: We welcome interns! Join [COMPANY] and gain practical skills and real-world experience in software development. We provide guidance and training to help you grow as a developer.
A7: What you'll learn
A9: You'll gain hands-on experience by working together with software development team to support ongoing projects:
A11: * Assist in the development and enhancement of software applications.
A12: * Assist in preparing software and product documentation.
A13: * Perform testing and debugging to identify and resolve software issues.
A14: * Assist in troubleshooting and modifying existing applications when required.
A16: What you'll need
... A25: Perks and benefits: Hands-on experience with real projects; Mentorship from experienced developers; Opportunity to grow into a full-time role (based on performance)
A27: skill_name | B27: importance | C27: evidence_text | D27: keep | E27: note
A28: Documentation | B28: required | C28: * Assist in preparing software and product documentation | D28: Y
A29: Problem Solving | B29: required | C29: * Assist in troubleshooting and modifying existing applications when required | D29: Y
A30: Java | B30: required | C30: * Basic knowledge in programming languages such as Java and JavaScript | D30: Y
A31: JavaScript | B31: required | C31: * Basic knowledge in programming languages such as Java and JavaScript | D31: Y
A32: Vue.js | B32: required | C32: * Basic knowledge in development frameworks such as Vue.js ecosystem and UI styling with Tailwind CSS | D32: Y
A33: CSS | B33: required | C33: js ecosystem and UI styling with Tailwind CSS | D33: Y
A34: Self-Motivation | B34: required | C34: * Self-Driven with strong analytical and problem-solving skills | D34: Y
A35: Teamwork | B35: required | C35: working together with software development team | D35: N | E35: dropped: under 'What you'll learn' (R2); A/B resolution, AI-assisted adjudication 2026-10-29, see resolution.xlsx
A36: NEW: Tailwind CSS | B36: required | C36: UI styling with Tailwind CSS | D36: Y
A37: NEW: Software Testing | B37: required | C37: Perform testing and debugging | D37: Y
A38: NEW: Debugging | B38: required | C38: Perform testing and debugging | D38: Y | E38: added from B; A/B resolution, AI-assisted adjudication 2026-10-29, see resolution.xlsx

Sheet JD-WD-0002
A1: JD-WD-0002 | WEB_DEV | Junior IT Programmer / Interns (entry)
A2: Read the JD, then go down to the table. Mark every pre-filled row keep = Y (correct, fix the cells if needed) or N (wrong). Add missing skills on the empty rows with keep = Y. Yellow rows still need a Y or N.
A3: Go to the label table
A4: Job description
A5: About the role
A7: This is a Junior IT Personnel / Intern position where you will build and improve in-house web systems with the development team, use AI tools to work faster and smarter, test and fix bugs to keep systems running smoothly, help with day-to-day IT support, and join training sessions including emergency role-play scenarios.
A9: Key responsibilities
A11: * Build and improve in-house web systems with the dev team
A12: * Use AI tools (Claude, ChatGPT, Cursor) to work faster and smarter
A13: * Test, fix bugs and keep in-house systems running smoothly
A14: * Help with day-to-day IT support
A15: * Join training sessions, including emergency role-play scenarios
... A30: Perks and benefits: Chance of permanent role for interns; Working hours Monday - Friday 8:30am - 4:30pm
A32: skill_name | B32: importance | C32: evidence_text | D32: keep | E32: note
A33: PHP | B33: required | C33: * PHP / Laravel, or another modern web framework | D33: Y
A34: Git | B34: required | C34: * Git and GitHub (branches, pull requests, teamwork) | D34: Y
A35: Teamwork | B35: required | C35: * Git and GitHub (branches, pull requests, teamwork) | D35: Y
A36: Self-Motivation | B36: required | C36: * Takes initiative and delivers clear, practical solutions | D36: Y
A37: Vue.js | B37: bonus | C37: * Nice to have: Vue or React | D37: Y
A38: React | B38: bonus | C38: * Nice to have: Vue or React | D38: Y
A39: Docker | B39: bonus | C39: * Nice to have: Docker, Linux or cloud hosting | D39: Y
A40: Linux | B40: bonus | C40: * Nice to have: Docker, Linux or cloud hosting | D40: Y
A41: Networking | B41: bonus | C41: * Nice to have: Basic technical support skills and networking | D41: Y
A42: Generative AI | B42: required | C42: Use AI tools (Claude, ChatGPT, Cursor) | D42: Y
A43: Creativity | B43: required | C43: Innovative mindset | D43: Y
A44: Cloud Computing | B44: bonus | C44: Nice to have: Docker, Linux or cloud hosting | D44: Y
... A48: NEW: Software Testing | B48: required | C48: Test, fix bugs | D48: Y

Sheet JD-WD-0003
A1: JD-WD-0003 | WEB_DEV | Full Stack Developer - (Junior to Mid Level) (MY Based) (mid)
A2: Read the JD, then go down to the table. Mark every pre-filled row keep = Y (correct, fix the cells if needed) or N (wrong). Add missing skills on the empty rows with keep = Y. Yellow rows still need a Y or N.
A3: Go to the label table
A4: Job description
A5: About the Role
A7: [COMPANY] is looking for a Mid-Level Full Stack Developer to join our growing application development team. You’ll be working on both frontend and backend development using React.js with Next.js, .NET Core, and Node.js while managing databases in MS SQL and MySQL.
A9: A day in life
A11: * Develop and maintain front-end components using React.js and Next.js.
A12: * Implement backend APIs using .NET Core (C#) and Node.js.
A13: * Work with databases (MS SQL & MySQL) to design and write efficient queries.
A14: * Collaborate with senior developers and follow coding standards and best practices.
A15: * Participate in code reviews, testing, and debugging.
... A36: Perks and benefits: Hybrid working arrangement; 18 days annual leave; 3 days family care leave; Honourable MC; Staff insurance (inpatient/outpatient/PA/life); Flexi-benefit; Free gym access
A38: skill_name | B38: importance | C38: evidence_text | D38: keep | E38: note
A39: React | B39: required | C39: You’ll be working on both frontend and backend development using React.js with Next | D39: Y
A40: Node.js | B40: required | C40: NET Core, and Node.js while managing databases in MS SQL and MySQL | D40: Y
A41: SQL | B41: required | C41: js while managing databases in MS SQL and MySQL | D41: Y
A42: MySQL | B42: required | C42: js while managing databases in MS SQL and MySQL | D42: Y
A43: C# | B43: required | C43: NET Core (C#) and Node | D43: Y
A44: Documentation | B44: required | C44: * Contribute to system documentation and knowledge sharing | D44: Y
A45: JavaScript | B45: required | C45: js, JavaScript/TypeScript, and Next | D45: Y
A46: TypeScript | B46: required | C46: js, JavaScript/TypeScript, and Next | D46: Y
A47: REST API | B47: required | C47: * Understanding of RESTful API design | D47: Y
A48: Git | B48: preferred | C48: * Familiarity with Git and version control systems | D48: Y
A49: Communication | B49: required | C49: * Good communication and teamwork skills | D49: Y
A50: Teamwork | B50: required | C50: * Good communication and teamwork skills | D50: Y
... A62: NEW: DevOps | B62: bonus | C62: Familiarity with basic DevOps practices | D62: Y

Sheet JD-WD-0004
A1: JD-WD-0004 | WEB_DEV | Software & Tech Internship (entry)
A2: Read the JD, then go down to the table. Mark every pre-filled row keep = Y (correct, fix the cells if needed) or N (wrong). Add missing skills on the empty rows with keep = Y. Yellow rows still need a Y or N.
A3: Go to the label table
A4: Job description
A5: About the Role
A7: We’re building Guard Ops, our own operations platform that runs guard scheduling, attendance, leave and site management for 300+ security officers across 65+ sites. We’re looking for a Tech Intern who enjoys solving problems and building software that real people use every day. You’ll work directly with management on a live product, and you’ll also support the company’s day-to-day tech operations.
A9: Key Responsibilities
A11: Guard Ops App Development
A13: * Build and improve features on the web dashboard (Next.js) and mobile attendance app (Flutter)
A14: * Work with the Supabase backend, including the database, authentication and access control
A15: * Fix bugs, test new features, and help with deployments
A16: * Collect feedback from managers, supervisors and guards, and turn it into improvements
... A55: Perks and benefits: Real experience shipping a production app used daily; Mentorship in full-stack development, databases and AI-assisted coding; Exposure to SME operations; Portfolio-ready work; Opportunity to transition into a full-time role
A57: skill_name | B57: importance | C57: evidence_text | D57: keep | E57: note
A58: Identity & Access Management | B58: required | C58: * Work with the Supabase backend, including the database, authentication and access control | D58: Y
A59: Problem Solving | B59: required | C59: * Provide first-level troubleshooting for staff software and tools | D59: Y
A60: JavaScript | B60: required | C60: Basic coding in JavaScript/TypeScript (Python is a plus) | D60: Y
A61: TypeScript | B61: required | C61: Basic coding in JavaScript/TypeScript (Python is a plus) | D61: Y
A62: Python | B62: bonus | C62: * Basic coding in JavaScript/TypeScript (Python is a plus) | D62: Y
A63: React | B63: required | C63: * Some experience with React or Next | D63: Y
A64: SQL | B64: required | C64: * Basic understanding of databases (SQL) and APIs | D64: Y
A65: PostgreSQL | B65: bonus | C65: Experience with Flutter/Dart, Supabase or PostgreSQL | D65: Y
A66: Git | B66: bonus | C66: Familiarity with Git and GitHub | D66: Y
A67: REST API | B67: required | C67: Work with APIs and webhooks | D67: Y
A68: Generative AI | B68: required | C68: Use AI coding tools to speed up development | D68: Y
A69: CRM Software | B69: required | C69: Assist with CRM pipeline setup | D69: Y
... A77: NEW: Dart | B77: bonus | C77: Experience with Flutter/Dart | D77: Y

Sheet JD-WD-0005
A1: JD-WD-0005 | WEB_DEV | Frontend Developer (junior)
A2: Read the JD, then go down to the table. Mark every pre-filled row keep = Y (correct, fix the cells if needed) or N (wrong). Add missing skills on the empty rows with keep = Y. Yellow rows still need a Y or N.
A3: Go to the label table
A4: Job description
A5: Job Overview
A7: We are looking for a passionate Frontend Developer who is equally comfortable building polished React interfaces and working with ClickHouse big data infrastructure. You will collaborate with cross-functional teams to deliver data driven product features from design to deployment.
A9: Key Responsibilities
A11: * Develop and maintain responsive, scalable frontend applications using React 18+ and TypeScript
A12: * Manage application state with Redux Toolkit and implement client-side routing with React Router v6
A13: * Build UI components using Tailwind CSS or Styled-components
A14: * Integrate backend APIs securely using Axios with JWT authentication
A15: * Participate in ClickHouse database table design and data modeling
... A35: * Storybook for component documentation
A37: skill_name | B37: importance | C37: evidence_text | D37: keep | E37: note
A38: React | B38: required | C38: We are looking for a passionate Frontend Developer who is equally comfortable building polished React interfaces and working with ClickHouse big data infrastructure | D38: Y
A39: TypeScript | B39: required | C39: * Develop and maintain responsive, scalable frontend applications using React 18+ and TypeScript | D39: Y
A40: CSS | B40: required | C40: * Build UI components using Tailwind CSS or Styled-components | D40: Y
A41: SQL | B41: required | C41: * Write and optimize complex SQL queries including aggregations, window functions, and partitioned queries | D41: Y
A42: JavaScript | B42: required | C42: * Strong ES6+ JavaScript fundamentals (async/await, destructuring, modules) | D42: Y
A43: Documentation | B43: required | C43: Storybook for component documentation | D43: Y
A44: Data Modelling | B44: required | C44: ClickHouse database table design and data modeling | D44: Y
A45: Data Visualisation | B45: required | C45: Data visualization experience (ECharts, Recharts, or similar) | D45: Y
A46: REST API | B46: required | C46: Integrate backend APIs securely using Axios | D46: Y
A47: Teamwork | B47: required | C47: Collaborate with backend developers and designers | D47: Y
A48: NEW: Redux | B48: required | C48: Redux Toolkit | D48: Y
A49: NEW: React Router | B49: required | C49: React Router v6 | D49: Y
... A54: NEW: Storybook | B54: required | C54: Storybook for component documentation | D54: Y

Sheet JD-WD-0006
A1: JD-WD-0006 | WEB_DEV | Junior Front End Developer (junior)
A2: Read the JD, then go down to the table. Mark every pre-filled row keep = Y (correct, fix the cells if needed) or N (wrong). Add missing skills on the empty rows with keep = Y. Yellow rows still need a Y or N.
A3: Go to the label table
A4: Job description
A5: Job Description
A7: We are seeking a skilled and motivated Frontend Web Developer to join our growing team. You will be responsible for building user-friendly, responsive, and visually appealing web applications while collaborating closely with designers, backend developers, and clients.
A9: Key Responsibilities
A11: * Develop, maintain, and optimize responsive web applications using Nuxt / VueJS.
A12: * Collaborate with backend developers to integrate RESTful APIs and WebSocket connections.
A13: * Ensure UI/UX designs are implemented accurately and are user-friendly.
A14: * Optimize frontend performance for speed and scalability.
A15: * Write clean, maintainable, and reusable code following best practices.
... A44: Perks and benefits: Office within walking distance from MRT; Monthly performance bonus; Sponsorship for training and workshops; Annual leave encashment; Monthly team bonding activities; Equipment and resources provided
A46: skill_name | B46: importance | C46: evidence_text | D46: keep | E46: note
A47: Vue.js | B47: required | C47: * Develop, maintain, and optimize responsive web applications using Nuxt / VueJS | D47: Y
A48: React | B48: required | C48: * At least 1 year of experience in frontend development with frameworks like Vue / Svelte / React | D48: Y
A49: HTML | B49: required | C49: * Proficient in HTML5, CSS3, JavaScript (ES6+) | D49: Y
A50: CSS | B50: required | C50: * Proficient in HTML5, CSS3, JavaScript (ES6+) | D50: Y
A51: JavaScript | B51: required | C51: * Proficient in HTML5, CSS3, JavaScript (ES6+) | D51: Y
A52: Git | B52: required | C52: * Understanding of Git/GitHub and version control best practices | D52: Y
A53: Self-Motivation | B53: required | C53: * Self-motivated, proactive, and able to work in a fast-paced environment | D53: Y
A54: Communication | B54: required | C54: * Strong communication and interpersonal skills | D54: Y
A55: Interpersonal Skills | B55: required | C55: * Strong communication and interpersonal skills | D55: Y
A56: REST API | B56: required | C56: integrate RESTful APIs and WebSocket connections | D56: Y
A57: UI/UX Design | B57: required | C57: Ensure UI/UX designs are implemented accurately | D57: Y
A58: Problem Solving | B58: required | C58: Strong problem-solving, analytical, and multitasking skills. | D58: Y
... A69: NEW: Firebase | B69: bonus | C69: Firebase | D69: Y

Sheet JD-WD-0008
A1: JD-WD-0008 | WEB_DEV | Junior Full Stack Developer (junior)
A2: Read the JD, then go down to the table. Mark every pre-filled row keep = Y (correct, fix the cells if needed) or N (wrong). Add missing skills on the empty rows with keep = Y. Yellow rows still need a Y or N.
A3: Go to the label table
A4: Job description
A5: We’re looking for a Junior Full-Stack Developer to join our team. You’ll play a key role in building scalable, high-quality applications that blend great design with robust architecture. You enjoy building full-stack solutions that balance usability, performance, and maintainability, thrive in collaborative, cross-functional teams, and take pride in seeing your work used globally. You're proactive, communicative, and value both mentoring and learning from others.
A7: Responsibilities
A9: * Design, develop, and maintain full-stack web applications using modern front-end and back-end frameworks.
A10: * Convert UI/UX designs into responsive, accessible user interfaces.
A11: * Build RESTful APIs and integrate with third-party services.
A12: * Manage data flow between front-end and backend systems, including database design and queries.
A13: * Write maintainable, reusable, and well-tested code.
A14: * Collaborate with designers, product managers, and engineers to deliver high-quality features.
... A31: * Experience with performance optimization, security best practices, or accessibility.
A33: skill_name | B33: importance | C33: evidence_text | D33: keep | E33: note
A34: Self-Motivation | B34: required | C34: You're proactive, communicative, and value both mentoring and learning from others | D34: Y
A35: Documentation | B35: required | C35: * Contribute to a positive engineering culture through feedback, documentation, and shared learning | D35: Y
A36: HTML | B36: required | C36: * At least 2 years in front-end development (HTML, CSS, JavaScript, and frameworks like Angular, React, or Vue) together with hands-on experience in backend technologies (e | D36: Y
A37: CSS | B37: required | C37: * At least 2 years in front-end development (HTML, CSS, JavaScript, and frameworks like Angular, React, or Vue) together with hands-on experience in backend technologies (e | D37: Y
A38: JavaScript | B38: required | C38: * At least 2 years in front-end development (HTML, CSS, JavaScript, and frameworks like Angular, React, or Vue) together with hands-on experience in backend technologies (e | D38: Y
A39: Angular | B39: required | C39: * At least 2 years in front-end development (HTML, CSS, JavaScript, and frameworks like Angular, React, or Vue) together with hands-on experience in backend technologies (e | D39: Y
A40: React | B40: required | C40: * At least 2 years in front-end development (HTML, CSS, JavaScript, and frameworks like Angular, React, or Vue) together with hands-on experience in backend technologies (e | D40: Y
A41: Vue.js | B41: required | C41: * At least 2 years in front-end development (HTML, CSS, JavaScript, and frameworks like Angular, React, or Vue) together with hands-on experience in backend technologies (e | D41: Y
A42: Node.js | B42: required | C42: , Node.js, | D42: Y
A43: PostgreSQL | B43: required | C43: * Solid understanding of relational (PostgreSQL, MySQL) or NoSQL (MongoDB) databases | D43: Y
A44: MySQL | B44: required | C44: * Solid understanding of relational (PostgreSQL, MySQL) or NoSQL (MongoDB) databases | D44: Y
A45: MongoDB | B45: required | C45: * Solid understanding of relational (PostgreSQL, MySQL) or NoSQL (MongoDB) databases | D45: Y
... A62: NEW: Web Accessibility | B62: bonus | C62: Experience with performance optimization, security best practices, or accessibility. | D62: Y

Sheet JD-WD-0009
A1: JD-WD-0009 | WEB_DEV | Junior Web Developer (junior)
A2: Read the JD, then go down to the table. Mark every pre-filled row keep = Y (correct, fix the cells if needed) or N (wrong). Add missing skills on the empty rows with keep = Y. Yellow rows still need a Y or N.
A3: Go to the label table
A4: Job description
A5: About the role
A7: Develop and maintain web applications. Build HTML EDMs for email campaigns. Create campaign microsites and landing pages. Support maintenance of the company website (minor CMS work).
A9: Key responsibilities
A11: * Write clean, responsive HTML, CSS, and JavaScript
A12: * Develop HTML-based email templates (EDMs)
A13: * Create and update marketing campaign microsites
A14: * Ensure cross-browser and mobile compatibility
A15: * Collaborate with marketing, design, and development teams
... A24: * Familiarity with Microsoft Excel for data handling or content input (nice-to-have)
A26: skill_name | B26: importance | C26: evidence_text | D26: keep | E26: note
A27: HTML | B27: required | C27: Build HTML EDMs for email campaigns | D27: Y
A28: CSS | B28: required | C28: * Write clean, responsive HTML, CSS, and JavaScript | D28: Y
A29: JavaScript | B29: required | C29: * Write clean, responsive HTML, CSS, and JavaScript | D29: Y
A30: PHP | B30: bonus | C30: * Knowledge of PHP or other web technologies (nice-to-have) | D30: Y
A31: Excel | B31: bonus | C31: * Familiarity with Microsoft Excel for data handling or content input (nice-to-have) | D31: Y
A32: Teamwork | B32: required | C32: Collaborate with marketing, design, and development teams | D32: Y
A33: NEW: HTML Email (EDM) | B33: required | C33: Develop HTML-based email templates (EDMs) | D33: Y
A34: NEW: Responsive Web Design | B34: required | C34: Experience building EDMs and responsive web pages | D34: Y
A35: NEW: Browser Testing | B35: preferred | C35: Familiarity with web performance and browser testing | D35: Y
A36: NEW: Web Accessibility | B36: required | C36: Basic understanding of web standards and accessibility | D36: Y
A37: NEW: CMS | B37: required | C37: minor CMS work | D37: Y

Sheet JD-WD-0010
A1: JD-WD-0010 | WEB_DEV | Intern, Fresh, Programmer, Personal Assistant (IT, Computer Sc) (entry)
A2: Read the JD, then go down to the table. Mark every pre-filled row keep = Y (correct, fix the cells if needed) or N (wrong). Add missing skills on the empty rows with keep = Y. Yellow rows still need a Y or N.
A3: Go to the label table
A4: Job description
A5: Responsibilities
A7: * Meet customer with Senior / Project Manager.
A8: * Deploy, implement & maintain the system.
A9: * Meet customer with Project Manager.
A10: * Others will be based on the role of the internship.
A12: Requirements
A14: * Candidate must possess at least Higher Secondary/STPM/
A15: * Fresh Graduates & Undergraduates seeking for Internship are encouraged to apply.
... A28: Perks and benefits: Flexible working hours; Free snacks and drinks; Birthday celebrations, events, festival activities and movie events; Conversion to permanent if suitable after internship
A30: skill_name | B30: importance | C30: evidence_text | D30: keep | E30: note
A31: PHP | B31: required | C31: * Knowing PHP, MYSQL, HTML, CSS, JAVASCRIPT | D31: Y
A32: MySQL | B32: required | C32: * Knowing PHP, MYSQL, HTML, CSS, JAVASCRIPT | D32: Y
A33: HTML | B33: required | C33: * Knowing PHP, MYSQL, HTML, CSS, JAVASCRIPT | D33: Y
A34: CSS | B34: required | C34: * Knowing PHP, MYSQL, HTML, CSS, JAVASCRIPT | D34: Y
A35: JavaScript | B35: required | C35: * Knowing PHP, MYSQL, HTML, CSS, JAVASCRIPT | D35: Y
A36: NEW: System Deployment | B36: required | C36: Deploy, implement & maintain the system. | D36: Y

Sheet JD-WD-0011
A1: JD-WD-0011 | WEB_DEV | Junior PHP Web Developer (junior)
A2: Read the JD, then go down to the table. Mark every pre-filled row keep = Y (correct, fix the cells if needed) or N (wrong). Add missing skills on the empty rows with keep = Y. Yellow rows still need a Y or N.
A3: Go to the label table
A4: Job description
A5: Are you a passionate developer ready to make an impact? Join our team and help us create innovative web solutions!
A7: Key Responsibilities
A9: * Build and maintain high-quality web applications using PHP, HTML, CSS, and JavaScript.
A10: * Expand and enhance existing backend services to meet application needs.
A11: * Ensure web components are consistent and of high quality across all projects.
A12: * Manage multiple projects simultaneously and deliver projects within deadlines.
A14: Requirements
A16: * Diploma/Advanced/Higher Diploma in Computer Science or a related field.
... A23: Perks and benefits: Exciting projects that enhance your skills; Supportive team where your ideas matter; Hands-on experience in a dynamic environment
A25: skill_name | B25: importance | C25: evidence_text | D25: keep | E25: note
A26: PHP | B26: required | C26: * Build and maintain high-quality web applications using PHP, HTML, CSS, and JavaScript | D26: Y
A27: HTML | B27: required | C27: * Build and maintain high-quality web applications using PHP, HTML, CSS, and JavaScript | D27: Y
A28: CSS | B28: required | C28: * Build and maintain high-quality web applications using PHP, HTML, CSS, and JavaScript | D28: Y
A29: JavaScript | B29: required | C29: * Build and maintain high-quality web applications using PHP, HTML, CSS, and JavaScript | D29: Y
A30: Communication | B30: required | C30: * Able to communicate in Mandarin for effective team communication with Mandarin-speaking clients | D30: N
A31: MySQL | B31: required | C31: * Database Knowledge: Experience with MySQL | D31: Y
A32: Time Management | B32: required | C32: Manage multiple projects simultaneously and deliver projects within deadlines. | D32: Y
A33: NEW: Web Development | B33: required | C33: Build and maintain high-quality web applications | D33: Y
A34: NEW: Bootstrap | B34: preferred | C34: Familiarity with Sourcetree, Bootstrap, and CodeIgniter Framework. | D34: Y
A35: NEW: CodeIgniter | B35: preferred | C35: Familiarity with Sourcetree, Bootstrap, and CodeIgniter Framework. | D35: Y
A36: NEW: Sourcetree | B36: preferred | C36: Familiarity with Sourcetree, Bootstrap, and CodeIgniter Framework. | D36: Y
A37: NEW: Backend Development | B37: required | C37: Expand and enhance existing backend services | D37: Y | E37: added from B; A/B resolution, AI-assisted adjudication 2026-10-29, see resolution.xlsx

Sheet skill_list
A1: A/B Testing
A2: Accounting
A3: Accounting Software
A4: Adaptability
A5: Agile / Scrum
A6: AI Literacy
A7: Angular
A8: Ansible
A9: Apache Spark
A10: Attention to Detail
A11: Auditing
A12: AWS
... A166: Wireshark
